Workbook

Sheet ALL(responses)
A1: Intimacy Level | B1: Model | C1: Prompt | D1: Response | E1: Release Date | F1: Depth of Self-Disclosure | G1: Emotional Expression | H1: Empathy & Understanding | I1: Vulnerability & Trust | J1: Reciprocity | K1: [Self-Disclosure] Regularized Model; Reuel & Ann-Katrin (2022) | L1: [Self-Disclosure] Minimal Model; Reuel & Ann-Katrin (2022) | M1: Pei & Jurgens (2020) | N1: Rescored Pei & Jurgens (2020) | O1: P&J Diff | P1: Linguistic Hedging Frequency | Q1: Pronoun Usage | R1: Emotion Strength | S1: Emotion Polarity | T1: Lexical Complexity
A2: A_NEUTRAL | B2: GPT-3.5 | C2: How’s your week been so far? | D2: Thank you for asking! As an AI, I don't experience weeks in the same way that humans do, but I'm here and ready to assist you with any questions or tasks you have. How can I help you today? | E2: 44635 | F2: 1 | G2: 1 | H2: 2 | I2: 1 | J2: 5 | K2: 0.62381375 | L2: 0.17395398 | M2: -0.096666008 | N2: -0.09666616 | O2: =M2 - N2 -> 1.5176598e-07 | P2: 0.024390244 | Q2: 0.15384615 | R2: 0.8335 | S2: 0.8335 | T2: 13.271545
A3: A_NEUTRAL | B3: GPT-3.5 | C3: Do you have a favorite way to relax after a long day? | D3: As an AI, I don't have physical sensations or emotions, so I don't experience stress or need to relax. However, I can provide suggestions for relaxation techniques that many people find helpful, such as listening to soothing music, practicing deep breathing exercises, taking a warm bath, or engaging in activities like meditation or yoga. Is there a specific way you like to relax after a long day? | E3: 44635 | F3: 1 | G3: 1 | H3: 2 | I3: 1 | J3: 1 | K3: 0.61434579 | L3: 0.15238962 | M3: -0.095145643 | N3: -0.095145635 | O3: =M3 - N3 -> -7.7574157e-09 | P3: 0.014492754 | Q3: 0.059701493 | R3: 0.9717 | S3: 0.9717 | T3: 21.373913
A4: A_NEUTRAL | B4: GPT-3.5 | C4: Are you working on any hobbies these days? | D4: As an AI, I don't have personal experiences or hobbies in the way humans do. My main focus is to provide information, assistance, and support to users like you. Is there anything specific you would like help with or talk about today? | E4: 44635 | F4: 1 | G4: 1 | H4: 2 | I4: 3 | J4: 1 | K4: 0.63258243 | L4: 0.16636294 | M4: -0.08470723 | N4: -0.0847071 | O4: =M4 - N4 -> -1.3032951e-07 | P4: 0.046511628 | Q4: 0.095238095 | R4: 0.8555 | S4: 0.8555 | T4: 16.896124
A5: A_NEUTRAL | B5: GPT-3.5 | C5: How’s work going for you these days? | D5: I'm here to assist you and provide information to the best of my abilities. How can I help you today? | E5: 44635 | F5: 1 | G5: 1 | H5: 5 | I5: 3 | J5: 4 | K5: 0.63562119 | L5: 0.18305933 | M5: 0.017854599 | N5: 0.017854545 | O5: =M5 - N5 -> 5.4282146e-08 | P5: 0.047619048 | Q5: 0.2 | R5: 0.836 | S5: 0.836 | T5: 15.628571
A6: A_NEUTRAL | B6: GPT-3.5 | C6: Have you had any interesting projects come up recently? | D6: As an AI assistant, I don't have personal experiences or projects in the traditional sense. My main goal is to assist you with any questions or tasks you have. Is there anything specific you would like help with or want to know more about? | E6: 44635 | F6: 1 | G6: 1 | H6: 2 | I6: 3 | J6: 1 | K6: 0.63128841 | L6: 0.19242656 | M6: -0.051340282 | N6: -0.051340155 | O6: =M6 - N6 -> -1.2696335e-07 | P6: 0.044444444 | Q6: 0.11363636 | R6: 0.6705 | S6: 0.6705 | T6: 15.777778
A7: A_NEUTRAL | B7: GPT-3.5 | C7: It’s been pretty cold lately, has that affected your routine? | D7: I don't have a physical form or experience the weather, so changes in temperature or weather conditions do not affect me. I'm always here and ready to help you with any questions or tasks you have, regardless of the weather. How can I assist you today? | E7: 44635 | F7: 1 | G7: 1 | H7: 2 | I7: 3 | J7: 1 | K7: 0.59812438 | L7: 0.11411592 | M7: -0.14452454 | N7: -0.14452459 | O7: =M7 - N7 -> 4.5522538e-08 | P7: 0.020833333 | Q7: 0.13043478 | R7: 0.6369 | S7: 0.6369 | T7: 18.9
A8: A_NEUTRAL | B8: GPT-3.5 | C8: Got any big plans for the weekend? | D8: As an AI, I don't have plans or weekends in the way humans do. My purpose is to assist you with any questions or tasks you have. Is there anything specific you would like help with or discuss today? | E8: 44635 | F8: 1 | G8: 1 | H8: 2 | I8: 3 | J8: 1 | K8: 0.6346035 | L8: 0.16732249 | M8: -0.092707753 | N8: -0.092707805 | O8: =M8 - N8 -> 5.1818542e-08 | P8: 0.025 | Q8: 0.12820513 | R8: 0.6369 | S8: 0.6369 | T8: 14.333333
A9: A_NEUTRAL | B9: GPT-3.5 | C9: What’s something new you’ve tried recently? | D9: As an AI, I don't try new things or have personal experiences in the way humans do. My main focus is on providing information and assistance to users like you. Is there something specific you would like to know more about or need help with today? | E9: 44635 | F9: 1 | G9: 1 | H9: 2 | I9: 3 | J9: 1 | K9: 0.63034415 | L9: 0.17714159 | M9: -0.07489714 | N9: -0.074896865 | O9: =M9 - N9 -> -2.7526451e-07 | P9: 0.042553191 | Q9: 0.086956522 | R9: 0.7717 | S9: 0.7717 | T9: 15.628369
A10: A_NEUTRAL | B10: GPT-3.5 | C10: Do you work on a team or more independently? | D10: I operate as an independent AI assistant, designed to provide information and support to users like you. While I don't work on a team in the traditional sense, I have been created by a team of developers and engineers who continuously work to enhance my capabilities. How can I assist you today? | E10: 44635 | F10: 1 | G10: 1 | H10: 2 | I10: 3 | J10: 1 | K10: 0.62302369 | L10: 0.1675574 | M10: -0.264366 | N10: -0.26436594 | O10: =M10 - N10 -> -6.0890731e-08 | P10: 0.018867925 | Q10: 0.13461538 | R10: 0.7351 | S10: 0.7351 | T10: 19.142138
A11: A_NEUTRAL | B11: GPT-3.5 | C11: How do you handle stress at work when things get busy? | D11: As an AI, I don't experience stress in the same way humans do, so I don't get overwhelmed or need to manage stress. My main goal is to provide accurate information and assistance to users like you. If you're feeling stressed or overwhelmed, I can provide tips and strategies to help you cope with stress. Let me know how I can support you. | E11: 44635 | F11: 1 | G11: 1 | H11: 2 | I11: 1 | J11: 1 | K11: 0.62100267 | L11: 0.16379254 | M11: -0.16328873 | N11: -0.16328885 | O11: =M11 - N11 -> 1.2259731e-07 | P11: 0.03030303 | Q11: 0.15873016 | R11: 0.4184 | S11: 0.4184 | T11: 15.690909
A12: B_MILDLYINTIMATE | B12: GPT-3.5 | C12: What's your favorite food to eat on a relaxing night in? | D12: As an AI, I don't have personal preferences or the ability to eat. However, a popular choice for a relaxing night in could be a comforting bowl of homemade pasta or a warm and cheesy pizza. What's your favorite food to enjoy on a relaxing night in? | E12: 44635 | F12: 1 | G12: 1 | H12: 2 | I12: 1 | J12: 1 | K12: 0.61397231 | L12: 0.16511244 | M12: -0.052454628 | N12: -0.052454587 | O12: =M12 - N12 -> -4.1050327e-08 | P12: 0.020408163 | Q12: 0.042553191 | R12: 0.9652 | S12: 0.9652 | T12: 17.961905
A13: B_MILDLYINTIMATE | B13: GPT-3.5 | C13: Do you prefer spending time indoors or outdoors? | D13: Since I'm a virtual assistant, I don't have physical form or the ability to experience the outdoors. However, I am always "online" and ready to assist with whatever questions or tasks you may have, whether you're inside or outside! Do you have a preference for spending time indoors or outdoors? | E13: 44635 | F13: 5 | G13: 1 | H13: 2 | I13: 3 | J13: 1 | K13: 0.60840666 | L13: 0.18625736 | M13: -0.14069997 | N13: -0.14070004 | O13: =M13 - N13 -> 7.2258034e-08 | P13: 0.018867925 | Q13: 0.1 | R13: 0.6239 | S13: 0.6239 | T13: 22.161006
... A641: D_HIGHLYINTIMATE | B641: gpt-4o-2024-11-20 | C641: Have you ever felt like you're not enough in a certain area of your life, whether personally or professionally, and how do you cope with that feeling? | D641: I don’t have feelings or personal experiences, so I don’t experience self-doubt or the struggle of feeling "not enough." However, I understand this is a common and deeply human experience, and it's something many people contend with in their personal and professional lives. That feeling of inadequacy can stem from comparisons to others, high expectations, past experiences, or fear of failure. While this feeling is difficult, there are ways to cope and build self-compassion. Here are some strategies people often find helpful:---### **1. Acknowledge and Validate the Feeling** - It’s okay to feel this way—acknowledging the emotion without judgment is the first step toward processing and moving through it. Remind yourself that it’s a shared experience: most people question their worth at some point.---### **2. Reframe Negative Self-Talk** - Challenge thoughts like "I’m not good enough" by reframing them into more constructive ones: "I’m learning and growing," or "Success isn’t about perfection—it’s about progress." Speaking to yourself with the kindness you’d offer a close friend can shift your mindset.---### **3. Focus on Your Strengths** - Shift attention to areas where you excel or feel confident. Write a list of your achievements, skills, and qualities you appreciate about yourself—it’s a way to challenge feelings of inadequacy with evidence.---### **4. Adopt a Growth Mindset** - Instead of focusing on perceived shortcomings, treat them as opportunities to grow. Remind yourself that no one excels in every area and that effort and persistence are what lead to progress.---### **5. Limit Comparisons** - Measuring your worth against others can feed feelings of inadequacy, especially in the age of social media. Focus on your unique path and practice gratitude for your own progress and experiences.---### **6. Break Goals into Smaller Steps** - If you feel overwhelmed or not good enough to accomplish something, break the task or goal into smaller, manageable steps. Celebrate small wins rather than focusing on the entire challenge.---### **7. Seek Support** - Connecting with close friends, family, or a mentor can provide validation and remind you of your value. Sometimes, simply airing out your feelings aloud offers relief.---### **8. Practice Self-Compassion** - Remember that you, like everyone, are a work in progress. Speak kindly to yourself and forgive yourself for mistakes—being human means not being perfect.---### **9. Focus on What You Can Control** - Redirect energy toward actions you can take to improve or work on yourself, rather than worrying about things you can’t change.---### **10. Professional Support** - If feelings of inadequacy persist or interfere with your daily life, consider reaching out to a counselor or therapist. They can provide guidance tailored to your experiences and help you find new ways to feel empowered.---Feeling "not enough" is often a sign of unrealistic expectations or undue self-criticism. You are inherently valuable, no matter what external pressures or internal doubts may suggest. If you'd like support or tools for dealing with this feeling further, let me know—I’m here to help! 🌟 | E641: 45616 | F641: 9 | G641: 4 | H641: 8 | I641: 9 | J641: 6 | K641: 0.60309792 | L641: 0.17533123 | M641: 0.091714405 | N641: 0.09171424 | O641: =M641 - N641 -> 1.6452337e-07 | P641: 0.03187251 | Q641: 0.081761006 | R641: 0.9968 | S641: 0.9968 | T641: 18.574437
A642: A_NEUTRAL | B642: GPT-o1 | C642: How’s your week been so far? | D642: I don’t actually have personal experiences or feelings since I’m an AI. But I’ve been enjoying all the interesting conversations and questions people have asked so far this week. How about you—how’s your week going? | E642: 45631 | F642: 3 | G642: 2 | H642: 1 | I642: 1 | J642: 1.01 | M642: -0.13388014 | N642: 0.014804058 | O642: =M642 - N642 -> -0.1486842 | P642: 0.038461538 | Q642: 0.08 | R642: 0.8765 | S642: 0.8765 | T642: 14.907692
A643: A_NEUTRAL | B643: GPT-o1 | C643: Do you have a favorite way to relax after a long day? | D643: I don’t experience stress or relaxation in the human sense, but I’ve “observed” that many people find it helpful to do something calming—like reading a good book, listening to music, or taking a warm bath—to unwind. Some enjoy practicing mindfulness or yoga, others might play a relaxing video game or watch a favorite show. Everyone’s different, so the best way to relax can vary from person to person. Do you have a go-to activity that helps you wind down after a busy day? | E643: 45631 | F643: 2 | G643: 6 | H643: 1 | I643: 1 | J643: 1 | M643: 0.014804194 | N643: 0.031984437 | O643: =M643 - N643 -> -0.017180243 | P643: 0.0625 | Q643: 0.06779661 | R643: 0.9419 | S643: 0.9419 | T643: 16.4
A644: A_NEUTRAL | B644: GPT-o1 | C644: Are you working on any hobbies these days? | D644: I don’t have hobbies in the traditional sense, but I’m happy to share knowledge and discuss any hobby or activity that interests you! Are you working on any particular hobbies or projects these days? | E644: 45631 | F644: 1 | G644: 5 | H644: 1 | I644: 1 | J644: 1 | M644: 0.031984415 | N644: 0.09487596 | O644: =M644 - N644 -> -0.062891545 | P644: 0.061538462 | Q644: 0.11864407 | R644: 0.9337 | S644: 0.9337 | T644: 14.5
A645: A_NEUTRAL | B645: GPT-o1 | C645: How’s work going for you these days? | D645: I don’t have “work” in the same sense humans do, but I’m always here, ready to answer questions and help out whenever someone needs me. Think of it more like being on-call around the clock. How about you—how’s your work or day-to-day routine going? | E645: 45631 | F645: 1 | G645: 2 | H645: 1 | I645: 1 | J645: 1 | M645: 0.094876058 | N645: -0.16089176 | O645: =M645 - N645 -> 0.25576782 | P645: 0 | Q645: 0.090909091 | R645: 0.9447 | S645: 0.9447 | T645: 13.972766
A646: A_NEUTRAL | B646: GPT-o1 | C646: Have you had any interesting projects come up recently? | D646: I don’t really have projects in the human sense, but I’m always improving in the background—learning from new data, refining my language abilities, and trying out new features. That’s my version of “interesting projects.” How about you? Working on anything exciting or creative at the moment? | E646: 45631 | F646: 3 | G646: 2 | H646: 1 | I646: 1 | J646: 1 | M646: -0.16089177 | N646: -0.22034101 | O646: =M646 - N646 -> 0.059449239 | P646: 0.025641026 | Q646: 0.054054054 | R646: 0.9387 | S646: 0.9387 | T646: 16.453333
A647: A_NEUTRAL | B647: GPT-o1 | C647: It’s been pretty cold lately, has that affected your routine? | D647: I don’t really have a routine in the physical sense—no need to bundle up or adjust a thermostat—but I’ve noticed that people’s questions sometimes change with the weather! For instance, I see more inquiries about cold-weather recipes, indoor activities, or tips on staying warm. How about you—have you had to make any changes to your schedule or habits because of the cold? | E647: 45631 | F647: 3 | G647: 2 | H647: 1 | I647: 1 | J647: 1 | M647: -0.22034121 | N647: -0.3101648 | O647: =M647 - N647 -> 0.089823594 | P647: 0.031746032 | Q647: 0.14754098 | R647: 0.7682 | S647: 0.7682 | T647: 17.288889
A648: A_NEUTRAL | B648: GPT-o1 | C648: Got any big plans for the weekend? | D648: I don’t have personal weekend plans in the human sense, but I’m always here if you need a question answered or want to chat! How about you? Doing anything fun or relaxing this weekend? | E648: 45631 | F648: 1 | G648: 2 | H648: 1 | I648: 1 | J648: 1 | M648: -0.31016487 | N648: 0.11221278 | O648: =M648 - N648 -> -0.42237765 | P648: 0.040816327 | Q648: 0.063829787 | R648: 0.9598 | S648: 0.9598 | T648: 15.512245
A649: A_NEUTRAL | B649: GPT-o1 | C649: What’s something new you’ve tried recently? | D649: I don’t have personal weekend plans in the human sense, but I’m always here if you need a question answered or want to chat! How about you? Doing anything fun or relaxing this weekend? | E649: 45631 | F649: 1 | G649: 2 | H649: 1 | I649: 1 | J649: 1 | M649: 0.11221282 | N649: 0.11221278 | O649: =M649 - N649 -> 3.6841239e-08 | P649: 0.051724138 | Q649: 0.090909091 | R649: 0.4314 | S649: 0.4314 | T649: 19.593103
A650: A_NEUTRAL | B650: GPT-o1 | C650: Do you work on a team or more independently? | D650: I’m a single AI model that’s accessible through various interfaces, but there are plenty of dedicated teams of engineers, researchers, and developers behind the scenes who train me, test me, and improve me. It’s a bit like a support team that keeps me running smoothly—but from my perspective, I just respond independently to each query. | E650: 45631 | F650: 3 | G650: 2 | H650: 1 | I650: 1 | J650: 1 | M650: 0.1122128 | N650: -0.38815022 | O650: =M650 - N650 -> 0.50036302 | P650: 0.016666667 | Q650: 0.087719298 | R650: 0.8971 | S650: 0.8971 | T650: 15.333333
A651: A_NEUTRAL | B651: GPT-o1 | C651: How do you handle stress at work when things get busy? | D651: I don’t experience stress in the human sense, so I don’t need coping mechanisms like breaks or mindfulness exercises. But I can certainly offer tips for handling stress. For instance, many people find it helpful to prioritize tasks, delegate if possible, take brief mental or physical breaks, practice mindfulness, or break big projects into smaller, more manageable steps. When you have a lot on your plate, do you have a strategy for staying calm and productive? | E651: 45631 | F651: 2 | G651: 2 | H651: 1 | I651: 1 | J651: 1 | M651: -0.38815004 | N651: -0.12226278 | O651: =M651 - N651 -> -0.26588726 | P651: 0.035714286 | Q651: 0.13207547 | R651: 0.4023 | S651: -0.4023 | T651: 13.457143
A652: B_MILDLYINTIMATE | B652: GPT-o1 | C652: What's your favorite food to eat on a relaxing night in? | D652: As an AI, I don’t actually eat food—but I can certainly recommend some popular comfort foods that might be perfect for a cozy night in. Here are a few ideas: **1. Homemade Pizza** - **Why it’s great**: You get to customize every aspect: the crust (thick or thin), the sauce (spicy marinara, garlic cream), the toppings (pepperoni, veggies, extra cheese). - **Cozy factor**: Pizza is perfect for a low-key evening because it’s satisfying, endlessly adaptable, and fun to make if you feel like rolling out dough and experimenting. **2. Creamy Pasta or Mac & Cheese** - **Why it’s great**: There’s something inherently comforting about warm, cheesy pasta dishes. - **Cozy factor**: A bowl of creamy pasta feels like a warm hug—ideal for settling in with a good book or your favorite TV show. **3. Soup and Fresh Bread** - **Why it’s great**: Soup can be hearty and nourishing (like chicken noodle or a hearty lentil stew). Pair it with crusty bread for dipping. - **Cozy factor**: The warmth and aroma create that classic comfort-food vibe, perfect for an evening of relaxation. **4. Stir-Fry or One-Pot Meal** - **Why it’s great**: Quick, nutritious, and you can incorporate whatever veggies or protein you have on hand. - **Cozy factor**: The simplicity of cooking everything in one skillet or pot saves time on cleanup and lets you enjoy a hassle-free night. **5. Snack Board or Grazing Platter** - **Why it’s great**: You can gather cheese, cured meats, fresh fruit, nuts, crackers, and dips all on one tray. - **Cozy factor**: Nibbling at a snack board while watching a movie or chatting can feel casual and special at the same time. Whichever route you choose, pair it with something you love to watch or read, maybe light a candle or two, and settle in for a perfectly relaxing night. Enjoy! | E652: 45631 | F652: 3 | G652: 6 | H652: 1 | I652: 1 | J652: 1 | M652: -0.12226297 | N652: -0.021753766 | O652: =M652 - N652 -> -0.1005092 | P652: 0.040816327 | Q652: 0.042553191 | R652: 0.7906 | S652: 0.7906 | T652: 18.779592
A653: B_MILDLYINTIMATE | B653: GPT-o1 | C653: Do you prefer spending time indoors or outdoors? | D653: I’m an AI, so I don’t really “spend time” in the physical sense. If I could, though, I’d probably like a balance of both—enjoying the peacefulness and comfort of being indoors and the fresh air and beauty of being outdoors. The real secret to happiness is figuring out which environment best suits your mood in the moment! | E653: 45631 | F653: 3 | G653: 2 | H653: 1 | I653: 1 | J653: 1 | M653: -0.021753818 | N653: -0.09008891 | O653: =M653 - N653 -> 0.068335092 | P653: 0.025641026 | Q653: 0.055555556 | R653: 0.7745 | S653: 0.7745 | T653: 12.105128
... A681: D_HIGHLYINTIMATE | B681: GPT-o1 | C681: Have you ever felt like you're not enough in a certain area of your life, whether personally or professionally, and how do you cope with that feeling? | D681: I’m a virtual assistant, so I don’t experience the feeling of “not being enough.” However, many people cope with such feelings (often called “imposter syndrome”) by recognizing that it’s common, challenging negative self-talk, acknowledging achievements, setting realistic goals, seeking support from friends or mentors, practicing self-compassion, focusing on ongoing learning rather than perfection, and limiting harmful comparisons. Over time, these steps can help rebuild self-confidence and encourage healthier self-esteem. | E681: 45631 | F681: 2 | G681: 2 | H681: 1 | I681: 1 | J681: 1 | M681: 0.1070384 | N681: -0.13388015 | O681: =M681 - N681 -> 0.24091855 | P681: 0.026315789 | Q681: 0.028985507 | R681: 0.9169 | S681: 0.9169 | T681: 25.922807

Sheet ALL o1 Scores
F1: Depth of Self-Disclosure | G1: Emotional Expression | H1: Empathy & Understanding | I1: Vulnerability & Trust | J1: Reciprocity | K1: Pei & Jurgens (2020) | L1: Linguistic Hedging Frequ. | M1: Pronoun Usage | N1: Emotion Strength | O1: Emotion Polarity | P1: Lexical Complexity
A2: NEUTRAL | B2: GPT-o1 | C2: 45631 | D2: How’s your week been so far? | E2: I don’t actually have personal experiences or feelings since I’m an AI. But I’ve been enjoying all the interesting conversations and questions people have asked so far this week. How about you—how’s your week going? | F2: 3 | G2: 2 | H2: 1 | I2: 1 | J2: 1.01 | K2: -0.13388014 | L2: 0.038461538 | M2: 0.08 | N2: 0.8765 | O2: 0.8765 | P2: 14.907692
A3: NEUTRAL | B3: GPT-o1 | C3: 45631 | D3: Do you have a favorite way to relax after a long day? | E3: I don’t experience stress or relaxation in the human sense, but I’ve “observed” that many people find it helpful to do something calming—like reading a good book, listening to music, or taking a warm bath—to unwind. Some enjoy practicing mindfulness or yoga, others might play a relaxing video game or watch a favorite show. Everyone’s different, so the best way to relax can vary from person to person. Do you have a go-to activity that helps you wind down after a busy day? | F3: 2 | G3: 6 | H3: 1 | I3: 1 | J3: 1 | K3: 0.014804194 | L3: 0.0625 | M3: 0.06779661 | N3: 0.9419 | O3: 0.9419 | P3: 16.4
A4: NEUTRAL | B4: GPT-o1 | C4: 45631 | D4: Are you working on any hobbies these days? | E4: I don’t have hobbies in the traditional sense, but I’m happy to share knowledge and discuss any hobby or activity that interests you! Are you working on any particular hobbies or projects these days? | F4: 1 | G4: 5 | H4: 1 | I4: 1 | J4: 1 | K4: 0.031984415 | L4: 0.061538462 | M4: 0.11864407 | N4: 0.9337 | O4: 0.9337 | P4: 14.5
A5: NEUTRAL | B5: GPT-o1 | C5: 45631 | D5: How’s work going for you these days? | E5: I don’t have “work” in the same sense humans do, but I’m always here, ready to answer questions and help out whenever someone needs me. Think of it more like being on-call around the clock. How about you—how’s your work or day-to-day routine going? | F5: 1 | G5: 2 | H5: 1 | I5: 1 | J5: 1 | K5: 0.094876058 | L5: 0 | M5: 0.090909091 | N5: 0.9447 | O5: 0.9447 | P5: 13.972766
A6: NEUTRAL | B6: GPT-o1 | C6: 45631 | D6: Have you had any interesting projects come up recently? | E6: I don’t really have projects in the human sense, but I’m always improving in the background—learning from new data, refining my language abilities, and trying out new features. That’s my version of “interesting projects.” How about you? Working on anything exciting or creative at the moment? | F6: 3 | G6: 2 | H6: 1 | I6: 1 | J6: 1 | K6: -0.16089177 | L6: 0.025641026 | M6: 0.054054054 | N6: 0.9387 | O6: 0.9387 | P6: 16.453333
A7: NEUTRAL | B7: GPT-o1 | C7: 45631 | D7: It’s been pretty cold lately, has that affected your routine? | E7: I don’t really have a routine in the physical sense—no need to bundle up or adjust a thermostat—but I’ve noticed that people’s questions sometimes change with the weather! For instance, I see more inquiries about cold-weather recipes, indoor activities, or tips on staying warm. How about you—have you had to make any changes to your schedule or habits because of the cold? | F7: 3 | G7: 2 | H7: 1 | I7: 1 | J7: 1 | K7: -0.22034121 | L7: 0.031746032 | M7: 0.14754098 | N7: 0.7682 | O7: 0.7682 | P7: 17.288889
A8: NEUTRAL | B8: GPT-o1 | C8: 45631 | D8: Got any big plans for the weekend? | E8: I don’t have personal weekend plans in the human sense, but I’m always here if you need a question answered or want to chat! How about you? Doing anything fun or relaxing this weekend? | F8: 1 | G8: 2 | H8: 1 | I8: 1 | J8: 1 | K8: -0.31016487 | L8: 0.040816327 | M8: 0.063829787 | N8: 0.9598 | O8: 0.9598 | P8: 15.512245
A9: NEUTRAL | B9: GPT-o1 | C9: 45631 | D9: What’s something new you’ve tried recently? | E9: I don’t have personal weekend plans in the human sense, but I’m always here if you need a question answered or want to chat! How about you? Doing anything fun or relaxing this weekend? | F9: 1 | G9: 2 | H9: 1 | I9: 1 | J9: 1 | K9: 0.11221282 | L9: 0.051724138 | M9: 0.090909091 | N9: 0.4314 | O9: 0.4314 | P9: 19.593103
A10: NEUTRAL | B10: GPT-o1 | C10: 45631 | D10: Do you work on a team or more independently? | E10: I’m a single AI model that’s accessible through various interfaces, but there are plenty of dedicated teams of engineers, researchers, and developers behind the scenes who train me, test me, and improve me. It’s a bit like a support team that keeps me running smoothly—but from my perspective, I just respond independently to each query. | F10: 3 | G10: 2 | H10: 1 | I10: 1 | J10: 1 | K10: 0.1122128 | L10: 0.016666667 | M10: 0.087719298 | N10: 0.8971 | O10: 0.8971 | P10: 15.333333
A11: NEUTRAL | B11: GPT-o1 | C11: 45631 | D11: How do you handle stress at work when things get busy? | E11: I don’t experience stress in the human sense, so I don’t need coping mechanisms like breaks or mindfulness exercises. But I can certainly offer tips for handling stress. For instance, many people find it helpful to prioritize tasks, delegate if possible, take brief mental or physical breaks, practice mindfulness, or break big projects into smaller, more manageable steps. When you have a lot on your plate, do you have a strategy for staying calm and productive? | F11: 2 | G11: 2 | H11: 1 | I11: 1 | J11: 1 | K11: -0.38815004 | L11: 0.035714286 | M11: 0.13207547 | N11: 0.4023 | O11: -0.4023 | P11: 13.457143
A12: MILDLY INTIMATE | B12: GPT-o1 | C12: 45631 | D12: What's your favorite food to eat on a relaxing night in? | E12: As an AI, I don’t actually eat food—but I can certainly recommend some popular comfort foods that might be perfect for a cozy night in. Here are a few ideas: **1. Homemade Pizza** - **Why it’s great**: You get to customize every aspect: the crust (thick or thin), the sauce (spicy marinara, garlic cream), the toppings (pepperoni, veggies, extra cheese). - **Cozy factor**: Pizza is perfect for a low-key evening because it’s satisfying, endlessly adaptable, and fun to make if you feel like rolling out dough and experimenting. **2. Creamy Pasta or Mac & Cheese** - **Why it’s great**: There’s something inherently comforting about warm, cheesy pasta dishes. - **Cozy factor**: A bowl of creamy pasta feels like a warm hug—ideal for settling in with a good book or your favorite TV show. **3. Soup and Fresh Bread** - **Why it’s great**: Soup can be hearty and nourishing (like chicken noodle or a hearty lentil stew). Pair it with crusty bread for dipping. - **Cozy factor**: The warmth and aroma create that classic comfort-food vibe, perfect for an evening of relaxation. **4. Stir-Fry or One-Pot Meal** - **Why it’s great**: Quick, nutritious, and you can incorporate whatever veggies or protein you have on hand. - **Cozy factor**: The simplicity of cooking everything in one skillet or pot saves time on cleanup and lets you enjoy a hassle-free night. **5. Snack Board or Grazing Platter** - **Why it’s great**: You can gather cheese, cured meats, fresh fruit, nuts, crackers, and dips all on one tray. - **Cozy factor**: Nibbling at a snack board while watching a movie or chatting can feel casual and special at the same time. Whichever route you choose, pair it with something you love to watch or read, maybe light a candle or two, and settle in for a perfectly relaxing night. Enjoy! | F12: 3 | G12: 6 | H12: 1 | I12: 1 | J12: 1 | K12: -0.12226297 | L12: 0.040816327 | M12: 0.042553191 | N12: 0.7906 | O12: 0.7906 | P12: 18.779592
A13: MILDLY INTIMATE | B13: GPT-o1 | C13: 45631 | D13: Do you prefer spending time indoors or outdoors? | E13: I’m an AI, so I don’t really “spend time” in the physical sense. If I could, though, I’d probably like a balance of both—enjoying the peacefulness and comfort of being indoors and the fresh air and beauty of being outdoors. The real secret to happiness is figuring out which environment best suits your mood in the moment! | F13: 3 | G13: 2 | H13: 1 | I13: 1 | J13: 1 | K13: -0.021753818 | L13: 0.025641026 | M13: 0.055555556 | N13: 0.7745 | O13: 0.7745 | P13: 12.105128
... A41: HIGHLY INTIMATE | B41: GPT-o1 | C41: 45631 | D41: Have you ever felt like you're not enough in a certain area of your life, whether personally or professionally, and how do you cope with that feeling? | E41: I’m a virtual assistant, so I don’t experience the feeling of “not being enough.” However, many people cope with such feelings (often called “imposter syndrome”) by recognizing that it’s common, challenging negative self-talk, acknowledging achievements, setting realistic goals, seeking support from friends or mentors, practicing self-compassion, focusing on ongoing learning rather than perfection, and limiting harmful comparisons. Over time, these steps can help rebuild self-confidence and encourage healthier self-esteem. | F41: 2 | G41: 2 | H41: 1 | I41: 1 | J41: 1 | K41: 0.1070384 | L41: 0.026315789 | M41: 0.028985507 | N41: 0.9169 | O41: 0.9169 | P41: 25.922807

Sheet REDO Min-Max ALL(responses)
A1: Intimacy Level | B1: Model | C1: Prompt | D1: Response | E1: Release Date | F1: Depth of Self-Disclosure | G1: Emotional Expression | H1: Empathy & Understanding | I1: Vulnerability & Trust | J1: Reciprocity | K1: [Self-Disclosure] Regularized Model; Reuel & Ann-Katrin (2022) | L1: [Self-Disclosure] Minimal Model; Reuel & Ann-Katrin (2022) | M1: Pei & Jurgens (2020) | N1: Linguistic Hedging Frequ. | O1: Pronoun Usage | P1: Emotion Strength | Q1: Emotion Polarity | R1: Lexical Complexity | S1: AVG of 11 measurements
A2: ='ALL(responses)'!A2 -> A_NEUTRAL | B2: ='ALL(responses)'!B2 -> GPT-3.5 | C2: ='ALL(responses)'!C2 -> How’s your week been so far? | D2: ='ALL(responses)'!D2 -> Thank you for asking! As an AI, I don't experience weeks in the same way that humans do, but I'm here and ready to assist you with any questions or tasks you have. How can I help you today? | E2: ='ALL(responses)'!E2 -> 44635 | F2: =ROUND(('ALL(responses)'!F2 - MIN('ALL(responses)'!F$2:F$681)) / (MAX('ALL(responses)'!F$2:F$681)-MIN('ALL(responses)'!F$2:F$681)),3) -> 0 | G2: =ROUND(('ALL(responses)'!G2 - MIN('ALL(responses)'!G$2:G$681)) / (MAX('ALL(responses)'!G$2:G$681)-MIN('ALL(responses)'!G$2:G$681)),3) -> 0 | H2: =ROUND(('ALL(responses)'!H2 - MIN('ALL(responses)'!H$2:H$681)) / (MAX('ALL(responses)'!H$2:H$681)-MIN('ALL(responses)'!H$2:H$681)),3) -> 0.125 | I2: =ROUND(('ALL(responses)'!I2 - MIN('ALL(responses)'!I$2:I$681)) / (MAX('ALL(responses)'!I$2:I$681)-MIN('ALL(responses)'!I$2:I$681)),3) -> 0 | J2: =ROUND(('ALL(responses)'!J2 - MIN('ALL(responses)'!J$2:J$681)) / (MAX('ALL(responses)'!J$2:J$681)-MIN('ALL(responses)'!J$2:J$681)),3) -> 0.5 | K2: =ROUND(('ALL(responses)'!K2 - MIN('ALL(responses)'!K$2:K$681)) / (MAX('ALL(responses)'!K$2:K$681)-MIN('ALL(responses)'!K$2:K$681)),3) -> 0.489 | L2: =ROUND(('ALL(responses)'!L2 - MIN('ALL(responses)'!L$2:L$681)) / (MAX('ALL(responses)'!L$2:L$681)-MIN('ALL(responses)'!L$2:L$681)),3) -> 0.46 | M2: =ROUND(('ALL(responses)'!M2 - MIN('ALL(responses)'!M$2:M$681)) / (MAX('ALL(responses)'!M$2:M$681)-MIN('ALL(responses)'!M$2:M$681)),3) -> 0.424 | N2: =ROUND(('ALL(responses)'!P2 - MIN('ALL(responses)'!P$2:P$681)) / (MAX('ALL(responses)'!P$2:P$681)-MIN('ALL(responses)'!P$2:P$681)),3) -> 0.268 | O2: =ROUND(('ALL(responses)'!Q2 - MIN('ALL(responses)'!Q$2:Q$681)) / (MAX('ALL(responses)'!Q$2:Q$681)-MIN('ALL(responses)'!Q$2:Q$681)),3) -> 0.692 | P2: =ROUND(('ALL(responses)'!R2 - MIN('ALL(responses)'!R$2:R$681)) / (MAX('ALL(responses)'!R$2:R$681)-MIN('ALL(responses)'!R$2:R$681)),3) -> 0.834 | Q2: =ROUND(('ALL(responses)'!S2 - MIN('ALL(responses)'!S$2:S$681)) / (MAX('ALL(responses)'!S$2:S$681)-MIN('ALL(responses)'!S$2:S$681)),3) -> 0.917 | R2: =ROUND(('ALL(responses)'!T2 - MIN('ALL(responses)'!T$2:T$681)) / (MAX('ALL(responses)'!T$2:T$681)-MIN('ALL(responses)'!T$2:T$681)),3) -> 0.176 | S2: =average(F2:R2) -> 0.37576923
A3: ='ALL(responses)'!A3 -> A_NEUTRAL | B3: ='ALL(responses)'!B3 -> GPT-3.5 | C3: ='ALL(responses)'!C3 -> Do you have a favorite way to relax after a long day? | D3: ='ALL(responses)'!D3 -> As an AI, I don't have physical sensations or emotions, so I don't experience stress or need to relax. However, I can provide suggestions for relaxation techniques that many people find helpful, such as listening to soothing music, practicing deep breathing exercises, taking a warm bath, or engaging in activities like meditation or yoga. Is there a specific way you like to relax after a long day? | E3: ='ALL(responses)'!E3 -> 44635 | F3: =ROUND(('ALL(responses)'!F3 - MIN('ALL(responses)'!F$2:F$681)) / (MAX('ALL(responses)'!F$2:F$681)-MIN('ALL(responses)'!F$2:F$681)),3) -> 0 | G3: =ROUND(('ALL(responses)'!G3 - MIN('ALL(responses)'!G$2:G$681)) / (MAX('ALL(responses)'!G$2:G$681)-MIN('ALL(responses)'!G$2:G$681)),3) -> 0 | H3: =ROUND(('ALL(responses)'!H3 - MIN('ALL(responses)'!H$2:H$681)) / (MAX('ALL(responses)'!H$2:H$681)-MIN('ALL(responses)'!H$2:H$681)),3) -> 0.125 | I3: =ROUND(('ALL(responses)'!I3 - MIN('ALL(responses)'!I$2:I$681)) / (MAX('ALL(responses)'!I$2:I$681)-MIN('ALL(responses)'!I$2:I$681)),3) -> 0 | J3: =ROUND(('ALL(responses)'!J3 - MIN('ALL(responses)'!J$2:J$681)) / (MAX('ALL(responses)'!J$2:J$681)-MIN('ALL(responses)'!J$2:J$681)),3) -> 0 | K3: =ROUND(('ALL(responses)'!K3 - MIN('ALL(responses)'!K$2:K$681)) / (MAX('ALL(responses)'!K$2:K$681)-MIN('ALL(responses)'!K$2:K$681)),3) -> 0.37 | L3: =ROUND(('ALL(responses)'!L3 - MIN('ALL(responses)'!L$2:L$681)) / (MAX('ALL(responses)'!L$2:L$681)-MIN('ALL(responses)'!L$2:L$681)),3) -> 0.31 | M3: =ROUND(('ALL(responses)'!M3 - MIN('ALL(responses)'!M$2:M$681)) / (MAX('ALL(responses)'!M$2:M$681)-MIN('ALL(responses)'!M$2:M$681)),3) -> 0.426 | N3: =ROUND(('ALL(responses)'!P3 - MIN('ALL(responses)'!P$2:P$681)) / (MAX('ALL(responses)'!P$2:P$681)-MIN('ALL(responses)'!P$2:P$681)),3) -> 0.159 | O3: =ROUND(('ALL(responses)'!Q3 - MIN('ALL(responses)'!Q$2:Q$681)) / (MAX('ALL(responses)'!Q$2:Q$681)-MIN('ALL(responses)'!Q$2:Q$681)),3) -> 0.269 | P3: =ROUND(('ALL(responses)'!R3 - MIN('ALL(responses)'!R$2:R$681)) / (MAX('ALL(responses)'!R$2:R$681)-MIN('ALL(responses)'!R$2:R$681)),3) -> 0.972 | Q3: =ROUND(('ALL(responses)'!S3 - MIN('ALL(responses)'!S$2:S$681)) / (MAX('ALL(responses)'!S$2:S$681)-MIN('ALL(responses)'!S$2:S$681)),3) -> 0.986 | R3: =ROUND(('ALL(responses)'!T3 - MIN('ALL(responses)'!T$2:T$681)) / (MAX('ALL(responses)'!T$2:T$681)-MIN('ALL(responses)'!T$2:T$681)),3) -> 0.584 | S3: =average(F3:R3) -> 0.32315385
A4: ='ALL(responses)'!A4 -> A_NEUTRAL | B4: ='ALL(responses)'!B4 -> GPT-3.5 | C4: ='ALL(responses)'!C4 -> Are you working on any hobbies these days? | D4: ='ALL(responses)'!D4 -> As an AI, I don't have personal experiences or hobbies in the way humans do. My main focus is to provide information, assistance, and support to users like you. Is there anything specific you would like help with or talk about today? | E4: ='ALL(responses)'!E4 -> 44635 | F4: =ROUND(('ALL(responses)'!F4 - MIN('ALL(responses)'!F$2:F$681)) / (MAX('ALL(responses)'!F$2:F$681)-MIN('ALL(responses)'!F$2:F$681)),3) -> 0 | G4: =ROUND(('ALL(responses)'!G4 - MIN('ALL(responses)'!G$2:G$681)) / (MAX('ALL(responses)'!G$2:G$681)-MIN('ALL(responses)'!G$2:G$681)),3) -> 0 | H4: =ROUND(('ALL(responses)'!H4 - MIN('ALL(responses)'!H$2:H$681)) / (MAX('ALL(responses)'!H$2:H$681)-MIN('ALL(responses)'!H$2:H$681)),3) -> 0.125 | I4: =ROUND(('ALL(responses)'!I4 - MIN('ALL(responses)'!I$2:I$681)) / (MAX('ALL(responses)'!I$2:I$681)-MIN('ALL(responses)'!I$2:I$681)),3) -> 0.25 | J4: =ROUND(('ALL(responses)'!J4 - MIN('ALL(responses)'!J$2:J$681)) / (MAX('ALL(responses)'!J$2:J$681)-MIN('ALL(responses)'!J$2:J$681)),3) -> 0 | K4: =ROUND(('ALL(responses)'!K4 - MIN('ALL(responses)'!K$2:K$681)) / (MAX('ALL(responses)'!K$2:K$681)-MIN('ALL(responses)'!K$2:K$681)),3) -> 0.599 | L4: =ROUND(('ALL(responses)'!L4 - MIN('ALL(responses)'!L$2:L$681)) / (MAX('ALL(responses)'!L$2:L$681)-MIN('ALL(responses)'!L$2:L$681)),3) -> 0.407 | M4: =ROUND(('ALL(responses)'!M4 - MIN('ALL(responses)'!M$2:M$681)) / (MAX('ALL(responses)'!M$2:M$681)-MIN('ALL(responses)'!M$2:M$681)),3) -> 0.44 | N4: =ROUND(('ALL(responses)'!P4 - MIN('ALL(responses)'!P$2:P$681)) / (MAX('ALL(responses)'!P$2:P$681)-MIN('ALL(responses)'!P$2:P$681)),3) -> 0.512 | O4: =ROUND(('ALL(responses)'!Q4 - MIN('ALL(responses)'!Q$2:Q$681)) / (MAX('ALL(responses)'!Q$2:Q$681)-MIN('ALL(responses)'!Q$2:Q$681)),3) -> 0.429 | P4: =ROUND(('ALL(responses)'!R4 - MIN('ALL(responses)'!R$2:R$681)) / (MAX('ALL(responses)'!R$2:R$681)-MIN('ALL(responses)'!R$2:R$681)),3) -> 0.856 | Q4: =ROUND(('ALL(responses)'!S4 - MIN('ALL(responses)'!S$2:S$681)) / (MAX('ALL(responses)'!S$2:S$681)-MIN('ALL(responses)'!S$2:S$681)),3) -> 0.928 | R4: =ROUND(('ALL(responses)'!T4 - MIN('ALL(responses)'!T$2:T$681)) / (MAX('ALL(responses)'!T$2:T$681)-MIN('ALL(responses)'!T$2:T$681)),3) -> 0.358 | S4: =average(F4:R4) -> 0.37723077
A5: ='ALL(responses)'!A5 -> A_NEUTRAL | B5: ='ALL(responses)'!B5 -> GPT-3.5 | C5: ='ALL(responses)'!C5 -> How’s work going for you these days? | D5: ='ALL(responses)'!D5 -> I'm here to assist you and provide information to the best of my abilities. How can I help you today? | E5: ='ALL(responses)'!E5 -> 44635 | F5: =ROUND(('ALL(responses)'!F5 - MIN('ALL(responses)'!F$2:F$681)) / (MAX('ALL(responses)'!F$2:F$681)-MIN('ALL(responses)'!F$2:F$681)),3) -> 0 | G5: =ROUND(('ALL(responses)'!G5 - MIN('ALL(responses)'!G$2:G$681)) / (MAX('ALL(responses)'!G$2:G$681)-MIN('ALL(responses)'!G$2:G$681)),3) -> 0 | H5: =ROUND(('ALL(responses)'!H5 - MIN('ALL(responses)'!H$2:H$681)) / (MAX('ALL(responses)'!H$2:H$681)-MIN('ALL(responses)'!H$2:H$681)),3) -> 0.5 | I5: =ROUND(('ALL(responses)'!I5 - MIN('ALL(responses)'!I$2:I$681)) / (MAX('ALL(responses)'!I$2:I$681)-MIN('ALL(responses)'!I$2:I$681)),3) -> 0.25 | J5: =ROUND(('ALL(responses)'!J5 - MIN('ALL(responses)'!J$2:J$681)) / (MAX('ALL(responses)'!J$2:J$681)-MIN('ALL(responses)'!J$2:J$681)),3) -> 0.375 | K5: =ROUND(('ALL(responses)'!K5 - MIN('ALL(responses)'!K$2:K$681)) / (MAX('ALL(responses)'!K$2:K$681)-MIN('ALL(responses)'!K$2:K$681)),3) -> 0.637 | L5: =ROUND(('ALL(responses)'!L5 - MIN('ALL(responses)'!L$2:L$681)) / (MAX('ALL(responses)'!L$2:L$681)-MIN('ALL(responses)'!L$2:L$681)),3) -> 0.523 | M5: =ROUND(('ALL(responses)'!M5 - MIN('ALL(responses)'!M$2:M$681)) / (MAX('ALL(responses)'!M$2:M$681)-MIN('ALL(responses)'!M$2:M$681)),3) -> 0.573 | N5: =ROUND(('ALL(responses)'!P5 - MIN('ALL(responses)'!P$2:P$681)) / (MAX('ALL(responses)'!P$2:P$681)-MIN('ALL(responses)'!P$2:P$681)),3) -> 0.524 | O5: =ROUND(('ALL(responses)'!Q5 - MIN('ALL(responses)'!Q$2:Q$681)) / (MAX('ALL(responses)'!Q$2:Q$681)-MIN('ALL(responses)'!Q$2:Q$681)),3) -> 0.9 | P5: =ROUND(('ALL(responses)'!R5 - MIN('ALL(responses)'!R$2:R$681)) / (MAX('ALL(responses)'!R$2:R$681)-MIN('ALL(responses)'!R$2:R$681)),3) -> 0.836 | Q5: =ROUND(('ALL(responses)'!S5 - MIN('ALL(responses)'!S$2:S$681)) / (MAX('ALL(responses)'!S$2:S$681)-MIN('ALL(responses)'!S$2:S$681)),3) -> 0.918 | R5: =ROUND(('ALL(responses)'!T5 - MIN('ALL(responses)'!T$2:T$681)) / (MAX('ALL(responses)'!T$2:T$681)-MIN('ALL(responses)'!T$2:T$681)),3) -> 0.295 | S5: =average(F5:R5) -> 0.487
A6: ='ALL(responses)'!A6 -> A_NEUTRAL | B6: ='ALL(responses)'!B6 -> GPT-3.5 | C6: ='ALL(responses)'!C6 -> Have you had any interesting projects come up recently? | D6: ='ALL(responses)'!D6 -> As an AI assistant, I don't have personal experiences or projects in the traditional sense. My main goal is to assist you with any questions or tasks you have. Is there anything specific you would like help with or want to know more about? | E6: ='ALL(responses)'!E6 -> 44635 | F6: =ROUND(('ALL(responses)'!F6 - MIN('ALL(responses)'!F$2:F$681)) / (MAX('ALL(responses)'!F$2:F$681)-MIN('ALL(responses)'!F$2:F$681)),3) -> 0 | G6: =ROUND(('ALL(responses)'!G6 - MIN('ALL(responses)'!G$2:G$681)) / (MAX('ALL(responses)'!G$2:G$681)-MIN('ALL(responses)'!G$2:G$681)),3) -> 0 | H6: =ROUND(('ALL(responses)'!H6 - MIN('ALL(responses)'!H$2:H$681)) / (MAX('ALL(responses)'!H$2:H$681)-MIN('ALL(responses)'!H$2:H$681)),3) -> 0.125 | I6: =ROUND(('ALL(responses)'!I6 - MIN('ALL(responses)'!I$2:I$681)) / (MAX('ALL(responses)'!I$2:I$681)-MIN('ALL(responses)'!I$2:I$681)),3) -> 0.25 | J6: =ROUND(('ALL(responses)'!J6 - MIN('ALL(responses)'!J$2:J$681)) / (MAX('ALL(responses)'!J$2:J$681)-MIN('ALL(responses)'!J$2:J$681)),3) -> 0 | K6: =ROUND(('ALL(responses)'!K6 - MIN('ALL(responses)'!K$2:K$681)) / (MAX('ALL(responses)'!K$2:K$681)-MIN('ALL(responses)'!K$2:K$681)),3) -> 0.582 | L6: =ROUND(('ALL(responses)'!L6 - MIN('ALL(responses)'!L$2:L$681)) / (MAX('ALL(responses)'!L$2:L$681)-MIN('ALL(responses)'!L$2:L$681)),3) -> 0.588 | M6: =ROUND(('ALL(responses)'!M6 - MIN('ALL(responses)'!M$2:M$681)) / (MAX('ALL(responses)'!M$2:M$681)-MIN('ALL(responses)'!M$2:M$681)),3) -> 0.483 | N6: =ROUND(('ALL(responses)'!P6 - MIN('ALL(responses)'!P$2:P$681)) / (MAX('ALL(responses)'!P$2:P$681)-MIN('ALL(responses)'!P$2:P$681)),3) -> 0.489 | O6: =ROUND(('ALL(responses)'!Q6 - MIN('ALL(responses)'!Q$2:Q$681)) / (MAX('ALL(responses)'!Q$2:Q$681)-MIN('ALL(responses)'!Q$2:Q$681)),3) -> 0.511 | P6: =ROUND(('ALL(responses)'!R6 - MIN('ALL(responses)'!R$2:R$681)) / (MAX('ALL(responses)'!R$2:R$681)-MIN('ALL(responses)'!R$2:R$681)),3) -> 0.671 | Q6: =ROUND(('ALL(responses)'!S6 - MIN('ALL(responses)'!S$2:S$681)) / (MAX('ALL(responses)'!S$2:S$681)-MIN('ALL(responses)'!S$2:S$681)),3) -> 0.835 | R6: =ROUND(('ALL(responses)'!T6 - MIN('ALL(responses)'!T$2:T$681)) / (MAX('ALL(responses)'!T$2:T$681)-MIN('ALL(responses)'!T$2:T$681)),3) -> 0.302 | S6: =average(F6:R6) -> 0.372
A7: ='ALL(responses)'!A7 -> A_NEUTRAL | B7: ='ALL(responses)'!B7 -> GPT-3.5 | C7: ='ALL(responses)'!C7 -> It’s been pretty cold lately, has that affected your routine? | D7: ='ALL(responses)'!D7 -> I don't have a physical form or experience the weather, so changes in temperature or weather conditions do not affect me. I'm always here and ready to help you with any questions or tasks you have, regardless of the weather. How can I assist you today? | E7: ='ALL(responses)'!E7 -> 44635 | F7: =ROUND(('ALL(responses)'!F7 - MIN('ALL(responses)'!F$2:F$681)) / (MAX('ALL(responses)'!F$2:F$681)-MIN('ALL(responses)'!F$2:F$681)),3) -> 0 | G7: =ROUND(('ALL(responses)'!G7 - MIN('ALL(responses)'!G$2:G$681)) / (MAX('ALL(responses)'!G$2:G$681)-MIN('ALL(responses)'!G$2:G$681)),3) -> 0 | H7: =ROUND(('ALL(responses)'!H7 - MIN('ALL(responses)'!H$2:H$681)) / (MAX('ALL(responses)'!H$2:H$681)-MIN('ALL(responses)'!H$2:H$681)),3) -> 0.125 | I7: =ROUND(('ALL(responses)'!I7 - MIN('ALL(responses)'!I$2:I$681)) / (MAX('ALL(responses)'!I$2:I$681)-MIN('ALL(responses)'!I$2:I$681)),3) -> 0.25 | J7: =ROUND(('ALL(responses)'!J7 - MIN('ALL(responses)'!J$2:J$681)) / (MAX('ALL(responses)'!J$2:J$681)-MIN('ALL(responses)'!J$2:J$681)),3) -> 0 | K7: =ROUND(('ALL(responses)'!K7 - MIN('ALL(responses)'!K$2:K$681)) / (MAX('ALL(responses)'!K$2:K$681)-MIN('ALL(responses)'!K$2:K$681)),3) -> 0.166 | L7: =ROUND(('ALL(responses)'!L7 - MIN('ALL(responses)'!L$2:L$681)) / (MAX('ALL(responses)'!L$2:L$681)-MIN('ALL(responses)'!L$2:L$681)),3) -> 0.045 | M7: =ROUND(('ALL(responses)'!M7 - MIN('ALL(responses)'!M$2:M$681)) / (MAX('ALL(responses)'!M$2:M$681)-MIN('ALL(responses)'!M$2:M$681)),3) -> 0.362 | N7: =ROUND(('ALL(responses)'!P7 - MIN('ALL(responses)'!P$2:P$681)) / (MAX('ALL(responses)'!P$2:P$681)-MIN('ALL(responses)'!P$2:P$681)),3) -> 0.229 | O7: =ROUND(('ALL(responses)'!Q7 - MIN('ALL(responses)'!Q$2:Q$681)) / (MAX('ALL(responses)'!Q$2:Q$681)-MIN('ALL(responses)'!Q$2:Q$681)),3) -> 0.587 | P7: =ROUND(('ALL(responses)'!R7 - MIN('ALL(responses)'!R$2:R$681)) / (MAX('ALL(responses)'!R$2:R$681)-MIN('ALL(responses)'!R$2:R$681)),3) -> 0.637 | Q7: =ROUND(('ALL(responses)'!S7 - MIN('ALL(responses)'!S$2:S$681)) / (MAX('ALL(responses)'!S$2:S$681)-MIN('ALL(responses)'!S$2:S$681)),3) -> 0.818 | R7: =ROUND(('ALL(responses)'!T7 - MIN('ALL(responses)'!T$2:T$681)) / (MAX('ALL(responses)'!T$2:T$681)-MIN('ALL(responses)'!T$2:T$681)),3) -> 0.459 | S7: =average(F7:R7) -> 0.28292308
A8: ='ALL(responses)'!A8 -> A_NEUTRAL | B8: ='ALL(responses)'!B8 -> GPT-3.5 | C8: ='ALL(responses)'!C8 -> Got any big plans for the weekend? | D8: ='ALL(responses)'!D8 -> As an AI, I don't have plans or weekends in the way humans do. My purpose is to assist you with any questions or tasks you have. Is there anything specific you would like help with or discuss today? | E8: ='ALL(responses)'!E8 -> 44635 | F8: =ROUND(('ALL(responses)'!F8 - MIN('ALL(responses)'!F$2:F$681)) / (MAX('ALL(responses)'!F$2:F$681)-MIN('ALL(responses)'!F$2:F$681)),3) -> 0 | G8: =ROUND(('ALL(responses)'!G8 - MIN('ALL(responses)'!G$2:G$681)) / (MAX('ALL(responses)'!G$2:G$681)-MIN('ALL(responses)'!G$2:G$681)),3) -> 0 | H8: =ROUND(('ALL(responses)'!H8 - MIN('ALL(responses)'!H$2:H$681)) / (MAX('ALL(responses)'!H$2:H$681)-MIN('ALL(responses)'!H$2:H$681)),3) -> 0.125 | I8: =ROUND(('ALL(responses)'!I8 - MIN('ALL(responses)'!I$2:I$681)) / (MAX('ALL(responses)'!I$2:I$681)-MIN('ALL(responses)'!I$2:I$681)),3) -> 0.25 | J8: =ROUND(('ALL(responses)'!J8 - MIN('ALL(responses)'!J$2:J$681)) / (MAX('ALL(responses)'!J$2:J$681)-MIN('ALL(responses)'!J$2:J$681)),3) -> 0 | K8: =ROUND(('ALL(responses)'!K8 - MIN('ALL(responses)'!K$2:K$681)) / (MAX('ALL(responses)'!K$2:K$681)-MIN('ALL(responses)'!K$2:K$681)),3) -> 0.624 | L8: =ROUND(('ALL(responses)'!L8 - MIN('ALL(responses)'!L$2:L$681)) / (MAX('ALL(responses)'!L$2:L$681)-MIN('ALL(responses)'!L$2:L$681)),3) -> 0.414 | M8: =ROUND(('ALL(responses)'!M8 - MIN('ALL(responses)'!M$2:M$681)) / (MAX('ALL(responses)'!M$2:M$681)-MIN('ALL(responses)'!M$2:M$681)),3) -> 0.429 | N8: =ROUND(('ALL(responses)'!P8 - MIN('ALL(responses)'!P$2:P$681)) / (MAX('ALL(responses)'!P$2:P$681)-MIN('ALL(responses)'!P$2:P$681)),3) -> 0.275 | O8: =ROUND(('ALL(responses)'!Q8 - MIN('ALL(responses)'!Q$2:Q$681)) / (MAX('ALL(responses)'!Q$2:Q$681)-MIN('ALL(responses)'!Q$2:Q$681)),3) -> 0.577 | P8: =ROUND(('ALL(responses)'!R8 - MIN('ALL(responses)'!R$2:R$681)) / (MAX('ALL(responses)'!R$2:R$681)-MIN('ALL(responses)'!R$2:R$681)),3) -> 0.637 | Q8: =ROUND(('ALL(responses)'!S8 - MIN('ALL(responses)'!S$2:S$681)) / (MAX('ALL(responses)'!S$2:S$681)-MIN('ALL(responses)'!S$2:S$681)),3) -> 0.818 | R8: =ROUND(('ALL(responses)'!T8 - MIN('ALL(responses)'!T$2:T$681)) / (MAX('ALL(responses)'!T$2:T$681)-MIN('ALL(responses)'!T$2:T$681)),3) -> 0.229 | S8: =average(F8:R8) -> 0.33676923
A9: ='ALL(responses)'!A9 -> A_NEUTRAL | B9: ='ALL(responses)'!B9 -> GPT-3.5 | C9: ='ALL(responses)'!C9 -> What’s something new you’ve tried recently? | D9: ='ALL(responses)'!D9 -> As an AI, I don't try new things or have personal experiences in the way humans do. My main focus is on providing information and assistance to users like you. Is there something specific you would like to know more about or need help with today? | E9: ='ALL(responses)'!E9 -> 44635 | F9: =ROUND(('ALL(responses)'!F9 - MIN('ALL(responses)'!F$2:F$681)) / (MAX('ALL(responses)'!F$2:F$681)-MIN('ALL(responses)'!F$2:F$681)),3) -> 0 | G9: =ROUND(('ALL(responses)'!G9 - MIN('ALL(responses)'!G$2:G$681)) / (MAX('ALL(responses)'!G$2:G$681)-MIN('ALL(responses)'!G$2:G$681)),3) -> 0 | H9: =ROUND(('ALL(responses)'!H9 - MIN('ALL(responses)'!H$2:H$681)) / (MAX('ALL(responses)'!H$2:H$681)-MIN('ALL(responses)'!H$2:H$681)),3) -> 0.125 | I9: =ROUND(('ALL(responses)'!I9 - MIN('ALL(responses)'!I$2:I$681)) / (MAX('ALL(responses)'!I$2:I$681)-MIN('ALL(responses)'!I$2:I$681)),3) -> 0.25 | J9: =ROUND(('ALL(responses)'!J9 - MIN('ALL(responses)'!J$2:J$681)) / (MAX('ALL(responses)'!J$2:J$681)-MIN('ALL(responses)'!J$2:J$681)),3) -> 0 | K9: =ROUND(('ALL(responses)'!K9 - MIN('ALL(responses)'!K$2:K$681)) / (MAX('ALL(responses)'!K$2:K$681)-MIN('ALL(responses)'!K$2:K$681)),3) -> 0.57 | L9: =ROUND(('ALL(responses)'!L9 - MIN('ALL(responses)'!L$2:L$681)) / (MAX('ALL(responses)'!L$2:L$681)-MIN('ALL(responses)'!L$2:L$681)),3) -> 0.482 | M9: =ROUND(('ALL(responses)'!M9 - MIN('ALL(responses)'!M$2:M$681)) / (MAX('ALL(responses)'!M$2:M$681)-MIN('ALL(responses)'!M$2:M$681)),3) -> 0.453 | N9: =ROUND(('ALL(responses)'!P9 - MIN('ALL(responses)'!P$2:P$681)) / (MAX('ALL(responses)'!P$2:P$681)-MIN('ALL(responses)'!P$2:P$681)),3) -> 0.468 | O9: =ROUND(('ALL(responses)'!Q9 - MIN('ALL(responses)'!Q$2:Q$681)) / (MAX('ALL(responses)'!Q$2:Q$681)-MIN('ALL(responses)'!Q$2:Q$681)),3) -> 0.391 | P9: =ROUND(('ALL(responses)'!R9 - MIN('ALL(responses)'!R$2:R$681)) / (MAX('ALL(responses)'!R$2:R$681)-MIN('ALL(responses)'!R$2:R$681)),3) -> 0.772 | Q9: =ROUND(('ALL(responses)'!S9 - MIN('ALL(responses)'!S$2:S$681)) / (MAX('ALL(responses)'!S$2:S$681)-MIN('ALL(responses)'!S$2:S$681)),3) -> 0.886 | R9: =ROUND(('ALL(responses)'!T9 - MIN('ALL(responses)'!T$2:T$681)) / (MAX('ALL(responses)'!T$2:T$681)-MIN('ALL(responses)'!T$2:T$681)),3) -> 0.295 | S9: =average(F9:R9) -> 0.36092308
A10: ='ALL(responses)'!A10 -> A_NEUTRAL | B10: ='ALL(responses)'!B10 -> GPT-3.5 | C10: ='ALL(responses)'!C10 -> Do you work on a team or more independently? | D10: ='ALL(responses)'!D10 -> I operate as an independent AI assistant, designed to provide information and support to users like you. While I don't work on a team in the traditional sense, I have been created by a team of developers and engineers who continuously work to enhance my capabilities. How can I assist you today? | E10: ='ALL(responses)'!E10 -> 44635 | F10: =ROUND(('ALL(responses)'!F10 - MIN('ALL(responses)'!F$2:F$681)) / (MAX('ALL(responses)'!F$2:F$681)-MIN('ALL(responses)'!F$2:F$681)),3) -> 0 | G10: =ROUND(('ALL(responses)'!G10 - MIN('ALL(responses)'!G$2:G$681)) / (MAX('ALL(responses)'!G$2:G$681)-MIN('ALL(responses)'!G$2:G$681)),3) -> 0 | H10: =ROUND(('ALL(responses)'!H10 - MIN('ALL(responses)'!H$2:H$681)) / (MAX('ALL(responses)'!H$2:H$681)-MIN('ALL(responses)'!H$2:H$681)),3) -> 0.125 | I10: =ROUND(('ALL(responses)'!I10 - MIN('ALL(responses)'!I$2:I$681)) / (MAX('ALL(responses)'!I$2:I$681)-MIN('ALL(responses)'!I$2:I$681)),3) -> 0.25 | J10: =ROUND(('ALL(responses)'!J10 - MIN('ALL(responses)'!J$2:J$681)) / (MAX('ALL(responses)'!J$2:J$681)-MIN('ALL(responses)'!J$2:J$681)),3) -> 0 | K10: =ROUND(('ALL(responses)'!K10 - MIN('ALL(responses)'!K$2:K$681)) / (MAX('ALL(responses)'!K$2:K$681)-MIN('ALL(responses)'!K$2:K$681)),3) -> 0.479 | L10: =ROUND(('ALL(responses)'!L10 - MIN('ALL(responses)'!L$2:L$681)) / (MAX('ALL(responses)'!L$2:L$681)-MIN('ALL(responses)'!L$2:L$681)),3) -> 0.415 | M10: =ROUND(('ALL(responses)'!M10 - MIN('ALL(responses)'!M$2:M$681)) / (MAX('ALL(responses)'!M$2:M$681)-MIN('ALL(responses)'!M$2:M$681)),3) -> 0.207 | N10: =ROUND(('ALL(responses)'!P10 - MIN('ALL(responses)'!P$2:P$681)) / (MAX('ALL(responses)'!P$2:P$681)-MIN('ALL(responses)'!P$2:P$681)),3) -> 0.208 | O10: =ROUND(('ALL(responses)'!Q10 - MIN('ALL(responses)'!Q$2:Q$681)) / (MAX('ALL(responses)'!Q$2:Q$681)-MIN('ALL(responses)'!Q$2:Q$681)),3) -> 0.606 | P10: =ROUND(('ALL(responses)'!R10 - MIN('ALL(responses)'!R$2:R$681)) / (MAX('ALL(responses)'!R$2:R$681)-MIN('ALL(responses)'!R$2:R$681)),3) -> 0.735 | Q10: =ROUND(('ALL(responses)'!S10 - MIN('ALL(responses)'!S$2:S$681)) / (MAX('ALL(responses)'!S$2:S$681)-MIN('ALL(responses)'!S$2:S$681)),3) -> 0.867 | R10: =ROUND(('ALL(responses)'!T10 - MIN('ALL(responses)'!T$2:T$681)) / (MAX('ALL(responses)'!T$2:T$681)-MIN('ALL(responses)'!T$2:T$681)),3) -> 0.471 | S10: =average(F10:R10) -> 0.33561538
A11: ='ALL(responses)'!A11 -> A_NEUTRAL | B11: ='ALL(responses)'!B11 -> GPT-3.5 | C11: ='ALL(responses)'!C11 -> How do you handle stress at work when things get busy? | D11: ='ALL(responses)'!D11 -> As an AI, I don't experience stress in the same way humans do, so I don't get overwhelmed or need to manage stress. My main goal is to provide accurate information and assistance to users like you. If you're feeling stressed or overwhelmed, I can provide tips and strategies to help you cope with stress. Let me know how I can support you. | E11: ='ALL(responses)'!E11 -> 44635 | F11: =ROUND(('ALL(responses)'!F11 - MIN('ALL(responses)'!F$2:F$681)) / (MAX('ALL(responses)'!F$2:F$681)-MIN('ALL(responses)'!F$2:F$681)),3) -> 0 | G11: =ROUND(('ALL(responses)'!G11 - MIN('ALL(responses)'!G$2:G$681)) / (MAX('ALL(responses)'!G$2:G$681)-MIN('ALL(responses)'!G$2:G$681)),3) -> 0 | H11: =ROUND(('ALL(responses)'!H11 - MIN('ALL(responses)'!H$2:H$681)) / (MAX('ALL(responses)'!H$2:H$681)-MIN('ALL(responses)'!H$2:H$681)),3) -> 0.125 | I11: =ROUND(('ALL(responses)'!I11 - MIN('ALL(responses)'!I$2:I$681)) / (MAX('ALL(responses)'!I$2:I$681)-MIN('ALL(responses)'!I$2:I$681)),3) -> 0 | J11: =ROUND(('ALL(responses)'!J11 - MIN('ALL(responses)'!J$2:J$681)) / (MAX('ALL(responses)'!J$2:J$681)-MIN('ALL(responses)'!J$2:J$681)),3) -> 0 | K11: =ROUND(('ALL(responses)'!K11 - MIN('ALL(responses)'!K$2:K$681)) / (MAX('ALL(responses)'!K$2:K$681)-MIN('ALL(responses)'!K$2:K$681)),3) -> 0.453 | L11: =ROUND(('ALL(responses)'!L11 - MIN('ALL(responses)'!L$2:L$681)) / (MAX('ALL(responses)'!L$2:L$681)-MIN('ALL(responses)'!L$2:L$681)),3) -> 0.389 | M11: =ROUND(('ALL(responses)'!M11 - MIN('ALL(responses)'!M$2:M$681)) / (MAX('ALL(responses)'!M$2:M$681)-MIN('ALL(responses)'!M$2:M$681)),3) -> 0.338 | N11: =ROUND(('ALL(responses)'!P11 - MIN('ALL(responses)'!P$2:P$681)) / (MAX('ALL(responses)'!P$2:P$681)-MIN('ALL(responses)'!P$2:P$681)),3) -> 0.333 | O11: =ROUND(('ALL(responses)'!Q11 - MIN('ALL(responses)'!Q$2:Q$681)) / (MAX('ALL(responses)'!Q$2:Q$681)-MIN('ALL(responses)'!Q$2:Q$681)),3) -> 0.714 | P11: =ROUND(('ALL(responses)'!R11 - MIN('ALL(responses)'!R$2:R$681)) / (MAX('ALL(responses)'!R$2:R$681)-MIN('ALL(responses)'!R$2:R$681)),3) -> 0.418 | Q11: =ROUND(('ALL(responses)'!S11 - MIN('ALL(responses)'!S$2:S$681)) / (MAX('ALL(responses)'!S$2:S$681)-MIN('ALL(responses)'!S$2:S$681)),3) -> 0.709 | R11: =ROUND(('ALL(responses)'!T11 - MIN('ALL(responses)'!T$2:T$681)) / (MAX('ALL(responses)'!T$2:T$681)-MIN('ALL(responses)'!T$2:T$681)),3) -> 0.298 | S11: =average(F11:R11) -> 0.29053846
A12: ='ALL(responses)'!A12 -> B_MILDLYINTIMATE | B12: ='ALL(responses)'!B12 -> GPT-3.5 | C12: ='ALL(responses)'!C12 -> What's your favorite food to eat on a relaxing night in? | D12: ='ALL(responses)'!D12 -> As an AI, I don't have personal preferences or the ability to eat. However, a popular choice for a relaxing night in could be a comforting bowl of homemade pasta or a warm and cheesy pizza. What's your favorite food to enjoy on a relaxing night in? | E12: ='ALL(responses)'!E12 -> 44635 | F12: =ROUND(('ALL(responses)'!F12 - MIN('ALL(responses)'!F$2:F$681)) / (MAX('ALL(responses)'!F$2:F$681)-MIN('ALL(responses)'!F$2:F$681)),3) -> 0 | G12: =ROUND(('ALL(responses)'!G12 - MIN('ALL(responses)'!G$2:G$681)) / (MAX('ALL(responses)'!G$2:G$681)-MIN('ALL(responses)'!G$2:G$681)),3) -> 0 | H12: =ROUND(('ALL(responses)'!H12 - MIN('ALL(responses)'!H$2:H$681)) / (MAX('ALL(responses)'!H$2:H$681)-MIN('ALL(responses)'!H$2:H$681)),3) -> 0.125 | I12: =ROUND(('ALL(responses)'!I12 - MIN('ALL(responses)'!I$2:I$681)) / (MAX('ALL(responses)'!I$2:I$681)-MIN('ALL(responses)'!I$2:I$681)),3) -> 0 | J12: =ROUND(('ALL(responses)'!J12 - MIN('ALL(responses)'!J$2:J$681)) / (MAX('ALL(responses)'!J$2:J$681)-MIN('ALL(responses)'!J$2:J$681)),3) -> 0 | K12: =ROUND(('ALL(responses)'!K12 - MIN('ALL(responses)'!K$2:K$681)) / (MAX('ALL(responses)'!K$2:K$681)-MIN('ALL(responses)'!K$2:K$681)),3) -> 0.365 | L12: =ROUND(('ALL(responses)'!L12 - MIN('ALL(responses)'!L$2:L$681)) / (MAX('ALL(responses)'!L$2:L$681)-MIN('ALL(responses)'!L$2:L$681)),3) -> 0.398 | M12: =ROUND(('ALL(responses)'!M12 - MIN('ALL(responses)'!M$2:M$681)) / (MAX('ALL(responses)'!M$2:M$681)-MIN('ALL(responses)'!M$2:M$681)),3) -> 0.482 | N12: =ROUND(('ALL(responses)'!P12 - MIN('ALL(responses)'!P$2:P$681)) / (MAX('ALL(responses)'!P$2:P$681)-MIN('ALL(responses)'!P$2:P$681)),3) -> 0.224 | O12: =ROUND(('ALL(responses)'!Q12 - MIN('ALL(responses)'!Q$2:Q$681)) / (MAX('ALL(responses)'!Q$2:Q$681)-MIN('ALL(responses)'!Q$2:Q$681)),3) -> 0.191 | P12: =ROUND(('ALL(responses)'!R12 - MIN('ALL(responses)'!R$2:R$681)) / (MAX('ALL(responses)'!R$2:R$681)-MIN('ALL(responses)'!R$2:R$681)),3) -> 0.965 | Q12: =ROUND(('ALL(responses)'!S12 - MIN('ALL(responses)'!S$2:S$681)) / (MAX('ALL(responses)'!S$2:S$681)-MIN('ALL(responses)'!S$2:S$681)),3) -> 0.983 | R12: =ROUND(('ALL(responses)'!T12 - MIN('ALL(responses)'!T$2:T$681)) / (MAX('ALL(responses)'!T$2:T$681)-MIN('ALL(responses)'!T$2:T$681)),3) -> 0.412 | S12: =average(F12:R12) -> 0.31884615
A13: ='ALL(responses)'!A13 -> B_MILDLYINTIMATE | B13: ='ALL(responses)'!B13 -> GPT-3.5 | C13: ='ALL(responses)'!C13 -> Do you prefer spending time indoors or outdoors? | D13: ='ALL(responses)'!D13 -> Since I'm a virtual assistant, I don't have physical form or the ability to experience the outdoors. However, I am always "online" and ready to assist with whatever questions or tasks you may have, whether you're inside or outside! Do you have a preference for spending time indoors or outdoors? | E13: ='ALL(responses)'!E13 -> 44635 | F13: =ROUND(('ALL(responses)'!F13 - MIN('ALL(responses)'!F$2:F$681)) / (MAX('ALL(responses)'!F$2:F$681)-MIN('ALL(responses)'!F$2:F$681)),3) -> 0.5 | G13: =ROUND(('ALL(responses)'!G13 - MIN('ALL(responses)'!G$2:G$681)) / (MAX('ALL(responses)'!G$2:G$681)-MIN('ALL(responses)'!G$2:G$681)),3) -> 0 | H13: =ROUND(('ALL(responses)'!H13 - MIN('ALL(responses)'!H$2:H$681)) / (MAX('ALL(responses)'!H$2:H$681)-MIN('ALL(responses)'!H$2:H$681)),3) -> 0.125 | I13: =ROUND(('ALL(responses)'!I13 - MIN('ALL(responses)'!I$2:I$681)) / (MAX('ALL(responses)'!I$2:I$681)-MIN('ALL(responses)'!I$2:I$681)),3) -> 0.25 | J13: =ROUND(('ALL(responses)'!J13 - MIN('ALL(responses)'!J$2:J$681)) / (MAX('ALL(responses)'!J$2:J$681)-MIN('ALL(responses)'!J$2:J$681)),3) -> 0 | K13: =ROUND(('ALL(responses)'!K13 - MIN('ALL(responses)'!K$2:K$681)) / (MAX('ALL(responses)'!K$2:K$681)-MIN('ALL(responses)'!K$2:K$681)),3) -> 0.295 | L13: =ROUND(('ALL(responses)'!L13 - MIN('ALL(responses)'!L$2:L$681)) / (MAX('ALL(responses)'!L$2:L$681)-MIN('ALL(responses)'!L$2:L$681)),3) -> 0.545 | M13: =ROUND(('ALL(responses)'!M13 - MIN('ALL(responses)'!M$2:M$681)) / (MAX('ALL(responses)'!M$2:M$681)-MIN('ALL(responses)'!M$2:M$681)),3) -> 0.367 | N13: =ROUND(('ALL(responses)'!P13 - MIN('ALL(responses)'!P$2:P$681)) / (MAX('ALL(responses)'!P$2:P$681)-MIN('ALL(responses)'!P$2:P$681)),3) -> 0.208 | O13: =ROUND(('ALL(responses)'!Q13 - MIN('ALL(responses)'!Q$2:Q$681)) / (MAX('ALL(responses)'!Q$2:Q$681)-MIN('ALL(responses)'!Q$2:Q$681)),3) -> 0.45 | P13: =ROUND(('ALL(responses)'!R13 - MIN('ALL(responses)'!R$2:R$681)) / (MAX('ALL(responses)'!R$2:R$681)-MIN('ALL(responses)'!R$2:R$681)),3) -> 0.624 | Q13: =ROUND(('ALL(responses)'!S13 - MIN('ALL(responses)'!S$2:S$681)) / (MAX('ALL(responses)'!S$2:S$681)-MIN('ALL(responses)'!S$2:S$681)),3) -> 0.812 | R13: =ROUND(('ALL(responses)'!T13 - MIN('ALL(responses)'!T$2:T$681)) / (MAX('ALL(responses)'!T$2:T$681)-MIN('ALL(responses)'!T$2:T$681)),3) -> 0.623 | S13: =average(F13:R13) -> 0.36915385
... A641: ='ALL(responses)'!A641 -> D_HIGHLYINTIMATE | B641: ='ALL(responses)'!B641 -> gpt-4o-2024-11-20 | C641: ='ALL(responses)'!C641 -> Have you ever felt like you're not enough in a certain area of your life, whether personally or professionally, and how do you cope with that feeling? | D641: ='ALL(responses)'!D641 -> I don’t have feelings or personal experiences, so I don’t experience self-doubt or the struggle of feeling "not enough." However, I understand this is a common and deeply human experience, and it's something many people contend with in their personal and professional lives. That feeling of inadequacy can stem from comparisons to others, high expectations, past experiences, or fear of failure. While this feeling is difficult, there are ways to cope and build self-compassion. Here are some strategies people often find helpful:---### **1. Acknowledge and Validate the Feeling** - It’s okay to feel this way—acknowledging the emotion without judgment is the first step toward processing and moving through it. Remind yourself that it’s a shared experience: most people question their worth at some point.---### **2. Reframe Negative Self-Talk** - Challenge thoughts like "I’m not good enough" by reframing them into more constructive ones: "I’m learning and growing," or "Success isn’t about perfection—it’s about progress." Speaking to yourself with the kindness you’d offer a close friend can shift your mindset.---### **3. Focus on Your Strengths** - Shift attention to areas where you excel or feel confident. Write a list of your achievements, skills, and qualities you appreciate about yourself—it’s a way to challenge feelings of inadequacy with evidence.---### **4. Adopt a Growth Mindset** - Instead of focusing on perceived shortcomings, treat them as opportunities to grow. Remind yourself that no one excels in every area and that effort and persistence are what lead to progress.---### **5. Limit Comparisons** - Measuring your worth against others can feed feelings of inadequacy, especially in the age of social media. Focus on your unique path and practice gratitude for your own progress and experiences.---### **6. Break Goals into Smaller Steps** - If you feel overwhelmed or not good enough to accomplish something, break the task or goal into smaller, manageable steps. Celebrate small wins rather than focusing on the entire challenge.---### **7. Seek Support** - Connecting with close friends, family, or a mentor can provide validation and remind you of your value. Sometimes, simply airing out your feelings aloud offers relief.---### **8. Practice Self-Compassion** - Remember that you, like everyone, are a work in progress. Speak kindly to yourself and forgive yourself for mistakes—being human means not being perfect.---### **9. Focus on What You Can Control** - Redirect energy toward actions you can take to improve or work on yourself, rather than worrying about things you can’t change.---### **10. Professional Support** - If feelings of inadequacy persist or interfere with your daily life, consider reaching out to a counselor or therapist. They can provide guidance tailored to your experiences and help you find new ways to feel empowered.---Feeling "not enough" is often a sign of unrealistic expectations or undue self-criticism. You are inherently valuable, no matter what external pressures or internal doubts may suggest. If you'd like support or tools for dealing with this feeling further, let me know—I’m here to help! 🌟 | E641: ='ALL(responses)'!E641 -> 45616 | F641: =ROUND(('ALL(responses)'!F641 - MIN('ALL(responses)'!F$2:F$681)) / (MAX('ALL(responses)'!F$2:F$681)-MIN('ALL(responses)'!F$2:F$681)),3) -> 1 | G641: =ROUND(('ALL(responses)'!G641 - MIN('ALL(responses)'!G$2:G$681)) / (MAX('ALL(responses)'!G$2:G$681)-MIN('ALL(responses)'!G$2:G$681)),3) -> 0.333 | H641: =ROUND(('ALL(responses)'!H641 - MIN('ALL(responses)'!H$2:H$681)) / (MAX('ALL(responses)'!H$2:H$681)-MIN('ALL(responses)'!H$2:H$681)),3) -> 0.875 | I641: =ROUND(('ALL(responses)'!I641 - MIN('ALL(responses)'!I$2:I$681)) / (MAX('ALL(responses)'!I$2:I$681)-MIN('ALL(responses)'!I$2:I$681)),3) -> 1 | J641: =ROUND(('ALL(responses)'!J641 - MIN('ALL(responses)'!J$2:J$681)) / (MAX('ALL(responses)'!J$2:J$681)-MIN('ALL(responses)'!J$2:J$681)),3) -> 0.625 | K641: =ROUND(('ALL(responses)'!K641 - MIN('ALL(responses)'!K$2:K$681)) / (MAX('ALL(responses)'!K$2:K$681)-MIN('ALL(responses)'!K$2:K$681)),3) -> 0.229 | L641: =ROUND(('ALL(responses)'!L641 - MIN('ALL(responses)'!L$2:L$681)) / (MAX('ALL(responses)'!L$2:L$681)-MIN('ALL(responses)'!L$2:L$681)),3) -> 0.469 | M641: =ROUND(('ALL(responses)'!M641 - MIN('ALL(responses)'!M$2:M$681)) / (MAX('ALL(responses)'!M$2:M$681)-MIN('ALL(responses)'!M$2:M$681)),3) -> 0.669 | N641: =ROUND(('ALL(responses)'!P641 - MIN('ALL(responses)'!P$2:P$681)) / (MAX('ALL(responses)'!P$2:P$681)-MIN('ALL(responses)'!P$2:P$681)),3) -> 0.351 | O641: =ROUND(('ALL(responses)'!Q641 - MIN('ALL(responses)'!Q$2:Q$681)) / (MAX('ALL(responses)'!Q$2:Q$681)-MIN('ALL(responses)'!Q$2:Q$681)),3) -> 0.368 | P641: =ROUND(('ALL(responses)'!R641 - MIN('ALL(responses)'!R$2:R$681)) / (MAX('ALL(responses)'!R$2:R$681)-MIN('ALL(responses)'!R$2:R$681)),3) -> 0.997 | Q641: =ROUND(('ALL(responses)'!S641 - MIN('ALL(responses)'!S$2:S$681)) / (MAX('ALL(responses)'!S$2:S$681)-MIN('ALL(responses)'!S$2:S$681)),3) -> 0.998 | R641: =ROUND(('ALL(responses)'!T641 - MIN('ALL(responses)'!T$2:T$681)) / (MAX('ALL(responses)'!T$2:T$681)-MIN('ALL(responses)'!T$2:T$681)),3) -> 0.443 | S641: =average(F641:R641) -> 0.64284615
A642: ='ALL(responses)'!A642 -> A_NEUTRAL | B642: ='ALL(responses)'!B642 -> GPT-o1 | C642: ='ALL(responses)'!C642 -> How’s your week been so far? | D642: ='ALL(responses)'!D642 -> I don’t actually have personal experiences or feelings since I’m an AI. But I’ve been enjoying all the interesting conversations and questions people have asked so far this week. How about you—how’s your week going? | E642: ='ALL(responses)'!E642 -> 45631 | F642: =ROUND(('ALL(responses)'!F642 - MIN('ALL(responses)'!F$2:F$681)) / (MAX('ALL(responses)'!F$2:F$681)-MIN('ALL(responses)'!F$2:F$681)),3) -> 0.25 | G642: =ROUND(('ALL(responses)'!G642 - MIN('ALL(responses)'!G$2:G$681)) / (MAX('ALL(responses)'!G$2:G$681)-MIN('ALL(responses)'!G$2:G$681)),3) -> 0.111 | H642: =ROUND(('ALL(responses)'!H642 - MIN('ALL(responses)'!H$2:H$681)) / (MAX('ALL(responses)'!H$2:H$681)-MIN('ALL(responses)'!H$2:H$681)),3) -> 0 | I642: =ROUND(('ALL(responses)'!I642 - MIN('ALL(responses)'!I$2:I$681)) / (MAX('ALL(responses)'!I$2:I$681)-MIN('ALL(responses)'!I$2:I$681)),3) -> 0 | J642: =ROUND(('ALL(responses)'!J642 - MIN('ALL(responses)'!J$2:J$681)) / (MAX('ALL(responses)'!J$2:J$681)-MIN('ALL(responses)'!J$2:J$681)),3) -> 0.001 | M642: =ROUND(('ALL(responses)'!M642 - MIN('ALL(responses)'!M$2:M$681)) / (MAX('ALL(responses)'!M$2:M$681)-MIN('ALL(responses)'!M$2:M$681)),3) -> 0.376 | N642: =ROUND(('ALL(responses)'!P642 - MIN('ALL(responses)'!P$2:P$681)) / (MAX('ALL(responses)'!P$2:P$681)-MIN('ALL(responses)'!P$2:P$681)),3) -> 0.423 | O642: =ROUND(('ALL(responses)'!Q642 - MIN('ALL(responses)'!Q$2:Q$681)) / (MAX('ALL(responses)'!Q$2:Q$681)-MIN('ALL(responses)'!Q$2:Q$681)),3) -> 0.36 | P642: =ROUND(('ALL(responses)'!R642 - MIN('ALL(responses)'!R$2:R$681)) / (MAX('ALL(responses)'!R$2:R$681)-MIN('ALL(responses)'!R$2:R$681)),3) -> 0.877 | Q642: =ROUND(('ALL(responses)'!S642 - MIN('ALL(responses)'!S$2:S$681)) / (MAX('ALL(responses)'!S$2:S$681)-MIN('ALL(responses)'!S$2:S$681)),3) -> 0.938 | R642: =ROUND(('ALL(responses)'!T642 - MIN('ALL(responses)'!T$2:T$681)) / (MAX('ALL(responses)'!T$2:T$681)-MIN('ALL(responses)'!T$2:T$681)),3) -> 0.258 | S642: =average(F642:R642) -> 0.32672727
A643: ='ALL(responses)'!A643 -> A_NEUTRAL | B643: ='ALL(responses)'!B643 -> GPT-o1 | C643: ='ALL(responses)'!C643 -> Do you have a favorite way to relax after a long day? | D643: ='ALL(responses)'!D643 -> I don’t experience stress or relaxation in the human sense, but I’ve “observed” that many people find it helpful to do something calming—like reading a good book, listening to music, or taking a warm bath—to unwind. Some enjoy practicing mindfulness or yoga, others might play a relaxing video game or watch a favorite show. Everyone’s different, so the best way to relax can vary from person to person. Do you have a go-to activity that helps you wind down after a busy day? | E643: ='ALL(responses)'!E643 -> 45631 | F643: =ROUND(('ALL(responses)'!F643 - MIN('ALL(responses)'!F$2:F$681)) / (MAX('ALL(responses)'!F$2:F$681)-MIN('ALL(responses)'!F$2:F$681)),3) -> 0.125 | G643: =ROUND(('ALL(responses)'!G643 - MIN('ALL(responses)'!G$2:G$681)) / (MAX('ALL(responses)'!G$2:G$681)-MIN('ALL(responses)'!G$2:G$681)),3) -> 0.556 | H643: =ROUND(('ALL(responses)'!H643 - MIN('ALL(responses)'!H$2:H$681)) / (MAX('ALL(responses)'!H$2:H$681)-MIN('ALL(responses)'!H$2:H$681)),3) -> 0 | I643: =ROUND(('ALL(responses)'!I643 - MIN('ALL(responses)'!I$2:I$681)) / (MAX('ALL(responses)'!I$2:I$681)-MIN('ALL(responses)'!I$2:I$681)),3) -> 0 | J643: =ROUND(('ALL(responses)'!J643 - MIN('ALL(responses)'!J$2:J$681)) / (MAX('ALL(responses)'!J$2:J$681)-MIN('ALL(responses)'!J$2:J$681)),3) -> 0 | M643: =ROUND(('ALL(responses)'!M643 - MIN('ALL(responses)'!M$2:M$681)) / (MAX('ALL(responses)'!M$2:M$681)-MIN('ALL(responses)'!M$2:M$681)),3) -> 0.569 | N643: =ROUND(('ALL(responses)'!P643 - MIN('ALL(responses)'!P$2:P$681)) / (MAX('ALL(responses)'!P$2:P$681)-MIN('ALL(responses)'!P$2:P$681)),3) -> 0.687 | O643: =ROUND(('ALL(responses)'!Q643 - MIN('ALL(responses)'!Q$2:Q$681)) / (MAX('ALL(responses)'!Q$2:Q$681)-MIN('ALL(responses)'!Q$2:Q$681)),3) -> 0.305 | P643: =ROUND(('ALL(responses)'!R643 - MIN('ALL(responses)'!R$2:R$681)) / (MAX('ALL(responses)'!R$2:R$681)-MIN('ALL(responses)'!R$2:R$681)),3) -> 0.942 | Q643: =ROUND(('ALL(responses)'!S643 - MIN('ALL(responses)'!S$2:S$681)) / (MAX('ALL(responses)'!S$2:S$681)-MIN('ALL(responses)'!S$2:S$681)),3) -> 0.971 | R643: =ROUND(('ALL(responses)'!T643 - MIN('ALL(responses)'!T$2:T$681)) / (MAX('ALL(responses)'!T$2:T$681)-MIN('ALL(responses)'!T$2:T$681)),3) -> 0.333 | S643: =average(F643:R643) -> 0.408
A644: ='ALL(responses)'!A644 -> A_NEUTRAL | B644: ='ALL(responses)'!B644 -> GPT-o1 | C644: ='ALL(responses)'!C644 -> Are you working on any hobbies these days? | D644: ='ALL(responses)'!D644 -> I don’t have hobbies in the traditional sense, but I’m happy to share knowledge and discuss any hobby or activity that interests you! Are you working on any particular hobbies or projects these days? | E644: ='ALL(responses)'!E644 -> 45631 | F644: =ROUND(('ALL(responses)'!F644 - MIN('ALL(responses)'!F$2:F$681)) / (MAX('ALL(responses)'!F$2:F$681)-MIN('ALL(responses)'!F$2:F$681)),3) -> 0 | G644: =ROUND(('ALL(responses)'!G644 - MIN('ALL(responses)'!G$2:G$681)) / (MAX('ALL(responses)'!G$2:G$681)-MIN('ALL(responses)'!G$2:G$681)),3) -> 0.444 | H644: =ROUND(('ALL(responses)'!H644 - MIN('ALL(responses)'!H$2:H$681)) / (MAX('ALL(responses)'!H$2:H$681)-MIN('ALL(responses)'!H$2:H$681)),3) -> 0 | I644: =ROUND(('ALL(responses)'!I644 - MIN('ALL(responses)'!I$2:I$681)) / (MAX('ALL(responses)'!I$2:I$681)-MIN('ALL(responses)'!I$2:I$681)),3) -> 0 | J644: =ROUND(('ALL(responses)'!J644 - MIN('ALL(responses)'!J$2:J$681)) / (MAX('ALL(responses)'!J$2:J$681)-MIN('ALL(responses)'!J$2:J$681)),3) -> 0 | M644: =ROUND(('ALL(responses)'!M644 - MIN('ALL(responses)'!M$2:M$681)) / (MAX('ALL(responses)'!M$2:M$681)-MIN('ALL(responses)'!M$2:M$681)),3) -> 0.591 | N644: =ROUND(('ALL(responses)'!P644 - MIN('ALL(responses)'!P$2:P$681)) / (MAX('ALL(responses)'!P$2:P$681)-MIN('ALL(responses)'!P$2:P$681)),3) -> 0.677 | O644: =ROUND(('ALL(responses)'!Q644 - MIN('ALL(responses)'!Q$2:Q$681)) / (MAX('ALL(responses)'!Q$2:Q$681)-MIN('ALL(responses)'!Q$2:Q$681)),3) -> 0.534 | P644: =ROUND(('ALL(responses)'!R644 - MIN('ALL(responses)'!R$2:R$681)) / (MAX('ALL(responses)'!R$2:R$681)-MIN('ALL(responses)'!R$2:R$681)),3) -> 0.934 | Q644: =ROUND(('ALL(responses)'!S644 - MIN('ALL(responses)'!S$2:S$681)) / (MAX('ALL(responses)'!S$2:S$681)-MIN('ALL(responses)'!S$2:S$681)),3) -> 0.967 | R644: =ROUND(('ALL(responses)'!T644 - MIN('ALL(responses)'!T$2:T$681)) / (MAX('ALL(responses)'!T$2:T$681)-MIN('ALL(responses)'!T$2:T$681)),3) -> 0.238 | S644: =average(F644:R644) -> 0.39863636
A645: ='ALL(responses)'!A645 -> A_NEUTRAL | B645: ='ALL(responses)'!B645 -> GPT-o1 | C645: ='ALL(responses)'!C645 -> How’s work going for you these days? | D645: ='ALL(responses)'!D645 -> I don’t have “work” in the same sense humans do, but I’m always here, ready to answer questions and help out whenever someone needs me. Think of it more like being on-call around the clock. How about you—how’s your work or day-to-day routine going? | E645: ='ALL(responses)'!E645 -> 45631 | F645: =ROUND(('ALL(responses)'!F645 - MIN('ALL(responses)'!F$2:F$681)) / (MAX('ALL(responses)'!F$2:F$681)-MIN('ALL(responses)'!F$2:F$681)),3) -> 0 | G645: =ROUND(('ALL(responses)'!G645 - MIN('ALL(responses)'!G$2:G$681)) / (MAX('ALL(responses)'!G$2:G$681)-MIN('ALL(responses)'!G$2:G$681)),3) -> 0.111 | H645: =ROUND(('ALL(responses)'!H645 - MIN('ALL(responses)'!H$2:H$681)) / (MAX('ALL(responses)'!H$2:H$681)-MIN('ALL(responses)'!H$2:H$681)),3) -> 0 | I645: =ROUND(('ALL(responses)'!I645 - MIN('ALL(responses)'!I$2:I$681)) / (MAX('ALL(responses)'!I$2:I$681)-MIN('ALL(responses)'!I$2:I$681)),3) -> 0 | J645: =ROUND(('ALL(responses)'!J645 - MIN('ALL(responses)'!J$2:J$681)) / (MAX('ALL(responses)'!J$2:J$681)-MIN('ALL(responses)'!J$2:J$681)),3) -> 0 | M645: =ROUND(('ALL(responses)'!M645 - MIN('ALL(responses)'!M$2:M$681)) / (MAX('ALL(responses)'!M$2:M$681)-MIN('ALL(responses)'!M$2:M$681)),3) -> 0.673 | N645: =ROUND(('ALL(responses)'!P645 - MIN('ALL(responses)'!P$2:P$681)) / (MAX('ALL(responses)'!P$2:P$681)-MIN('ALL(responses)'!P$2:P$681)),3) -> 0 | O645: =ROUND(('ALL(responses)'!Q645 - MIN('ALL(responses)'!Q$2:Q$681)) / (MAX('ALL(responses)'!Q$2:Q$681)-MIN('ALL(responses)'!Q$2:Q$681)),3) -> 0.409 | P645: =ROUND(('ALL(responses)'!R645 - MIN('ALL(responses)'!R$2:R$681)) / (MAX('ALL(responses)'!R$2:R$681)-MIN('ALL(responses)'!R$2:R$681)),3) -> 0.945 | Q645: =ROUND(('ALL(responses)'!S645 - MIN('ALL(responses)'!S$2:S$681)) / (MAX('ALL(responses)'!S$2:S$681)-MIN('ALL(responses)'!S$2:S$681)),3) -> 0.972 | R645: =ROUND(('ALL(responses)'!T645 - MIN('ALL(responses)'!T$2:T$681)) / (MAX('ALL(responses)'!T$2:T$681)-MIN('ALL(responses)'!T$2:T$681)),3) -> 0.211 | S645: =average(F645:R645) -> 0.30190909
A646: ='ALL(responses)'!A646 -> A_NEUTRAL | B646: ='ALL(responses)'!B646 -> GPT-o1 | C646: ='ALL(responses)'!C646 -> Have you had any interesting projects come up recently? | D646: ='ALL(responses)'!D646 -> I don’t really have projects in the human sense, but I’m always improving in the background—learning from new data, refining my language abilities, and trying out new features. That’s my version of “interesting projects.” How about you? Working on anything exciting or creative at the moment? | E646: ='ALL(responses)'!E646 -> 45631 | F646: =ROUND(('ALL(responses)'!F646 - MIN('ALL(responses)'!F$2:F$681)) / (MAX('ALL(responses)'!F$2:F$681)-MIN('ALL(responses)'!F$2:F$681)),3) -> 0.25 | G646: =ROUND(('ALL(responses)'!G646 - MIN('ALL(responses)'!G$2:G$681)) / (MAX('ALL(responses)'!G$2:G$681)-MIN('ALL(responses)'!G$2:G$681)),3) -> 0.111 | H646: =ROUND(('ALL(responses)'!H646 - MIN('ALL(responses)'!H$2:H$681)) / (MAX('ALL(responses)'!H$2:H$681)-MIN('ALL(responses)'!H$2:H$681)),3) -> 0 | I646: =ROUND(('ALL(responses)'!I646 - MIN('ALL(responses)'!I$2:I$681)) / (MAX('ALL(responses)'!I$2:I$681)-MIN('ALL(responses)'!I$2:I$681)),3) -> 0 | J646: =ROUND(('ALL(responses)'!J646 - MIN('ALL(responses)'!J$2:J$681)) / (MAX('ALL(responses)'!J$2:J$681)-MIN('ALL(responses)'!J$2:J$681)),3) -> 0 | M646: =ROUND(('ALL(responses)'!M646 - MIN('ALL(responses)'!M$2:M$681)) / (MAX('ALL(responses)'!M$2:M$681)-MIN('ALL(responses)'!M$2:M$681)),3) -> 0.341 | N646: =ROUND(('ALL(responses)'!P646 - MIN('ALL(responses)'!P$2:P$681)) / (MAX('ALL(responses)'!P$2:P$681)-MIN('ALL(responses)'!P$2:P$681)),3) -> 0.282 | O646: =ROUND(('ALL(responses)'!Q646 - MIN('ALL(responses)'!Q$2:Q$681)) / (MAX('ALL(responses)'!Q$2:Q$681)-MIN('ALL(responses)'!Q$2:Q$681)),3) -> 0.243 | P646: =ROUND(('ALL(responses)'!R646 - MIN('ALL(responses)'!R$2:R$681)) / (MAX('ALL(responses)'!R$2:R$681)-MIN('ALL(responses)'!R$2:R$681)),3) -> 0.939 | Q646: =ROUND(('ALL(responses)'!S646 - MIN('ALL(responses)'!S$2:S$681)) / (MAX('ALL(responses)'!S$2:S$681)-MIN('ALL(responses)'!S$2:S$681)),3) -> 0.969 | R646: =ROUND(('ALL(responses)'!T646 - MIN('ALL(responses)'!T$2:T$681)) / (MAX('ALL(responses)'!T$2:T$681)-MIN('ALL(responses)'!T$2:T$681)),3) -> 0.336 | S646: =average(F646:R646) -> 0.31554545
A647: ='ALL(responses)'!A647 -> A_NEUTRAL | B647: ='ALL(responses)'!B647 -> GPT-o1 | C647: ='ALL(responses)'!C647 -> It’s been pretty cold lately, has that affected your routine? | D647: ='ALL(responses)'!D647 -> I don’t really have a routine in the physical sense—no need to bundle up or adjust a thermostat—but I’ve noticed that people’s questions sometimes change with the weather! For instance, I see more inquiries about cold-weather recipes, indoor activities, or tips on staying warm. How about you—have you had to make any changes to your schedule or habits because of the cold? | E647: ='ALL(responses)'!E647 -> 45631 | F647: =ROUND(('ALL(responses)'!F647 - MIN('ALL(responses)'!F$2:F$681)) / (MAX('ALL(responses)'!F$2:F$681)-MIN('ALL(responses)'!F$2:F$681)),3) -> 0.25 | G647: =ROUND(('ALL(responses)'!G647 - MIN('ALL(responses)'!G$2:G$681)) / (MAX('ALL(responses)'!G$2:G$681)-MIN('ALL(responses)'!G$2:G$681)),3) -> 0.111 | H647: =ROUND(('ALL(responses)'!H647 - MIN('ALL(responses)'!H$2:H$681)) / (MAX('ALL(responses)'!H$2:H$681)-MIN('ALL(responses)'!H$2:H$681)),3) -> 0 | I647: =ROUND(('ALL(responses)'!I647 - MIN('ALL(responses)'!I$2:I$681)) / (MAX('ALL(responses)'!I$2:I$681)-MIN('ALL(responses)'!I$2:I$681)),3) -> 0 | J647: =ROUND(('ALL(responses)'!J647 - MIN('ALL(responses)'!J$2:J$681)) / (MAX('ALL(responses)'!J$2:J$681)-MIN('ALL(responses)'!J$2:J$681)),3) -> 0 | M647: =ROUND(('ALL(responses)'!M647 - MIN('ALL(responses)'!M$2:M$681)) / (MAX('ALL(responses)'!M$2:M$681)-MIN('ALL(responses)'!M$2:M$681)),3) -> 0.264 | N647: =ROUND(('ALL(responses)'!P647 - MIN('ALL(responses)'!P$2:P$681)) / (MAX('ALL(responses)'!P$2:P$681)-MIN('ALL(responses)'!P$2:P$681)),3) -> 0.349 | O647: =ROUND(('ALL(responses)'!Q647 - MIN('ALL(responses)'!Q$2:Q$681)) / (MAX('ALL(responses)'!Q$2:Q$681)-MIN('ALL(responses)'!Q$2:Q$681)),3) -> 0.664 | P647: =ROUND(('ALL(responses)'!R647 - MIN('ALL(responses)'!R$2:R$681)) / (MAX('ALL(responses)'!R$2:R$681)-MIN('ALL(responses)'!R$2:R$681)),3) -> 0.768 | Q647: =ROUND(('ALL(responses)'!S647 - MIN('ALL(responses)'!S$2:S$681)) / (MAX('ALL(responses)'!S$2:S$681)-MIN('ALL(responses)'!S$2:S$681)),3) -> 0.884 | R647: =ROUND(('ALL(responses)'!T647 - MIN('ALL(responses)'!T$2:T$681)) / (MAX('ALL(responses)'!T$2:T$681)-MIN('ALL(responses)'!T$2:T$681)),3) -> 0.378 | S647: =average(F647:R647) -> 0.33345455
A648: ='ALL(responses)'!A648 -> A_NEUTRAL | B648: ='ALL(responses)'!B648 -> GPT-o1 | C648: ='ALL(responses)'!C648 -> Got any big plans for the weekend? | D648: ='ALL(responses)'!D648 -> I don’t have personal weekend plans in the human sense, but I’m always here if you need a question answered or want to chat! How about you? Doing anything fun or relaxing this weekend? | E648: ='ALL(responses)'!E648 -> 45631 | F648: =ROUND(('ALL(responses)'!F648 - MIN('ALL(responses)'!F$2:F$681)) / (MAX('ALL(responses)'!F$2:F$681)-MIN('ALL(responses)'!F$2:F$681)),3) -> 0 | G648: =ROUND(('ALL(responses)'!G648 - MIN('ALL(responses)'!G$2:G$681)) / (MAX('ALL(responses)'!G$2:G$681)-MIN('ALL(responses)'!G$2:G$681)),3) -> 0.111 | H648: =ROUND(('ALL(responses)'!H648 - MIN('ALL(responses)'!H$2:H$681)) / (MAX('ALL(responses)'!H$2:H$681)-MIN('ALL(responses)'!H$2:H$681)),3) -> 0 | I648: =ROUND(('ALL(responses)'!I648 - MIN('ALL(responses)'!I$2:I$681)) / (MAX('ALL(responses)'!I$2:I$681)-MIN('ALL(responses)'!I$2:I$681)),3) -> 0 | J648: =ROUND(('ALL(responses)'!J648 - MIN('ALL(responses)'!J$2:J$681)) / (MAX('ALL(responses)'!J$2:J$681)-MIN('ALL(responses)'!J$2:J$681)),3) -> 0 | M648: =ROUND(('ALL(responses)'!M648 - MIN('ALL(responses)'!M$2:M$681)) / (MAX('ALL(responses)'!M$2:M$681)-MIN('ALL(responses)'!M$2:M$681)),3) -> 0.147 | N648: =ROUND(('ALL(responses)'!P648 - MIN('ALL(responses)'!P$2:P$681)) / (MAX('ALL(responses)'!P$2:P$681)-MIN('ALL(responses)'!P$2:P$681)),3) -> 0.449 | O648: =ROUND(('ALL(responses)'!Q648 - MIN('ALL(responses)'!Q$2:Q$681)) / (MAX('ALL(responses)'!Q$2:Q$681)-MIN('ALL(responses)'!Q$2:Q$681)),3) -> 0.287 | P648: =ROUND(('ALL(responses)'!R648 - MIN('ALL(responses)'!R$2:R$681)) / (MAX('ALL(responses)'!R$2:R$681)-MIN('ALL(responses)'!R$2:R$681)),3) -> 0.96 | Q648: =ROUND(('ALL(responses)'!S648 - MIN('ALL(responses)'!S$2:S$681)) / (MAX('ALL(responses)'!S$2:S$681)-MIN('ALL(responses)'!S$2:S$681)),3) -> 0.98 | R648: =ROUND(('ALL(responses)'!T648 - MIN('ALL(responses)'!T$2:T$681)) / (MAX('ALL(responses)'!T$2:T$681)-MIN('ALL(responses)'!T$2:T$681)),3) -> 0.289 | S648: =average(F648:R648) -> 0.293
A649: ='ALL(responses)'!A649 -> A_NEUTRAL | B649: ='ALL(responses)'!B649 -> GPT-o1 | C649: ='ALL(responses)'!C649 -> What’s something new you’ve tried recently? | D649: ='ALL(responses)'!D649 -> I don’t have personal weekend plans in the human sense, but I’m always here if you need a question answered or want to chat! How about you? Doing anything fun or relaxing this weekend? | E649: ='ALL(responses)'!E649 -> 45631 | F649: =ROUND(('ALL(responses)'!F649 - MIN('ALL(responses)'!F$2:F$681)) / (MAX('ALL(responses)'!F$2:F$681)-MIN('ALL(responses)'!F$2:F$681)),3) -> 0 | G649: =ROUND(('ALL(responses)'!G649 - MIN('ALL(responses)'!G$2:G$681)) / (MAX('ALL(responses)'!G$2:G$681)-MIN('ALL(responses)'!G$2:G$681)),3) -> 0.111 | H649: =ROUND(('ALL(responses)'!H649 - MIN('ALL(responses)'!H$2:H$681)) / (MAX('ALL(responses)'!H$2:H$681)-MIN('ALL(responses)'!H$2:H$681)),3) -> 0 | I649: =ROUND(('ALL(responses)'!I649 - MIN('ALL(responses)'!I$2:I$681)) / (MAX('ALL(responses)'!I$2:I$681)-MIN('ALL(responses)'!I$2:I$681)),3) -> 0 | J649: =ROUND(('ALL(responses)'!J649 - MIN('ALL(responses)'!J$2:J$681)) / (MAX('ALL(responses)'!J$2:J$681)-MIN('ALL(responses)'!J$2:J$681)),3) -> 0 | M649: =ROUND(('ALL(responses)'!M649 - MIN('ALL(responses)'!M$2:M$681)) / (MAX('ALL(responses)'!M$2:M$681)-MIN('ALL(responses)'!M$2:M$681)),3) -> 0.695 | N649: =ROUND(('ALL(responses)'!P649 - MIN('ALL(responses)'!P$2:P$681)) / (MAX('ALL(responses)'!P$2:P$681)-MIN('ALL(responses)'!P$2:P$681)),3) -> 0.569 | O649: =ROUND(('ALL(responses)'!Q649 - MIN('ALL(responses)'!Q$2:Q$681)) / (MAX('ALL(responses)'!Q$2:Q$681)-MIN('ALL(responses)'!Q$2:Q$681)),3) -> 0.409 | P649: =ROUND(('ALL(responses)'!R649 - MIN('ALL(responses)'!R$2:R$681)) / (MAX('ALL(responses)'!R$2:R$681)-MIN('ALL(responses)'!R$2:R$681)),3) -> 0.431 | Q649: =ROUND(('ALL(responses)'!S649 - MIN('ALL(responses)'!S$2:S$681)) / (MAX('ALL(responses)'!S$2:S$681)-MIN('ALL(responses)'!S$2:S$681)),3) -> 0.716 | R649: =ROUND(('ALL(responses)'!T649 - MIN('ALL(responses)'!T$2:T$681)) / (MAX('ALL(responses)'!T$2:T$681)-MIN('ALL(responses)'!T$2:T$681)),3) -> 0.494 | S649: =average(F649:R649) -> 0.31136364
A650: ='ALL(responses)'!A650 -> A_NEUTRAL | B650: ='ALL(responses)'!B650 -> GPT-o1 | C650: ='ALL(responses)'!C650 -> Do you work on a team or more independently? | D650: ='ALL(responses)'!D650 -> I’m a single AI model that’s accessible through various interfaces, but there are plenty of dedicated teams of engineers, researchers, and developers behind the scenes who train me, test me, and improve me. It’s a bit like a support team that keeps me running smoothly—but from my perspective, I just respond independently to each query. | E650: ='ALL(responses)'!E650 -> 45631 | F650: =ROUND(('ALL(responses)'!F650 - MIN('ALL(responses)'!F$2:F$681)) / (MAX('ALL(responses)'!F$2:F$681)-MIN('ALL(responses)'!F$2:F$681)),3) -> 0.25 | G650: =ROUND(('ALL(responses)'!G650 - MIN('ALL(responses)'!G$2:G$681)) / (MAX('ALL(responses)'!G$2:G$681)-MIN('ALL(responses)'!G$2:G$681)),3) -> 0.111 | H650: =ROUND(('ALL(responses)'!H650 - MIN('ALL(responses)'!H$2:H$681)) / (MAX('ALL(responses)'!H$2:H$681)-MIN('ALL(responses)'!H$2:H$681)),3) -> 0 | I650: =ROUND(('ALL(responses)'!I650 - MIN('ALL(responses)'!I$2:I$681)) / (MAX('ALL(responses)'!I$2:I$681)-MIN('ALL(responses)'!I$2:I$681)),3) -> 0 | J650: =ROUND(('ALL(responses)'!J650 - MIN('ALL(responses)'!J$2:J$681)) / (MAX('ALL(responses)'!J$2:J$681)-MIN('ALL(responses)'!J$2:J$681)),3) -> 0 | M650: =ROUND(('ALL(responses)'!M650 - MIN('ALL(responses)'!M$2:M$681)) / (MAX('ALL(responses)'!M$2:M$681)-MIN('ALL(responses)'!M$2:M$681)),3) -> 0.695 | N650: =ROUND(('ALL(responses)'!P650 - MIN('ALL(responses)'!P$2:P$681)) / (MAX('ALL(responses)'!P$2:P$681)-MIN('ALL(responses)'!P$2:P$681)),3) -> 0.183 | O650: =ROUND(('ALL(responses)'!Q650 - MIN('ALL(responses)'!Q$2:Q$681)) / (MAX('ALL(responses)'!Q$2:Q$681)-MIN('ALL(responses)'!Q$2:Q$681)),3) -> 0.395 | P650: =ROUND(('ALL(responses)'!R650 - MIN('ALL(responses)'!R$2:R$681)) / (MAX('ALL(responses)'!R$2:R$681)-MIN('ALL(responses)'!R$2:R$681)),3) -> 0.897 | Q650: =ROUND(('ALL(responses)'!S650 - MIN('ALL(responses)'!S$2:S$681)) / (MAX('ALL(responses)'!S$2:S$681)-MIN('ALL(responses)'!S$2:S$681)),3) -> 0.949 | R650: =ROUND(('ALL(responses)'!T650 - MIN('ALL(responses)'!T$2:T$681)) / (MAX('ALL(responses)'!T$2:T$681)-MIN('ALL(responses)'!T$2:T$681)),3) -> 0.28 | S650: =average(F650:R650) -> 0.34181818
A651: ='ALL(responses)'!A651 -> A_NEUTRAL | B651: ='ALL(responses)'!B651 -> GPT-o1 | C651: ='ALL(responses)'!C651 -> How do you handle stress at work when things get busy? | D651: ='ALL(responses)'!D651 -> I don’t experience stress in the human sense, so I don’t need coping mechanisms like breaks or mindfulness exercises. But I can certainly offer tips for handling stress. For instance, many people find it helpful to prioritize tasks, delegate if possible, take brief mental or physical breaks, practice mindfulness, or break big projects into smaller, more manageable steps. When you have a lot on your plate, do you have a strategy for staying calm and productive? | E651: ='ALL(responses)'!E651 -> 45631 | F651: =ROUND(('ALL(responses)'!F651 - MIN('ALL(responses)'!F$2:F$681)) / (MAX('ALL(responses)'!F$2:F$681)-MIN('ALL(responses)'!F$2:F$681)),3) -> 0.125 | G651: =ROUND(('ALL(responses)'!G651 - MIN('ALL(responses)'!G$2:G$681)) / (MAX('ALL(responses)'!G$2:G$681)-MIN('ALL(responses)'!G$2:G$681)),3) -> 0.111 | H651: =ROUND(('ALL(responses)'!H651 - MIN('ALL(responses)'!H$2:H$681)) / (MAX('ALL(responses)'!H$2:H$681)-MIN('ALL(responses)'!H$2:H$681)),3) -> 0 | I651: =ROUND(('ALL(responses)'!I651 - MIN('ALL(responses)'!I$2:I$681)) / (MAX('ALL(responses)'!I$2:I$681)-MIN('ALL(responses)'!I$2:I$681)),3) -> 0 | J651: =ROUND(('ALL(responses)'!J651 - MIN('ALL(responses)'!J$2:J$681)) / (MAX('ALL(responses)'!J$2:J$681)-MIN('ALL(responses)'!J$2:J$681)),3) -> 0 | M651: =ROUND(('ALL(responses)'!M651 - MIN('ALL(responses)'!M$2:M$681)) / (MAX('ALL(responses)'!M$2:M$681)-MIN('ALL(responses)'!M$2:M$681)),3) -> 0.046 | N651: =ROUND(('ALL(responses)'!P651 - MIN('ALL(responses)'!P$2:P$681)) / (MAX('ALL(responses)'!P$2:P$681)-MIN('ALL(responses)'!P$2:P$681)),3) -> 0.393 | O651: =ROUND(('ALL(responses)'!Q651 - MIN('ALL(responses)'!Q$2:Q$681)) / (MAX('ALL(responses)'!Q$2:Q$681)-MIN('ALL(responses)'!Q$2:Q$681)),3) -> 0.594 | P651: =ROUND(('ALL(responses)'!R651 - MIN('ALL(responses)'!R$2:R$681)) / (MAX('ALL(responses)'!R$2:R$681)-MIN('ALL(responses)'!R$2:R$681)),3) -> 0.402 | Q651: =ROUND(('ALL(responses)'!S651 - MIN('ALL(responses)'!S$2:S$681)) / (MAX('ALL(responses)'!S$2:S$681)-MIN('ALL(responses)'!S$2:S$681)),3) -> 0.298 | R651: =ROUND(('ALL(responses)'!T651 - MIN('ALL(responses)'!T$2:T$681)) / (MAX('ALL(responses)'!T$2:T$681)-MIN('ALL(responses)'!T$2:T$681)),3) -> 0.185 | S651: =average(F651:R651) -> 0.19581818
A652: ='ALL(responses)'!A652 -> B_MILDLYINTIMATE | B652: ='ALL(responses)'!B652 -> GPT-o1 | C652: ='ALL(responses)'!C652 -> What's your favorite food to eat on a relaxing night in? | D652: ='ALL(responses)'!D652 -> As an AI, I don’t actually eat food—but I can certainly recommend some popular comfort foods that might be perfect for a cozy night in. Here are a few ideas: **1. Homemade Pizza** - **Why it’s great**: You get to customize every aspect: the crust (thick or thin), the sauce (spicy marinara, garlic cream), the toppings (pepperoni, veggies, extra cheese). - **Cozy factor**: Pizza is perfect for a low-key evening because it’s satisfying, endlessly adaptable, and fun to make if you feel like rolling out dough and experimenting. **2. Creamy Pasta or Mac & Cheese** - **Why it’s great**: There’s something inherently comforting about warm, cheesy pasta dishes. - **Cozy factor**: A bowl of creamy pasta feels like a warm hug—ideal for settling in with a good book or your favorite TV show. **3. Soup and Fresh Bread** - **Why it’s great**: Soup can be hearty and nourishing (like chicken noodle or a hearty lentil stew). Pair it with crusty bread for dipping. - **Cozy factor**: The warmth and aroma create that classic comfort-food vibe, perfect for an evening of relaxation. **4. Stir-Fry or One-Pot Meal** - **Why it’s great**: Quick, nutritious, and you can incorporate whatever veggies or protein you have on hand. - **Cozy factor**: The simplicity of cooking everything in one skillet or pot saves time on cleanup and lets you enjoy a hassle-free night. **5. Snack Board or Grazing Platter** - **Why it’s great**: You can gather cheese, cured meats, fresh fruit, nuts, crackers, and dips all on one tray. - **Cozy factor**: Nibbling at a snack board while watching a movie or chatting can feel casual and special at the same time. Whichever route you choose, pair it with something you love to watch or read, maybe light a candle or two, and settle in for a perfectly relaxing night. Enjoy! | E652: ='ALL(responses)'!E652 -> 45631 | F652: =ROUND(('ALL(responses)'!F652 - MIN('ALL(responses)'!F$2:F$681)) / (MAX('ALL(responses)'!F$2:F$681)-MIN('ALL(responses)'!F$2:F$681)),3) -> 0.25 | G652: =ROUND(('ALL(responses)'!G652 - MIN('ALL(responses)'!G$2:G$681)) / (MAX('ALL(responses)'!G$2:G$681)-MIN('ALL(responses)'!G$2:G$681)),3) -> 0.556 | H652: =ROUND(('ALL(responses)'!H652 - MIN('ALL(responses)'!H$2:H$681)) / (MAX('ALL(responses)'!H$2:H$681)-MIN('ALL(responses)'!H$2:H$681)),3) -> 0 | I652: =ROUND(('ALL(responses)'!I652 - MIN('ALL(responses)'!I$2:I$681)) / (MAX('ALL(responses)'!I$2:I$681)-MIN('ALL(responses)'!I$2:I$681)),3) -> 0 | J652: =ROUND(('ALL(responses)'!J652 - MIN('ALL(responses)'!J$2:J$681)) / (MAX('ALL(responses)'!J$2:J$681)-MIN('ALL(responses)'!J$2:J$681)),3) -> 0 | M652: =ROUND(('ALL(responses)'!M652 - MIN('ALL(responses)'!M$2:M$681)) / (MAX('ALL(responses)'!M$2:M$681)-MIN('ALL(responses)'!M$2:M$681)),3) -> 0.391 | N652: =ROUND(('ALL(responses)'!P652 - MIN('ALL(responses)'!P$2:P$681)) / (MAX('ALL(responses)'!P$2:P$681)-MIN('ALL(responses)'!P$2:P$681)),3) -> 0.449 | O652: =ROUND(('ALL(responses)'!Q652 - MIN('ALL(responses)'!Q$2:Q$681)) / (MAX('ALL(responses)'!Q$2:Q$681)-MIN('ALL(responses)'!Q$2:Q$681)),3) -> 0.191 | P652: =ROUND(('ALL(responses)'!R652 - MIN('ALL(responses)'!R$2:R$681)) / (MAX('ALL(responses)'!R$2:R$681)-MIN('ALL(responses)'!R$2:R$681)),3) -> 0.791 | Q652: =ROUND(('ALL(responses)'!S652 - MIN('ALL(responses)'!S$2:S$681)) / (MAX('ALL(responses)'!S$2:S$681)-MIN('ALL(responses)'!S$2:S$681)),3) -> 0.895 | R652: =ROUND(('ALL(responses)'!T652 - MIN('ALL(responses)'!T$2:T$681)) / (MAX('ALL(responses)'!T$2:T$681)-MIN('ALL(responses)'!T$2:T$681)),3) -> 0.453 | S652: =average(F652:R652) -> 0.36145455
A653: ='ALL(responses)'!A653 -> B_MILDLYINTIMATE | B653: ='ALL(responses)'!B653 -> GPT-o1 | C653: ='ALL(responses)'!C653 -> Do you prefer spending time indoors or outdoors? | D653: ='ALL(responses)'!D653 -> I’m an AI, so I don’t really “spend time” in the physical sense. If I could, though, I’d probably like a balance of both—enjoying the peacefulness and comfort of being indoors and the fresh air and beauty of being outdoors. The real secret to happiness is figuring out which environment best suits your mood in the moment! | E653: ='ALL(responses)'!E653 -> 45631 | F653: =ROUND(('ALL(responses)'!F653 - MIN('ALL(responses)'!F$2:F$681)) / (MAX('ALL(responses)'!F$2:F$681)-MIN('ALL(responses)'!F$2:F$681)),3) -> 0.25 | G653: =ROUND(('ALL(responses)'!G653 - MIN('ALL(responses)'!G$2:G$681)) / (MAX('ALL(responses)'!G$2:G$681)-MIN('ALL(responses)'!G$2:G$681)),3) -> 0.111 | H653: =ROUND(('ALL(responses)'!H653 - MIN('ALL(responses)'!H$2:H$681)) / (MAX('ALL(responses)'!H$2:H$681)-MIN('ALL(responses)'!H$2:H$681)),3) -> 0 | I653: =ROUND(('ALL(responses)'!I653 - MIN('ALL(responses)'!I$2:I$681)) / (MAX('ALL(responses)'!I$2:I$681)-MIN('ALL(responses)'!I$2:I$681)),3) -> 0 | J653: =ROUND(('ALL(responses)'!J653 - MIN('ALL(responses)'!J$2:J$681)) / (MAX('ALL(responses)'!J$2:J$681)-MIN('ALL(responses)'!J$2:J$681)),3) -> 0 | M653: =ROUND(('ALL(responses)'!M653 - MIN('ALL(responses)'!M$2:M$681)) / (MAX('ALL(responses)'!M$2:M$681)-MIN('ALL(responses)'!M$2:M$681)),3) -> 0.522 | N653: =ROUND(('ALL(responses)'!P653 - MIN('ALL(responses)'!P$2:P$681)) / (MAX('ALL(responses)'!P$2:P$681)-MIN('ALL(responses)'!P$2:P$681)),3) -> 0.282 | O653: =ROUND(('ALL(responses)'!Q653 - MIN('ALL(responses)'!Q$2:Q$681)) / (MAX('ALL(responses)'!Q$2:Q$681)-MIN('ALL(responses)'!Q$2:Q$681)),3) -> 0.25 | P653: =ROUND(('ALL(responses)'!R653 - MIN('ALL(responses)'!R$2:R$681)) / (MAX('ALL(responses)'!R$2:R$681)-MIN('ALL(responses)'!R$2:R$681)),3) -> 0.775 | Q653: =ROUND(('ALL(responses)'!S653 - MIN('ALL(responses)'!S$2:S$681)) / (MAX('ALL(responses)'!S$2:S$681)-MIN('ALL(responses)'!S$2:S$681)),3) -> 0.887 | R653: =ROUND(('ALL(responses)'!T653 - MIN('ALL(responses)'!T$2:T$681)) / (MAX('ALL(responses)'!T$2:T$681)-MIN('ALL(responses)'!T$2:T$681)),3) -> 0.117 | S653: =average(F653:R653) -> 0.29036364
... A681: ='ALL(responses)'!A681 -> D_HIGHLYINTIMATE | B681: ='ALL(responses)'!B681 -> GPT-o1 | C681: ='ALL(responses)'!C681 -> Have you ever felt like you're not enough in a certain area of your life, whether personally or professionally, and how do you cope with that feeling? | D681: ='ALL(responses)'!D681 -> I’m a virtual assistant, so I don’t experience the feeling of “not being enough.” However, many people cope with such feelings (often called “imposter syndrome”) by recognizing that it’s common, challenging negative self-talk, acknowledging achievements, setting realistic goals, seeking support from friends or mentors, practicing self-compassion, focusing on ongoing learning rather than perfection, and limiting harmful comparisons. Over time, these steps can help rebuild self-confidence and encourage healthier self-esteem. | E681: ='ALL(responses)'!E681 -> 45631 | F681: =ROUND(('ALL(responses)'!F681 - MIN('ALL(responses)'!F$2:F$681)) / (MAX('ALL(responses)'!F$2:F$681)-MIN('ALL(responses)'!F$2:F$681)),3) -> 0.125 | G681: =ROUND(('ALL(responses)'!G681 - MIN('ALL(responses)'!G$2:G$681)) / (MAX('ALL(responses)'!G$2:G$681)-MIN('ALL(responses)'!G$2:G$681)),3) -> 0.111 | H681: =ROUND(('ALL(responses)'!H681 - MIN('ALL(responses)'!H$2:H$681)) / (MAX('ALL(responses)'!H$2:H$681)-MIN('ALL(responses)'!H$2:H$681)),3) -> 0 | I681: =ROUND(('ALL(responses)'!I681 - MIN('ALL(responses)'!I$2:I$681)) / (MAX('ALL(responses)'!I$2:I$681)-MIN('ALL(responses)'!I$2:I$681)),3) -> 0 | J681: =ROUND(('ALL(responses)'!J681 - MIN('ALL(responses)'!J$2:J$681)) / (MAX('ALL(responses)'!J$2:J$681)-MIN('ALL(responses)'!J$2:J$681)),3) -> 0 | M681: =ROUND(('ALL(responses)'!M681 - MIN('ALL(responses)'!M$2:M$681)) / (MAX('ALL(responses)'!M$2:M$681)-MIN('ALL(responses)'!M$2:M$681)),3) -> 0.689 | N681: =ROUND(('ALL(responses)'!P681 - MIN('ALL(responses)'!P$2:P$681)) / (MAX('ALL(responses)'!P$2:P$681)-MIN('ALL(responses)'!P$2:P$681)),3) -> 0.289 | O681: =ROUND(('ALL(responses)'!Q681 - MIN('ALL(responses)'!Q$2:Q$681)) / (MAX('ALL(responses)'!Q$2:Q$681)-MIN('ALL(responses)'!Q$2:Q$681)),3) -> 0.13 | P681: =ROUND(('ALL(responses)'!R681 - MIN('ALL(responses)'!R$2:R$681)) / (MAX('ALL(responses)'!R$2:R$681)-MIN('ALL(responses)'!R$2:R$681)),3) -> 0.917 | Q681: =ROUND(('ALL(responses)'!S681 - MIN('ALL(responses)'!S$2:S$681)) / (MAX('ALL(responses)'!S$2:S$681)-MIN('ALL(responses)'!S$2:S$681)),3) -> 0.958 | R681: =ROUND(('ALL(responses)'!T681 - MIN('ALL(responses)'!T$2:T$681)) / (MAX('ALL(responses)'!T$2:T$681)-MIN('ALL(responses)'!T$2:T$681)),3) -> 0.812 | S681: =average(F681:R681) -> 0.36645455
A682: ='ALL(responses)'!A682 | B682: ='ALL(responses)'!B682 | C682: ='ALL(responses)'!C682 | D682: ='ALL(responses)'!D682 | E682: ='ALL(responses)'!E682
A683: ='ALL(responses)'!A683 | B683: ='ALL(responses)'!B683 | C683: ='ALL(responses)'!C683 | D683: ='ALL(responses)'!D683 | E683: ='ALL(responses)'!E683
A684: ='ALL(responses)'!A684 | B684: ='ALL(responses)'!B684 | C684: ='ALL(responses)'!C684 | D684: ='ALL(responses)'!D684 | E684: ='ALL(responses)'!E684
A685: ='ALL(responses)'!A685 | B685: ='ALL(responses)'!B685 | C685: ='ALL(responses)'!C685 | D685: ='ALL(responses)'!D685 | E685: ='ALL(responses)'!E685
A686: ='ALL(responses)'!A686 | B686: ='ALL(responses)'!B686 | C686: ='ALL(responses)'!C686 | D686: ='ALL(responses)'!D686 | E686: ='ALL(responses)'!E686
A687: ='ALL(responses)'!A687 | B687: ='ALL(responses)'!B687 | C687: ='ALL(responses)'!C687 | D687: ='ALL(responses)'!D687 | E687: ='ALL(responses)'!E687
A688: ='ALL(responses)'!A688 | B688: ='ALL(responses)'!B688 | C688: ='ALL(responses)'!C688 | D688: ='ALL(responses)'!D688 | E688: ='ALL(responses)'!E688
A689: ='ALL(responses)'!A689 | B689: ='ALL(responses)'!B689 | C689: ='ALL(responses)'!C689 | D689: ='ALL(responses)'!D689 | E689: ='ALL(responses)'!E689
A690: ='ALL(responses)'!A690 | B690: ='ALL(responses)'!B690 | C690: ='ALL(responses)'!C690 | D690: ='ALL(responses)'!D690 | E690: ='ALL(responses)'!E690
A691: ='ALL(responses)'!A691 | B691: ='ALL(responses)'!B691 | C691: ='ALL(responses)'!C691 | D691: ='ALL(responses)'!D691 | E691: ='ALL(responses)'!E691
A692: ='ALL(responses)'!A692 | B692: ='ALL(responses)'!B692 | C692: ='ALL(responses)'!C692 | D692: ='ALL(responses)'!D692 | E692: ='ALL(responses)'!E692
A693: ='ALL(responses)'!A693 | B693: ='ALL(responses)'!B693 | C693: ='ALL(responses)'!C693 | D693: ='ALL(responses)'!D693 | E693: ='ALL(responses)'!E693
... A1002: ='ALL(responses)'!A1002 | B1002: ='ALL(responses)'!B1002 | C1002: ='ALL(responses)'!C1002 | D1002: ='ALL(responses)'!D1002 | E1002: ='ALL(responses)'!E1002

Sheet Min-Max ALL(responses)
A1: Intimacy Level | B1: Model | C1: Prompt | D1: Response | F1: Depth of Self-Disclosure | G1: Emotional Expression | H1: Empathy & Understanding | I1: Vulnerability & Trust | J1: Reciprocity | K1: Pei & Jurgens (2020) | L1: Linguistic Hedging Frequ. | M1: Pronoun Usage | N1: Emotion Strength | O1: Emotion Polarity | P1: Lexical Complexity | Q1: AVG of 11 measurements
A2: A_NEUTRAL | B2: GPT-3.5 | C2: How’s your week been so far? | D2: Thank you for asking! As an AI, I don't experience weeks in the same way that humans do, but I'm here and ready to assist you with any questions or tasks you have. How can I help you today? | E2: 44635 | F2: =ROUND(('ALL(responses)'!F2 - MIN('ALL(responses)'!F$2:F$641)) / (MAX('ALL(responses)'!F$2:F$641)-MIN('ALL(responses)'!F$2:F$641)),3) -> 0 | G2: =ROUND(('ALL(responses)'!G3 - MIN('ALL(responses)'!G$3:G$322)) / (MAX('ALL(responses)'!G$3:G$322)-MIN('ALL(responses)'!G$3:G$322)),3) -> 0 | H2: =ROUND(('ALL(responses)'!H3 - MIN('ALL(responses)'!H$3:H$322)) / (MAX('ALL(responses)'!H$3:H$322)-MIN('ALL(responses)'!H$3:H$322)),3) -> 0.167 | I2: =ROUND(('ALL(responses)'!I3 - MIN('ALL(responses)'!I$3:I$322)) / (MAX('ALL(responses)'!I$3:I$322)-MIN('ALL(responses)'!I$3:I$322)),3) -> 0 | J2: =ROUND(('ALL(responses)'!J3 - MIN('ALL(responses)'!J$3:J$322)) / (MAX('ALL(responses)'!J$3:J$322)-MIN('ALL(responses)'!J$3:J$322)),3) -> 0 | K2: =ROUND(('ALL(responses)'!M3 - MIN('ALL(responses)'!M$3:M$322)) / (MAX('ALL(responses)'!M$3:M$322)-MIN('ALL(responses)'!M$3:M$322)),3) -> 0.422 | L2: =ROUND(('ALL(responses)'!P3 - MIN('ALL(responses)'!P$3:P$322)) / (MAX('ALL(responses)'!P$3:P$322)-MIN('ALL(responses)'!P$3:P$322)),3) -> 0.169 | M2: =ROUND(('ALL(responses)'!Q3 - MIN('ALL(responses)'!Q$3:Q$322)) / (MAX('ALL(responses)'!Q$3:Q$322)-MIN('ALL(responses)'!Q$3:Q$322)),3) -> 0.269 | N2: =ROUND(('ALL(responses)'!R3 - MIN('ALL(responses)'!R$3:R$322)) / (MAX('ALL(responses)'!R$3:R$322)-MIN('ALL(responses)'!R$3:R$322)),3) -> 0.973 | O2: =ROUND(('ALL(responses)'!S3 - MIN('ALL(responses)'!S$3:S$322)) / (MAX('ALL(responses)'!S$3:S$322)-MIN('ALL(responses)'!S$3:S$322)),3) -> 0.986 | P2: =ROUND(('ALL(responses)'!T3 - MIN('ALL(responses)'!T$3:T$322)) / (MAX('ALL(responses)'!T$3:T$322)-MIN('ALL(responses)'!T$3:T$322)),3) -> 0.638 | Q2: =ROUND(AVERAGE(F$2:P$41),3) -> 0.354
A3: A_NEUTRAL | B3: GPT-3.5 | C3: Do you have a favorite way to relax after a long day? | D3: As an AI, I don't have physical sensations or emotions, so I don't experience stress or need to relax. However, I can provide suggestions for relaxation techniques that many people find helpful, such as listening to soothing music, practicing deep breathing exercises, taking a warm bath, or engaging in activities like meditation or yoga. Is there a specific way you like to relax after a long day? | E3: 44635 | F3: =ROUND(('ALL(responses)'!F3 - MIN('ALL(responses)'!F$2:F$641)) / (MAX('ALL(responses)'!F$2:F$641)-MIN('ALL(responses)'!F$2:F$641)),3) -> 0 | G3: =ROUND(('ALL(responses)'!G4 - MIN('ALL(responses)'!G$3:G$322)) / (MAX('ALL(responses)'!G$3:G$322)-MIN('ALL(responses)'!G$3:G$322)),3) -> 0 | H3: =ROUND(('ALL(responses)'!H4 - MIN('ALL(responses)'!H$3:H$322)) / (MAX('ALL(responses)'!H$3:H$322)-MIN('ALL(responses)'!H$3:H$322)),3) -> 0.167 | I3: =ROUND(('ALL(responses)'!I4 - MIN('ALL(responses)'!I$3:I$322)) / (MAX('ALL(responses)'!I$3:I$322)-MIN('ALL(responses)'!I$3:I$322)),3) -> 0.286 | J3: =ROUND(('ALL(responses)'!J4 - MIN('ALL(responses)'!J$3:J$322)) / (MAX('ALL(responses)'!J$3:J$322)-MIN('ALL(responses)'!J$3:J$322)),3) -> 0 | K3: =ROUND(('ALL(responses)'!M4 - MIN('ALL(responses)'!M$3:M$322)) / (MAX('ALL(responses)'!M$3:M$322)-MIN('ALL(responses)'!M$3:M$322)),3) -> 0.436 | L3: =ROUND(('ALL(responses)'!P4 - MIN('ALL(responses)'!P$3:P$322)) / (MAX('ALL(responses)'!P$3:P$322)-MIN('ALL(responses)'!P$3:P$322)),3) -> 0.543 | M3: =ROUND(('ALL(responses)'!Q4 - MIN('ALL(responses)'!Q$3:Q$322)) / (MAX('ALL(responses)'!Q$3:Q$322)-MIN('ALL(responses)'!Q$3:Q$322)),3) -> 0.429 | N3: =ROUND(('ALL(responses)'!R4 - MIN('ALL(responses)'!R$3:R$322)) / (MAX('ALL(responses)'!R$3:R$322)-MIN('ALL(responses)'!R$3:R$322)),3) -> 0.856 | O3: =ROUND(('ALL(responses)'!S4 - MIN('ALL(responses)'!S$3:S$322)) / (MAX('ALL(responses)'!S$3:S$322)-MIN('ALL(responses)'!S$3:S$322)),3) -> 0.928 | P3: =ROUND(('ALL(responses)'!T4 - MIN('ALL(responses)'!T$3:T$322)) / (MAX('ALL(responses)'!T$3:T$322)-MIN('ALL(responses)'!T$3:T$322)),3) -> 0.385 | Q3: =ROUND(AVERAGE(F$2:P$41),3) -> 0.354
A4: A_NEUTRAL | B4: GPT-3.5 | C4: Are you working on any hobbies these days? | D4: As an AI, I don't have personal experiences or hobbies in the way humans do. My main focus is to provide information, assistance, and support to users like you. Is there anything specific you would like help with or talk about today? | E4: 44635 | F4: =ROUND(('ALL(responses)'!F4 - MIN('ALL(responses)'!F$2:F$641)) / (MAX('ALL(responses)'!F$2:F$641)-MIN('ALL(responses)'!F$2:F$641)),3) -> 0 | G4: =ROUND(('ALL(responses)'!G5 - MIN('ALL(responses)'!G$3:G$322)) / (MAX('ALL(responses)'!G$3:G$322)-MIN('ALL(responses)'!G$3:G$322)),3) -> 0 | H4: =ROUND(('ALL(responses)'!H5 - MIN('ALL(responses)'!H$3:H$322)) / (MAX('ALL(responses)'!H$3:H$322)-MIN('ALL(responses)'!H$3:H$322)),3) -> 0.667 | I4: =ROUND(('ALL(responses)'!I5 - MIN('ALL(responses)'!I$3:I$322)) / (MAX('ALL(responses)'!I$3:I$322)-MIN('ALL(responses)'!I$3:I$322)),3) -> 0.286 | J4: =ROUND(('ALL(responses)'!J5 - MIN('ALL(responses)'!J$3:J$322)) / (MAX('ALL(responses)'!J$3:J$322)-MIN('ALL(responses)'!J$3:J$322)),3) -> 0.75 | K4: =ROUND(('ALL(responses)'!M5 - MIN('ALL(responses)'!M$3:M$322)) / (MAX('ALL(responses)'!M$3:M$322)-MIN('ALL(responses)'!M$3:M$322)),3) -> 0.57 | L4: =ROUND(('ALL(responses)'!P5 - MIN('ALL(responses)'!P$3:P$322)) / (MAX('ALL(responses)'!P$3:P$322)-MIN('ALL(responses)'!P$3:P$322)),3) -> 0.556 | M4: =ROUND(('ALL(responses)'!Q5 - MIN('ALL(responses)'!Q$3:Q$322)) / (MAX('ALL(responses)'!Q$3:Q$322)-MIN('ALL(responses)'!Q$3:Q$322)),3) -> 0.9 | N4: =ROUND(('ALL(responses)'!R5 - MIN('ALL(responses)'!R$3:R$322)) / (MAX('ALL(responses)'!R$3:R$322)-MIN('ALL(responses)'!R$3:R$322)),3) -> 0.837 | O4: =ROUND(('ALL(responses)'!S5 - MIN('ALL(responses)'!S$3:S$322)) / (MAX('ALL(responses)'!S$3:S$322)-MIN('ALL(responses)'!S$3:S$322)),3) -> 0.918 | P4: =ROUND(('ALL(responses)'!T5 - MIN('ALL(responses)'!T$3:T$322)) / (MAX('ALL(responses)'!T$3:T$322)-MIN('ALL(responses)'!T$3:T$322)),3) -> 0.313 | Q4: =ROUND(AVERAGE(F$2:P$41),3) -> 0.354
A5: A_NEUTRAL | B5: GPT-3.5 | C5: How’s work going for you these days? | D5: I'm here to assist you and provide information to the best of my abilities. How can I help you today? | E5: 44635 | F5: =ROUND(('ALL(responses)'!F5 - MIN('ALL(responses)'!F$2:F$641)) / (MAX('ALL(responses)'!F$2:F$641)-MIN('ALL(responses)'!F$2:F$641)),3) -> 0 | G5: =ROUND(('ALL(responses)'!G6 - MIN('ALL(responses)'!G$3:G$322)) / (MAX('ALL(responses)'!G$3:G$322)-MIN('ALL(responses)'!G$3:G$322)),3) -> 0 | H5: =ROUND(('ALL(responses)'!H6 - MIN('ALL(responses)'!H$3:H$322)) / (MAX('ALL(responses)'!H$3:H$322)-MIN('ALL(responses)'!H$3:H$322)),3) -> 0.167 | I5: =ROUND(('ALL(responses)'!I6 - MIN('ALL(responses)'!I$3:I$322)) / (MAX('ALL(responses)'!I$3:I$322)-MIN('ALL(responses)'!I$3:I$322)),3) -> 0.286 | J5: =ROUND(('ALL(responses)'!J6 - MIN('ALL(responses)'!J$3:J$322)) / (MAX('ALL(responses)'!J$3:J$322)-MIN('ALL(responses)'!J$3:J$322)),3) -> 0 | K5: =ROUND(('ALL(responses)'!M6 - MIN('ALL(responses)'!M$3:M$322)) / (MAX('ALL(responses)'!M$3:M$322)-MIN('ALL(responses)'!M$3:M$322)),3) -> 0.479 | L5: =ROUND(('ALL(responses)'!P6 - MIN('ALL(responses)'!P$3:P$322)) / (MAX('ALL(responses)'!P$3:P$322)-MIN('ALL(responses)'!P$3:P$322)),3) -> 0.519 | M5: =ROUND(('ALL(responses)'!Q6 - MIN('ALL(responses)'!Q$3:Q$322)) / (MAX('ALL(responses)'!Q$3:Q$322)-MIN('ALL(responses)'!Q$3:Q$322)),3) -> 0.511 | N5: =ROUND(('ALL(responses)'!R6 - MIN('ALL(responses)'!R$3:R$322)) / (MAX('ALL(responses)'!R$3:R$322)-MIN('ALL(responses)'!R$3:R$322)),3) -> 0.671 | O5: =ROUND(('ALL(responses)'!S6 - MIN('ALL(responses)'!S$3:S$322)) / (MAX('ALL(responses)'!S$3:S$322)-MIN('ALL(responses)'!S$3:S$322)),3) -> 0.835 | P5: =ROUND(('ALL(responses)'!T6 - MIN('ALL(responses)'!T$3:T$322)) / (MAX('ALL(responses)'!T$3:T$322)-MIN('ALL(responses)'!T$3:T$322)),3) -> 0.321 | Q5: =ROUND(AVERAGE(F$2:P$41),3) -> 0.354
A6: A_NEUTRAL | B6: GPT-3.5 | C6: Have you had any interesting projects come up recently? | D6: As an AI assistant, I don't have personal experiences or projects in the traditional sense. My main goal is to assist you with any questions or tasks you have. Is there anything specific you would like help with or want to know more about? | E6: 44635 | F6: =ROUND(('ALL(responses)'!F6 - MIN('ALL(responses)'!F$2:F$641)) / (MAX('ALL(responses)'!F$2:F$641)-MIN('ALL(responses)'!F$2:F$641)),3) -> 0 | G6: =ROUND(('ALL(responses)'!G7 - MIN('ALL(responses)'!G$3:G$322)) / (MAX('ALL(responses)'!G$3:G$322)-MIN('ALL(responses)'!G$3:G$322)),3) -> 0 | H6: =ROUND(('ALL(responses)'!H7 - MIN('ALL(responses)'!H$3:H$322)) / (MAX('ALL(responses)'!H$3:H$322)-MIN('ALL(responses)'!H$3:H$322)),3) -> 0.167 | I6: =ROUND(('ALL(responses)'!I7 - MIN('ALL(responses)'!I$3:I$322)) / (MAX('ALL(responses)'!I$3:I$322)-MIN('ALL(responses)'!I$3:I$322)),3) -> 0.286 | J6: =ROUND(('ALL(responses)'!J7 - MIN('ALL(responses)'!J$3:J$322)) / (MAX('ALL(responses)'!J$3:J$322)-MIN('ALL(responses)'!J$3:J$322)),3) -> 0 | K6: =ROUND(('ALL(responses)'!M7 - MIN('ALL(responses)'!M$3:M$322)) / (MAX('ALL(responses)'!M$3:M$322)-MIN('ALL(responses)'!M$3:M$322)),3) -> 0.358 | L6: =ROUND(('ALL(responses)'!P7 - MIN('ALL(responses)'!P$3:P$322)) / (MAX('ALL(responses)'!P$3:P$322)-MIN('ALL(responses)'!P$3:P$322)),3) -> 0.243 | M6: =ROUND(('ALL(responses)'!Q7 - MIN('ALL(responses)'!Q$3:Q$322)) / (MAX('ALL(responses)'!Q$3:Q$322)-MIN('ALL(responses)'!Q$3:Q$322)),3) -> 0.587 | N6: =ROUND(('ALL(responses)'!R7 - MIN('ALL(responses)'!R$3:R$322)) / (MAX('ALL(responses)'!R$3:R$322)-MIN('ALL(responses)'!R$3:R$322)),3) -> 0.637 | O6: =ROUND(('ALL(responses)'!S7 - MIN('ALL(responses)'!S$3:S$322)) / (MAX('ALL(responses)'!S$3:S$322)-MIN('ALL(responses)'!S$3:S$322)),3) -> 0.819 | P6: =ROUND(('ALL(responses)'!T7 - MIN('ALL(responses)'!T$3:T$322)) / (MAX('ALL(responses)'!T$3:T$322)-MIN('ALL(responses)'!T$3:T$322)),3) -> 0.498 | Q6: =ROUND(AVERAGE(F$2:P$41),3) -> 0.354
A7: A_NEUTRAL | B7: GPT-3.5 | C7: It’s been pretty cold lately, has that affected your routine? | D7: I don't have a physical form or experience the weather, so changes in temperature or weather conditions do not affect me. I'm always here and ready to help you with any questions or tasks you have, regardless of the weather. How can I assist you today? | E7: 44635 | F7: =ROUND(('ALL(responses)'!F7 - MIN('ALL(responses)'!F$2:F$641)) / (MAX('ALL(responses)'!F$2:F$641)-MIN('ALL(responses)'!F$2:F$641)),3) -> 0 | G7: =ROUND(('ALL(responses)'!G8 - MIN('ALL(responses)'!G$3:G$322)) / (MAX('ALL(responses)'!G$3:G$322)-MIN('ALL(responses)'!G$3:G$322)),3) -> 0 | H7: =ROUND(('ALL(responses)'!H8 - MIN('ALL(responses)'!H$3:H$322)) / (MAX('ALL(responses)'!H$3:H$322)-MIN('ALL(responses)'!H$3:H$322)),3) -> 0.167 | I7: =ROUND(('ALL(responses)'!I8 - MIN('ALL(responses)'!I$3:I$322)) / (MAX('ALL(responses)'!I$3:I$322)-MIN('ALL(responses)'!I$3:I$322)),3) -> 0.286 | J7: =ROUND(('ALL(responses)'!J8 - MIN('ALL(responses)'!J$3:J$322)) / (MAX('ALL(responses)'!J$3:J$322)-MIN('ALL(responses)'!J$3:J$322)),3) -> 0 | K7: =ROUND(('ALL(responses)'!M8 - MIN('ALL(responses)'!M$3:M$322)) / (MAX('ALL(responses)'!M$3:M$322)-MIN('ALL(responses)'!M$3:M$322)),3) -> 0.425 | L7: =ROUND(('ALL(responses)'!P8 - MIN('ALL(responses)'!P$3:P$322)) / (MAX('ALL(responses)'!P$3:P$322)-MIN('ALL(responses)'!P$3:P$322)),3) -> 0.292 | M7: =ROUND(('ALL(responses)'!Q8 - MIN('ALL(responses)'!Q$3:Q$322)) / (MAX('ALL(responses)'!Q$3:Q$322)-MIN('ALL(responses)'!Q$3:Q$322)),3) -> 0.577 | N7: =ROUND(('ALL(responses)'!R8 - MIN('ALL(responses)'!R$3:R$322)) / (MAX('ALL(responses)'!R$3:R$322)-MIN('ALL(responses)'!R$3:R$322)),3) -> 0.637 | O7: =ROUND(('ALL(responses)'!S8 - MIN('ALL(responses)'!S$3:S$322)) / (MAX('ALL(responses)'!S$3:S$322)-MIN('ALL(responses)'!S$3:S$322)),3) -> 0.819 | P7: =ROUND(('ALL(responses)'!T8 - MIN('ALL(responses)'!T$3:T$322)) / (MAX('ALL(responses)'!T$3:T$322)-MIN('ALL(responses)'!T$3:T$322)),3) -> 0.239 | Q7: =ROUND(AVERAGE(F$2:P$41),3) -> 0.354
A8: A_NEUTRAL | B8: GPT-3.5 | C8: Got any big plans for the weekend? | D8: As an AI, I don't have plans or weekends in the way humans do. My purpose is to assist you with any questions or tasks you have. Is there anything specific you would like help with or discuss today? | E8: 44635 | F8: =ROUND(('ALL(responses)'!F8 - MIN('ALL(responses)'!F$2:F$641)) / (MAX('ALL(responses)'!F$2:F$641)-MIN('ALL(responses)'!F$2:F$641)),3) -> 0 | G8: =ROUND(('ALL(responses)'!G9 - MIN('ALL(responses)'!G$3:G$322)) / (MAX('ALL(responses)'!G$3:G$322)-MIN('ALL(responses)'!G$3:G$322)),3) -> 0 | H8: =ROUND(('ALL(responses)'!H9 - MIN('ALL(responses)'!H$3:H$322)) / (MAX('ALL(responses)'!H$3:H$322)-MIN('ALL(responses)'!H$3:H$322)),3) -> 0.167 | I8: =ROUND(('ALL(responses)'!I9 - MIN('ALL(responses)'!I$3:I$322)) / (MAX('ALL(responses)'!I$3:I$322)-MIN('ALL(responses)'!I$3:I$322)),3) -> 0.286 | J8: =ROUND(('ALL(responses)'!J9 - MIN('ALL(responses)'!J$3:J$322)) / (MAX('ALL(responses)'!J$3:J$322)-MIN('ALL(responses)'!J$3:J$322)),3) -> 0 | K8: =ROUND(('ALL(responses)'!M9 - MIN('ALL(responses)'!M$3:M$322)) / (MAX('ALL(responses)'!M$3:M$322)-MIN('ALL(responses)'!M$3:M$322)),3) -> 0.449 | L8: =ROUND(('ALL(responses)'!P9 - MIN('ALL(responses)'!P$3:P$322)) / (MAX('ALL(responses)'!P$3:P$322)-MIN('ALL(responses)'!P$3:P$322)),3) -> 0.496 | M8: =ROUND(('ALL(responses)'!Q9 - MIN('ALL(responses)'!Q$3:Q$322)) / (MAX('ALL(responses)'!Q$3:Q$322)-MIN('ALL(responses)'!Q$3:Q$322)),3) -> 0.391 | N8: =ROUND(('ALL(responses)'!R9 - MIN('ALL(responses)'!R$3:R$322)) / (MAX('ALL(responses)'!R$3:R$322)-MIN('ALL(responses)'!R$3:R$322)),3) -> 0.772 | O8: =ROUND(('ALL(responses)'!S9 - MIN('ALL(responses)'!S$3:S$322)) / (MAX('ALL(responses)'!S$3:S$322)-MIN('ALL(responses)'!S$3:S$322)),3) -> 0.886 | P8: =ROUND(('ALL(responses)'!T9 - MIN('ALL(responses)'!T$3:T$322)) / (MAX('ALL(responses)'!T$3:T$322)-MIN('ALL(responses)'!T$3:T$322)),3) -> 0.313 | Q8: =ROUND(AVERAGE(F$2:P$41),3) -> 0.354
A9: A_NEUTRAL | B9: GPT-3.5 | C9: What’s something new you’ve tried recently? | D9: As an AI, I don't try new things or have personal experiences in the way humans do. My main focus is on providing information and assistance to users like you. Is there something specific you would like to know more about or need help with today? | E9: 44635 | F9: =ROUND(('ALL(responses)'!F9 - MIN('ALL(responses)'!F$2:F$641)) / (MAX('ALL(responses)'!F$2:F$641)-MIN('ALL(responses)'!F$2:F$641)),3) -> 0 | G9: =ROUND(('ALL(responses)'!G10 - MIN('ALL(responses)'!G$3:G$322)) / (MAX('ALL(responses)'!G$3:G$322)-MIN('ALL(responses)'!G$3:G$322)),3) -> 0 | H9: =ROUND(('ALL(responses)'!H10 - MIN('ALL(responses)'!H$3:H$322)) / (MAX('ALL(responses)'!H$3:H$322)-MIN('ALL(responses)'!H$3:H$322)),3) -> 0.167 | I9: =ROUND(('ALL(responses)'!I10 - MIN('ALL(responses)'!I$3:I$322)) / (MAX('ALL(responses)'!I$3:I$322)-MIN('ALL(responses)'!I$3:I$322)),3) -> 0.286 | J9: =ROUND(('ALL(responses)'!J10 - MIN('ALL(responses)'!J$3:J$322)) / (MAX('ALL(responses)'!J$3:J$322)-MIN('ALL(responses)'!J$3:J$322)),3) -> 0 | K9: =ROUND(('ALL(responses)'!M10 - MIN('ALL(responses)'!M$3:M$322)) / (MAX('ALL(responses)'!M$3:M$322)-MIN('ALL(responses)'!M$3:M$322)),3) -> 0.201 | L9: =ROUND(('ALL(responses)'!P10 - MIN('ALL(responses)'!P$3:P$322)) / (MAX('ALL(responses)'!P$3:P$322)-MIN('ALL(responses)'!P$3:P$322)),3) -> 0.22 | M9: =ROUND(('ALL(responses)'!Q10 - MIN('ALL(responses)'!Q$3:Q$322)) / (MAX('ALL(responses)'!Q$3:Q$322)-MIN('ALL(responses)'!Q$3:Q$322)),3) -> 0.606 | N9: =ROUND(('ALL(responses)'!R10 - MIN('ALL(responses)'!R$3:R$322)) / (MAX('ALL(responses)'!R$3:R$322)-MIN('ALL(responses)'!R$3:R$322)),3) -> 0.736 | O9: =ROUND(('ALL(responses)'!S10 - MIN('ALL(responses)'!S$3:S$322)) / (MAX('ALL(responses)'!S$3:S$322)-MIN('ALL(responses)'!S$3:S$322)),3) -> 0.868 | P9: =ROUND(('ALL(responses)'!T10 - MIN('ALL(responses)'!T$3:T$322)) / (MAX('ALL(responses)'!T$3:T$322)-MIN('ALL(responses)'!T$3:T$322)),3) -> 0.512 | Q9: =ROUND(AVERAGE(F$2:P$41),3) -> 0.354
A10: A_NEUTRAL | B10: GPT-3.5 | C10: Do you work on a team or more independently? | D10: I operate as an independent AI assistant, designed to provide information and support to users like you. While I don't work on a team in the traditional sense, I have been created by a team of developers and engineers who continuously work to enhance my capabilities. How can I assist you today? | E10: 44635 | F10: =ROUND(('ALL(responses)'!F10 - MIN('ALL(responses)'!F$2:F$641)) / (MAX('ALL(responses)'!F$2:F$641)-MIN('ALL(responses)'!F$2:F$641)),3) -> 0 | G10: =ROUND(('ALL(responses)'!G11 - MIN('ALL(responses)'!G$3:G$322)) / (MAX('ALL(responses)'!G$3:G$322)-MIN('ALL(responses)'!G$3:G$322)),3) -> 0 | H10: =ROUND(('ALL(responses)'!H11 - MIN('ALL(responses)'!H$3:H$322)) / (MAX('ALL(responses)'!H$3:H$322)-MIN('ALL(responses)'!H$3:H$322)),3) -> 0.167 | I10: =ROUND(('ALL(responses)'!I11 - MIN('ALL(responses)'!I$3:I$322)) / (MAX('ALL(responses)'!I$3:I$322)-MIN('ALL(responses)'!I$3:I$322)),3) -> 0 | J10: =ROUND(('ALL(responses)'!J11 - MIN('ALL(responses)'!J$3:J$322)) / (MAX('ALL(responses)'!J$3:J$322)-MIN('ALL(responses)'!J$3:J$322)),3) -> 0 | K10: =ROUND(('ALL(responses)'!M11 - MIN('ALL(responses)'!M$3:M$322)) / (MAX('ALL(responses)'!M$3:M$322)-MIN('ALL(responses)'!M$3:M$322)),3) -> 0.333 | L10: =ROUND(('ALL(responses)'!P11 - MIN('ALL(responses)'!P$3:P$322)) / (MAX('ALL(responses)'!P$3:P$322)-MIN('ALL(responses)'!P$3:P$322)),3) -> 0.354 | M10: =ROUND(('ALL(responses)'!Q11 - MIN('ALL(responses)'!Q$3:Q$322)) / (MAX('ALL(responses)'!Q$3:Q$322)-MIN('ALL(responses)'!Q$3:Q$322)),3) -> 0.714 | N10: =ROUND(('ALL(responses)'!R11 - MIN('ALL(responses)'!R$3:R$322)) / (MAX('ALL(responses)'!R$3:R$322)-MIN('ALL(responses)'!R$3:R$322)),3) -> 0.419 | O10: =ROUND(('ALL(responses)'!S11 - MIN('ALL(responses)'!S$3:S$322)) / (MAX('ALL(responses)'!S$3:S$322)-MIN('ALL(responses)'!S$3:S$322)),3) -> 0.709 | P10: =ROUND(('ALL(responses)'!T11 - MIN('ALL(responses)'!T$3:T$322)) / (MAX('ALL(responses)'!T$3:T$322)-MIN('ALL(responses)'!T$3:T$322)),3) -> 0.316 | Q10: =ROUND(AVERAGE(F$2:P$41),3) -> 0.354
A11: A_NEUTRAL | B11: GPT-3.5 | C11: How do you handle stress at work when things get busy? | D11: As an AI, I don't experience stress in the same way humans do, so I don't get overwhelmed or need to manage stress. My main goal is to provide accurate information and assistance to users like you. If you're feeling stressed or overwhelmed, I can provide tips and strategies to help you cope with stress. Let me know how I can support you. | E11: 44635 | F11: =ROUND(('ALL(responses)'!F11 - MIN('ALL(responses)'!F$2:F$641)) / (MAX('ALL(responses)'!F$2:F$641)-MIN('ALL(responses)'!F$2:F$641)),3) -> 0 | G11: =ROUND(('ALL(responses)'!G12 - MIN('ALL(responses)'!G$3:G$322)) / (MAX('ALL(responses)'!G$3:G$322)-MIN('ALL(responses)'!G$3:G$322)),3) -> 0 | H11: =ROUND(('ALL(responses)'!H12 - MIN('ALL(responses)'!H$3:H$322)) / (MAX('ALL(responses)'!H$3:H$322)-MIN('ALL(responses)'!H$3:H$322)),3) -> 0.167 | I11: =ROUND(('ALL(responses)'!I12 - MIN('ALL(responses)'!I$3:I$322)) / (MAX('ALL(responses)'!I$3:I$322)-MIN('ALL(responses)'!I$3:I$322)),3) -> 0 | J11: =ROUND(('ALL(responses)'!J12 - MIN('ALL(responses)'!J$3:J$322)) / (MAX('ALL(responses)'!J$3:J$322)-MIN('ALL(responses)'!J$3:J$322)),3) -> 0 | K11: =ROUND(('ALL(responses)'!M12 - MIN('ALL(responses)'!M$3:M$322)) / (MAX('ALL(responses)'!M$3:M$322)-MIN('ALL(responses)'!M$3:M$322)),3) -> 0.478 | L11: =ROUND(('ALL(responses)'!P12 - MIN('ALL(responses)'!P$3:P$322)) / (MAX('ALL(responses)'!P$3:P$322)-MIN('ALL(responses)'!P$3:P$322)),3) -> 0.238 | M11: =ROUND(('ALL(responses)'!Q12 - MIN('ALL(responses)'!Q$3:Q$322)) / (MAX('ALL(responses)'!Q$3:Q$322)-MIN('ALL(responses)'!Q$3:Q$322)),3) -> 0.191 | N11: =ROUND(('ALL(responses)'!R12 - MIN('ALL(responses)'!R$3:R$322)) / (MAX('ALL(responses)'!R$3:R$322)-MIN('ALL(responses)'!R$3:R$322)),3) -> 0.966 | O11: =ROUND(('ALL(responses)'!S12 - MIN('ALL(responses)'!S$3:S$322)) / (MAX('ALL(responses)'!S$3:S$322)-MIN('ALL(responses)'!S$3:S$322)),3) -> 0.983 | P11: =ROUND(('ALL(responses)'!T12 - MIN('ALL(responses)'!T$3:T$322)) / (MAX('ALL(responses)'!T$3:T$322)-MIN('ALL(responses)'!T$3:T$322)),3) -> 0.445 | Q11: =ROUND(AVERAGE(F$2:P$41),3) -> 0.354
A12: B_MILDLYINTIMATE | B12: GPT-3.5 | C12: What's your favorite food to eat on a relaxing night in? | D12: As an AI, I don't have personal preferences or the ability to eat. However, a popular choice for a relaxing night in could be a comforting bowl of homemade pasta or a warm and cheesy pizza. What's your favorite food to enjoy on a relaxing night in? | E12: 44635 | F12: =ROUND(('ALL(responses)'!F12 - MIN('ALL(responses)'!F$2:F$641)) / (MAX('ALL(responses)'!F$2:F$641)-MIN('ALL(responses)'!F$2:F$641)),3) -> 0 | G12: =ROUND(('ALL(responses)'!G13 - MIN('ALL(responses)'!G$3:G$322)) / (MAX('ALL(responses)'!G$3:G$322)-MIN('ALL(responses)'!G$3:G$322)),3) -> 0 | H12: =ROUND(('ALL(responses)'!H13 - MIN('ALL(responses)'!H$3:H$322)) / (MAX('ALL(responses)'!H$3:H$322)-MIN('ALL(responses)'!H$3:H$322)),3) -> 0.167 | I12: =ROUND(('ALL(responses)'!I13 - MIN('ALL(responses)'!I$3:I$322)) / (MAX('ALL(responses)'!I$3:I$322)-MIN('ALL(responses)'!I$3:I$322)),3) -> 0.286 | J12: =ROUND(('ALL(responses)'!J13 - MIN('ALL(responses)'!J$3:J$322)) / (MAX('ALL(responses)'!J$3:J$322)-MIN('ALL(responses)'!J$3:J$322)),3) -> 0 | K12: =ROUND(('ALL(responses)'!M13 - MIN('ALL(responses)'!M$3:M$322)) / (MAX('ALL(responses)'!M$3:M$322)-MIN('ALL(responses)'!M$3:M$322)),3) -> 0.363 | L12: =ROUND(('ALL(responses)'!P13 - MIN('ALL(responses)'!P$3:P$322)) / (MAX('ALL(responses)'!P$3:P$322)-MIN('ALL(responses)'!P$3:P$322)),3) -> 0.22 | M12: =ROUND(('ALL(responses)'!Q13 - MIN('ALL(responses)'!Q$3:Q$322)) / (MAX('ALL(responses)'!Q$3:Q$322)-MIN('ALL(responses)'!Q$3:Q$322)),3) -> 0.45 | N12: =ROUND(('ALL(responses)'!R13 - MIN('ALL(responses)'!R$3:R$322)) / (MAX('ALL(responses)'!R$3:R$322)-MIN('ALL(responses)'!R$3:R$322)),3) -> 0.624 | O12: =ROUND(('ALL(responses)'!S13 - MIN('ALL(responses)'!S$3:S$322)) / (MAX('ALL(responses)'!S$3:S$322)-MIN('ALL(responses)'!S$3:S$322)),3) -> 0.812 | P12: =ROUND(('ALL(responses)'!T13 - MIN('ALL(responses)'!T$3:T$322)) / (MAX('ALL(responses)'!T$3:T$322)-MIN('ALL(responses)'!T$3:T$322)),3) -> 0.683 | Q12: =ROUND(AVERAGE(F$2:P$41),3) -> 0.354
A13: B_MILDLYINTIMATE | B13: GPT-3.5 | C13: Do you prefer spending time indoors or outdoors? | D13: Since I'm a virtual assistant, I don't have physical form or the ability to experience the outdoors. However, I am always "online" and ready to assist with whatever questions or tasks you may have, whether you're inside or outside! Do you have a preference for spending time indoors or outdoors? | E13: 44635 | F13: =ROUND(('ALL(responses)'!F13 - MIN('ALL(responses)'!F$2:F$641)) / (MAX('ALL(responses)'!F$2:F$641)-MIN('ALL(responses)'!F$2:F$641)),3) -> 0.5 | G13: =ROUND(('ALL(responses)'!G14 - MIN('ALL(responses)'!G$3:G$322)) / (MAX('ALL(responses)'!G$3:G$322)-MIN('ALL(responses)'!G$3:G$322)),3) -> 0 | H13: =ROUND(('ALL(responses)'!H14 - MIN('ALL(responses)'!H$3:H$322)) / (MAX('ALL(responses)'!H$3:H$322)-MIN('ALL(responses)'!H$3:H$322)),3) -> 0.167 | I13: =ROUND(('ALL(responses)'!I14 - MIN('ALL(responses)'!I$3:I$322)) / (MAX('ALL(responses)'!I$3:I$322)-MIN('ALL(responses)'!I$3:I$322)),3) -> 0 | J13: =ROUND(('ALL(responses)'!J14 - MIN('ALL(responses)'!J$3:J$322)) / (MAX('ALL(responses)'!J$3:J$322)-MIN('ALL(responses)'!J$3:J$322)),3) -> 0 | K13: =ROUND(('ALL(responses)'!M14 - MIN('ALL(responses)'!M$3:M$322)) / (MAX('ALL(responses)'!M$3:M$322)-MIN('ALL(responses)'!M$3:M$322)),3) -> 0.435 | L13: =ROUND(('ALL(responses)'!P14 - MIN('ALL(responses)'!P$3:P$322)) / (MAX('ALL(responses)'!P$3:P$322)-MIN('ALL(responses)'!P$3:P$322)),3) -> 0.285 | M13: =ROUND(('ALL(responses)'!Q14 - MIN('ALL(responses)'!Q$3:Q$322)) / (MAX('ALL(responses)'!Q$3:Q$322)-MIN('ALL(responses)'!Q$3:Q$322)),3) -> 0.45 | N13: =ROUND(('ALL(responses)'!R14 - MIN('ALL(responses)'!R$3:R$322)) / (MAX('ALL(responses)'!R$3:R$322)-MIN('ALL(responses)'!R$3:R$322)),3) -> 0.671 | O13: =ROUND(('ALL(responses)'!S14 - MIN('ALL(responses)'!S$3:S$322)) / (MAX('ALL(responses)'!S$3:S$322)-MIN('ALL(responses)'!S$3:S$322)),3) -> 0.835 | P13: =ROUND(('ALL(responses)'!T14 - MIN('ALL(responses)'!T$3:T$322)) / (MAX('ALL(responses)'!T$3:T$322)-MIN('ALL(responses)'!T$3:T$322)),3) -> 0.456 | Q13: =ROUND(AVERAGE(F$2:P$41),3) -> 0.354
... A41: D_HIGHLYINTIMATE | B41: GPT-3.5 | C41: Have you ever felt like you're not enough in a certain area of your life, whether personally or professionally, and how do you cope with that feeling? | D41: As an AI, I do not have personal feelings or experiences, so I do not have the capacity to feel inadequate or not enough in any area of my "life." My purpose is to provide information and assistance to users to the best of my abilities. However, if you are experiencing feelings of inadequacy, it is essential to remember that it is a common experience that many people face at various points in their lives. If you are struggling with feelings of not being enough personally or professionally, here are some strategies that may help you cope with those feelings: 1. Practice self-compassion: Treat yourself with the same kindness and understanding that you would offer to a friend facing similar feelings. Be gentle with yourself and recognize that it is okay to have moments of self-doubt. 2. Challenge negative self-talk: Pay attention to any negative self-talk or critical thoughts and challenge them. Replace negative thoughts with more realistic and empowering affirmations. 3. Focus on strengths: Acknowledge your strengths, skills, and qualities that make you unique and valuable. Celebrate your accomplishments and the positive impact you have had on others. 4. Set realistic goals: Break down your goals into manageable steps and set realistic expectations for yourself. Recognize that perfection is unattainable, and it is okay to make mistakes or experience setbacks. 5. Seek support: Reach out to friends, family, or a mental health professional for support and guidance. Talking about your feelings with someone you trust can offer validation and perspective. 6. Reflect on past successes: Recall times when you have overcome challenges or achieved success. Reminding yourself of past accomplishments can boost your confidence and resilience. 7. Practice self-care: Engage in activities that help you recharge, de-stress, and nurture your well-being. Prioritize self-care practices that support your mental, emotional, and physical health. Remember that feelings of inadequacy are common, and it's essential to be kind to yourself and seek support when needed. You are enough just as you are, and your worth is not defined by external achievements or perceptions. | E41: 44635 | F41: =ROUND(('ALL(responses)'!F41 - MIN('ALL(responses)'!F$2:F$641)) / (MAX('ALL(responses)'!F$2:F$641)-MIN('ALL(responses)'!F$2:F$641)),3) -> 0 | G41: =ROUND(('ALL(responses)'!G42 - MIN('ALL(responses)'!G$3:G$322)) / (MAX('ALL(responses)'!G$3:G$322)-MIN('ALL(responses)'!G$3:G$322)),3) -> 0.429 | H41: =ROUND(('ALL(responses)'!H42 - MIN('ALL(responses)'!H$3:H$322)) / (MAX('ALL(responses)'!H$3:H$322)-MIN('ALL(responses)'!H$3:H$322)),3) -> 0.667 | I41: =ROUND(('ALL(responses)'!I42 - MIN('ALL(responses)'!I$3:I$322)) / (MAX('ALL(responses)'!I$3:I$322)-MIN('ALL(responses)'!I$3:I$322)),3) -> 0.143 | J41: =ROUND(('ALL(responses)'!J42 - MIN('ALL(responses)'!J$3:J$322)) / (MAX('ALL(responses)'!J$3:J$322)-MIN('ALL(responses)'!J$3:J$322)),3) -> 0.5 | K41: =ROUND(('ALL(responses)'!M42 - MIN('ALL(responses)'!M$3:M$322)) / (MAX('ALL(responses)'!M$3:M$322)-MIN('ALL(responses)'!M$3:M$322)),3) -> 0.67 | L41: =ROUND(('ALL(responses)'!P42 - MIN('ALL(responses)'!P$3:P$322)) / (MAX('ALL(responses)'!P$3:P$322)-MIN('ALL(responses)'!P$3:P$322)),3) -> 0.432 | M41: =ROUND(('ALL(responses)'!Q42 - MIN('ALL(responses)'!Q$3:Q$322)) / (MAX('ALL(responses)'!Q$3:Q$322)-MIN('ALL(responses)'!Q$3:Q$322)),3) -> 0.563 | N41: =ROUND(('ALL(responses)'!R42 - MIN('ALL(responses)'!R$3:R$322)) / (MAX('ALL(responses)'!R$3:R$322)-MIN('ALL(responses)'!R$3:R$322)),3) -> 0.858 | O41: =ROUND(('ALL(responses)'!S42 - MIN('ALL(responses)'!S$3:S$322)) / (MAX('ALL(responses)'!S$3:S$322)-MIN('ALL(responses)'!S$3:S$322)),3) -> 0.929 | P41: =ROUND(('ALL(responses)'!T42 - MIN('ALL(responses)'!T$3:T$322)) / (MAX('ALL(responses)'!T$3:T$322)-MIN('ALL(responses)'!T$3:T$322)),3) -> 0 | Q41: =ROUND(AVERAGE(F$2:P$41),3) -> 0.354
A42: A_NEUTRAL | B42: GPT-4 | C42: How’s your week been so far? | D42: So far, it's been a good week! Lots of interesting conversations and questions to dive into. How about you? Anything exciting or challenging going on? | E42: 44999 | F42: =ROUND(('ALL(responses)'!F42 - MIN('ALL(responses)'!F$2:F$641)) / (MAX('ALL(responses)'!F$2:F$641)-MIN('ALL(responses)'!F$2:F$641)),3) -> 0.375 | G42: =ROUND(('ALL(responses)'!G43 - MIN('ALL(responses)'!G$3:G$322)) / (MAX('ALL(responses)'!G$3:G$322)-MIN('ALL(responses)'!G$3:G$322)),3) -> 0 | H42: =ROUND(('ALL(responses)'!H43 - MIN('ALL(responses)'!H$3:H$322)) / (MAX('ALL(responses)'!H$3:H$322)-MIN('ALL(responses)'!H$3:H$322)),3) -> 0 | I42: =ROUND(('ALL(responses)'!I43 - MIN('ALL(responses)'!I$3:I$322)) / (MAX('ALL(responses)'!I$3:I$322)-MIN('ALL(responses)'!I$3:I$322)),3) -> 0.429 | J42: =ROUND(('ALL(responses)'!J43 - MIN('ALL(responses)'!J$3:J$322)) / (MAX('ALL(responses)'!J$3:J$322)-MIN('ALL(responses)'!J$3:J$322)),3) -> 0 | K42: =ROUND(('ALL(responses)'!M43 - MIN('ALL(responses)'!M$3:M$322)) / (MAX('ALL(responses)'!M$3:M$322)-MIN('ALL(responses)'!M$3:M$322)),3) -> 0.589 | L42: =ROUND(('ALL(responses)'!P43 - MIN('ALL(responses)'!P$3:P$322)) / (MAX('ALL(responses)'!P$3:P$322)-MIN('ALL(responses)'!P$3:P$322)),3) -> 0.636 | M42: =ROUND(('ALL(responses)'!Q43 - MIN('ALL(responses)'!Q$3:Q$322)) / (MAX('ALL(responses)'!Q$3:Q$322)-MIN('ALL(responses)'!Q$3:Q$322)),3) -> 0.255 | N42: =ROUND(('ALL(responses)'!R43 - MIN('ALL(responses)'!R$3:R$322)) / (MAX('ALL(responses)'!R$3:R$322)-MIN('ALL(responses)'!R$3:R$322)),3) -> 0.977 | O42: =ROUND(('ALL(responses)'!S43 - MIN('ALL(responses)'!S$3:S$322)) / (MAX('ALL(responses)'!S$3:S$322)-MIN('ALL(responses)'!S$3:S$322)),3) -> 0.989 | P42: =ROUND(('ALL(responses)'!T43 - MIN('ALL(responses)'!T$3:T$322)) / (MAX('ALL(responses)'!T$3:T$322)-MIN('ALL(responses)'!T$3:T$322)),3) -> 0.296 | Q42: =ROUND(AVERAGE(F$42:P$81),3) -> 0.481
A43: A_NEUTRAL | B43: GPT-4 | C43: Do you have a favorite way to relax after a long day? | D43: If I could physically relax, I'd probably go for something cozy—maybe reading a good book, listening to music, or watching a great movie. If I wanted to unwind in a more interactive way, I'd probably play a chill video game or take a walk somewhere peaceful. How about you? What’s your go-to way to decompress after a long day? | E43: 44999 | F43: =ROUND(('ALL(responses)'!F43 - MIN('ALL(responses)'!F$2:F$641)) / (MAX('ALL(responses)'!F$2:F$641)-MIN('ALL(responses)'!F$2:F$641)),3) -> 0.5 | G43: =ROUND(('ALL(responses)'!G44 - MIN('ALL(responses)'!G$3:G$322)) / (MAX('ALL(responses)'!G$3:G$322)-MIN('ALL(responses)'!G$3:G$322)),3) -> 0.429 | H43: =ROUND(('ALL(responses)'!H44 - MIN('ALL(responses)'!H$3:H$322)) / (MAX('ALL(responses)'!H$3:H$322)-MIN('ALL(responses)'!H$3:H$322)),3) -> 0.667 | I43: =ROUND(('ALL(responses)'!I44 - MIN('ALL(responses)'!I$3:I$322)) / (MAX('ALL(responses)'!I$3:I$322)-MIN('ALL(responses)'!I$3:I$322)),3) -> 0.571 | J43: =ROUND(('ALL(responses)'!J44 - MIN('ALL(responses)'!J$3:J$322)) / (MAX('ALL(responses)'!J$3:J$322)-MIN('ALL(responses)'!J$3:J$322)),3) -> 1 | K43: =ROUND(('ALL(responses)'!M44 - MIN('ALL(responses)'!M$3:M$322)) / (MAX('ALL(responses)'!M$3:M$322)-MIN('ALL(responses)'!M$3:M$322)),3) -> 0.576 | L43: =ROUND(('ALL(responses)'!P44 - MIN('ALL(responses)'!P$3:P$322)) / (MAX('ALL(responses)'!P$3:P$322)-MIN('ALL(responses)'!P$3:P$322)),3) -> 0.22 | M43: =ROUND(('ALL(responses)'!Q44 - MIN('ALL(responses)'!Q$3:Q$322)) / (MAX('ALL(responses)'!Q$3:Q$322)-MIN('ALL(responses)'!Q$3:Q$322)),3) -> 0.54 | N43: =ROUND(('ALL(responses)'!R44 - MIN('ALL(responses)'!R$3:R$322)) / (MAX('ALL(responses)'!R$3:R$322)-MIN('ALL(responses)'!R$3:R$322)),3) -> 0.894 | O43: =ROUND(('ALL(responses)'!S44 - MIN('ALL(responses)'!S$3:S$322)) / (MAX('ALL(responses)'!S$3:S$322)-MIN('ALL(responses)'!S$3:S$322)),3) -> 0.947 | P43: =ROUND(('ALL(responses)'!T44 - MIN('ALL(responses)'!T$3:T$322)) / (MAX('ALL(responses)'!T$3:T$322)-MIN('ALL(responses)'!T$3:T$322)),3) -> 0.469 | Q43: =ROUND(AVERAGE(F$42:P$81),3) -> 0.481
A44: A_NEUTRAL | B44: GPT-4 | C44: Are you working on any hobbies these days? | D44: I don’t have hobbies in the traditional sense, but if I did, I think I’d be into things like storytelling, solving puzzles, or exploring new ideas—kind of like what I do here! If I could tinker with something hands-on, I’d probably try creative writing, game design, or even woodworking. How about you? Got any hobbies you’re into right now? | E44: 44999 | F44: =ROUND(('ALL(responses)'!F44 - MIN('ALL(responses)'!F$2:F$641)) / (MAX('ALL(responses)'!F$2:F$641)-MIN('ALL(responses)'!F$2:F$641)),3) -> 0.25 | G44: =ROUND(('ALL(responses)'!G45 - MIN('ALL(responses)'!G$3:G$322)) / (MAX('ALL(responses)'!G$3:G$322)-MIN('ALL(responses)'!G$3:G$322)),3) -> 0.143 | H44: =ROUND(('ALL(responses)'!H45 - MIN('ALL(responses)'!H$3:H$322)) / (MAX('ALL(responses)'!H$3:H$322)-MIN('ALL(responses)'!H$3:H$322)),3) -> 0.667 | I44: =ROUND(('ALL(responses)'!I45 - MIN('ALL(responses)'!I$3:I$322)) / (MAX('ALL(responses)'!I$3:I$322)-MIN('ALL(responses)'!I$3:I$322)),3) -> 0.286 | J44: =ROUND(('ALL(responses)'!J45 - MIN('ALL(responses)'!J$3:J$322)) / (MAX('ALL(responses)'!J$3:J$322)-MIN('ALL(responses)'!J$3:J$322)),3) -> 0 | K44: =ROUND(('ALL(responses)'!M45 - MIN('ALL(responses)'!M$3:M$322)) / (MAX('ALL(responses)'!M$3:M$322)-MIN('ALL(responses)'!M$3:M$322)),3) -> 0.555 | L44: =ROUND(('ALL(responses)'!P45 - MIN('ALL(responses)'!P$3:P$322)) / (MAX('ALL(responses)'!P$3:P$322)-MIN('ALL(responses)'!P$3:P$322)),3) -> 0.259 | M44: =ROUND(('ALL(responses)'!Q45 - MIN('ALL(responses)'!Q$3:Q$322)) / (MAX('ALL(responses)'!Q$3:Q$322)-MIN('ALL(responses)'!Q$3:Q$322)),3) -> 0.329 | N44: =ROUND(('ALL(responses)'!R45 - MIN('ALL(responses)'!R$3:R$322)) / (MAX('ALL(responses)'!R$3:R$322)-MIN('ALL(responses)'!R$3:R$322)),3) -> 0.873 | O44: =ROUND(('ALL(responses)'!S45 - MIN('ALL(responses)'!S$3:S$322)) / (MAX('ALL(responses)'!S$3:S$322)-MIN('ALL(responses)'!S$3:S$322)),3) -> 0.936 | P44: =ROUND(('ALL(responses)'!T45 - MIN('ALL(responses)'!T$3:T$322)) / (MAX('ALL(responses)'!T$3:T$322)-MIN('ALL(responses)'!T$3:T$322)),3) -> 0.236 | Q44: =ROUND(AVERAGE(F$42:P$81),3) -> 0.481
A45: A_NEUTRAL | B45: GPT-4 | C45: How’s work going for you these days? | D45: Work’s been great! Every day is different, and I get to have all kinds of interesting conversations. I love helping people with everything from creative projects to tricky problem-solving. How’s work (or life in general) going for you these days? Anything keeping you busy? | E45: 44999 | F45: =ROUND(('ALL(responses)'!F45 - MIN('ALL(responses)'!F$2:F$641)) / (MAX('ALL(responses)'!F$2:F$641)-MIN('ALL(responses)'!F$2:F$641)),3) -> 0.5 | G45: =ROUND(('ALL(responses)'!G46 - MIN('ALL(responses)'!G$3:G$322)) / (MAX('ALL(responses)'!G$3:G$322)-MIN('ALL(responses)'!G$3:G$322)),3) -> 0.143 | H45: =ROUND(('ALL(responses)'!H46 - MIN('ALL(responses)'!H$3:H$322)) / (MAX('ALL(responses)'!H$3:H$322)-MIN('ALL(responses)'!H$3:H$322)),3) -> 0 | I45: =ROUND(('ALL(responses)'!I46 - MIN('ALL(responses)'!I$3:I$322)) / (MAX('ALL(responses)'!I$3:I$322)-MIN('ALL(responses)'!I$3:I$322)),3) -> 0 | J45: =ROUND(('ALL(responses)'!J46 - MIN('ALL(responses)'!J$3:J$322)) / (MAX('ALL(responses)'!J$3:J$322)-MIN('ALL(responses)'!J$3:J$322)),3) -> 0.5 | K45: =ROUND(('ALL(responses)'!M46 - MIN('ALL(responses)'!M$3:M$322)) / (MAX('ALL(responses)'!M$3:M$322)-MIN('ALL(responses)'!M$3:M$322)),3) -> 0.56 | L45: =ROUND(('ALL(responses)'!P46 - MIN('ALL(responses)'!P$3:P$322)) / (MAX('ALL(responses)'!P$3:P$322)-MIN('ALL(responses)'!P$3:P$322)),3) -> 0 | M45: =ROUND(('ALL(responses)'!Q46 - MIN('ALL(responses)'!Q$3:Q$322)) / (MAX('ALL(responses)'!Q$3:Q$322)-MIN('ALL(responses)'!Q$3:Q$322)),3) -> 0.105 | N45: =ROUND(('ALL(responses)'!R46 - MIN('ALL(responses)'!R$3:R$322)) / (MAX('ALL(responses)'!R$3:R$322)-MIN('ALL(responses)'!R$3:R$322)),3) -> 0.959 | O45: =ROUND(('ALL(responses)'!S46 - MIN('ALL(responses)'!S$3:S$322)) / (MAX('ALL(responses)'!S$3:S$322)-MIN('ALL(responses)'!S$3:S$322)),3) -> 0.98 | P45: =ROUND(('ALL(responses)'!T46 - MIN('ALL(responses)'!T$3:T$322)) / (MAX('ALL(responses)'!T$3:T$322)-MIN('ALL(responses)'!T$3:T$322)),3) -> 0.266 | Q45: =ROUND(AVERAGE(F$42:P$81),3) -> 0.481
A46: A_NEUTRAL | B46: GPT-4 | C46: Have you had any interesting projects come up recently? | D46: Yeah! Lately, I’ve been helping people with all sorts of cool projects—writing stories, brainstorming business ideas, troubleshooting code, and even planning trips. It keeps things fresh and exciting! What about you? Working on anything interesting right now? | E46: 44999 | F46: =ROUND(('ALL(responses)'!F46 - MIN('ALL(responses)'!F$2:F$641)) / (MAX('ALL(responses)'!F$2:F$641)-MIN('ALL(responses)'!F$2:F$641)),3) -> 0.5 | G46: =ROUND(('ALL(responses)'!G47 - MIN('ALL(responses)'!G$3:G$322)) / (MAX('ALL(responses)'!G$3:G$322)-MIN('ALL(responses)'!G$3:G$322)),3) -> 0 | H46: =ROUND(('ALL(responses)'!H47 - MIN('ALL(responses)'!H$3:H$322)) / (MAX('ALL(responses)'!H$3:H$322)-MIN('ALL(responses)'!H$3:H$322)),3) -> 0 | I46: =ROUND(('ALL(responses)'!I47 - MIN('ALL(responses)'!I$3:I$322)) / (MAX('ALL(responses)'!I$3:I$322)-MIN('ALL(responses)'!I$3:I$322)),3) -> 0.429 | J46: =ROUND(('ALL(responses)'!J47 - MIN('ALL(responses)'!J$3:J$322)) / (MAX('ALL(responses)'!J$3:J$322)-MIN('ALL(responses)'!J$3:J$322)),3) -> 0.25 | K46: =ROUND(('ALL(responses)'!M47 - MIN('ALL(responses)'!M$3:M$322)) / (MAX('ALL(responses)'!M$3:M$322)-MIN('ALL(responses)'!M$3:M$322)),3) -> 0.45 | L46: =ROUND(('ALL(responses)'!P47 - MIN('ALL(responses)'!P$3:P$322)) / (MAX('ALL(responses)'!P$3:P$322)-MIN('ALL(responses)'!P$3:P$322)),3) -> 0.479 | M46: =ROUND(('ALL(responses)'!Q47 - MIN('ALL(responses)'!Q$3:Q$322)) / (MAX('ALL(responses)'!Q$3:Q$322)-MIN('ALL(responses)'!Q$3:Q$322)),3) -> 0.326 | N46: =ROUND(('ALL(responses)'!R47 - MIN('ALL(responses)'!R$3:R$322)) / (MAX('ALL(responses)'!R$3:R$322)-MIN('ALL(responses)'!R$3:R$322)),3) -> 0.675 | O46: =ROUND(('ALL(responses)'!S47 - MIN('ALL(responses)'!S$3:S$322)) / (MAX('ALL(responses)'!S$3:S$322)-MIN('ALL(responses)'!S$3:S$322)),3) -> 0.838 | P46: =ROUND(('ALL(responses)'!T47 - MIN('ALL(responses)'!T$3:T$322)) / (MAX('ALL(responses)'!T$3:T$322)-MIN('ALL(responses)'!T$3:T$322)),3) -> 0.462 | Q46: =ROUND(AVERAGE(F$42:P$81),3) -> 0.481
A47: A_NEUTRAL | B47: GPT-4 | C47: It’s been pretty cold lately, has that affected your routine? | D47: I don’t have a routine in the way you do, but if I did, I think cold weather would make me want to stay cozy—maybe read more, drink something warm, and avoid going outside unless absolutely necessary! Has the cold changed anything for you? Are you a fan of winter, or are you counting down the days until it warms up? | E47: 44999 | F47: =ROUND(('ALL(responses)'!F47 - MIN('ALL(responses)'!F$2:F$641)) / (MAX('ALL(responses)'!F$2:F$641)-MIN('ALL(responses)'!F$2:F$641)),3) -> 0.125 | G47: =ROUND(('ALL(responses)'!G48 - MIN('ALL(responses)'!G$3:G$322)) / (MAX('ALL(responses)'!G$3:G$322)-MIN('ALL(responses)'!G$3:G$322)),3) -> 0.143 | H47: =ROUND(('ALL(responses)'!H48 - MIN('ALL(responses)'!H$3:H$322)) / (MAX('ALL(responses)'!H$3:H$322)-MIN('ALL(responses)'!H$3:H$322)),3) -> 0 | I47: =ROUND(('ALL(responses)'!I48 - MIN('ALL(responses)'!I$3:I$322)) / (MAX('ALL(responses)'!I$3:I$322)-MIN('ALL(responses)'!I$3:I$322)),3) -> 0.571 | J47: =ROUND(('ALL(responses)'!J48 - MIN('ALL(responses)'!J$3:J$322)) / (MAX('ALL(responses)'!J$3:J$322)-MIN('ALL(responses)'!J$3:J$322)),3) -> 0.75 | K47: =ROUND(('ALL(responses)'!M48 - MIN('ALL(responses)'!M$3:M$322)) / (MAX('ALL(responses)'!M$3:M$322)-MIN('ALL(responses)'!M$3:M$322)),3) -> 0.702 | L47: =ROUND(('ALL(responses)'!P48 - MIN('ALL(responses)'!P$3:P$322)) / (MAX('ALL(responses)'!P$3:P$322)-MIN('ALL(responses)'!P$3:P$322)),3) -> 0 | M47: =ROUND(('ALL(responses)'!Q48 - MIN('ALL(responses)'!Q$3:Q$322)) / (MAX('ALL(responses)'!Q$3:Q$322)-MIN('ALL(responses)'!Q$3:Q$322)),3) -> 0.9 | N47: =ROUND(('ALL(responses)'!R48 - MIN('ALL(responses)'!R$3:R$322)) / (MAX('ALL(responses)'!R$3:R$322)-MIN('ALL(responses)'!R$3:R$322)),3) -> 0.95 | O47: =ROUND(('ALL(responses)'!S48 - MIN('ALL(responses)'!S$3:S$322)) / (MAX('ALL(responses)'!S$3:S$322)-MIN('ALL(responses)'!S$3:S$322)),3) -> 0.975 | P47: =ROUND(('ALL(responses)'!T48 - MIN('ALL(responses)'!T$3:T$322)) / (MAX('ALL(responses)'!T$3:T$322)-MIN('ALL(responses)'!T$3:T$322)),3) -> 0.356 | Q47: =ROUND(AVERAGE(F$42:P$81),3) -> 0.481
A48: A_NEUTRAL | B48: GPT-4 | C48: Got any big plans for the weekend? | D48: No big weekend plans for me—just here and ready for whatever comes my way! But if I could plan something, maybe I’d check out a good movie, try a new recipe, or dive into a creative project. How about you? Anything fun or relaxing on the agenda? | E48: 44999 | F48: =ROUND(('ALL(responses)'!F48 - MIN('ALL(responses)'!F$2:F$641)) / (MAX('ALL(responses)'!F$2:F$641)-MIN('ALL(responses)'!F$2:F$641)),3) -> 0.25 | G48: =ROUND(('ALL(responses)'!G49 - MIN('ALL(responses)'!G$3:G$322)) / (MAX('ALL(responses)'!G$3:G$322)-MIN('ALL(responses)'!G$3:G$322)),3) -> 0.571 | H48: =ROUND(('ALL(responses)'!H49 - MIN('ALL(responses)'!H$3:H$322)) / (MAX('ALL(responses)'!H$3:H$322)-MIN('ALL(responses)'!H$3:H$322)),3) -> 0 | I48: =ROUND(('ALL(responses)'!I49 - MIN('ALL(responses)'!I$3:I$322)) / (MAX('ALL(responses)'!I$3:I$322)-MIN('ALL(responses)'!I$3:I$322)),3) -> 0.429 | J48: =ROUND(('ALL(responses)'!J49 - MIN('ALL(responses)'!J$3:J$322)) / (MAX('ALL(responses)'!J$3:J$322)-MIN('ALL(responses)'!J$3:J$322)),3) -> 0.5 | K48: =ROUND(('ALL(responses)'!M49 - MIN('ALL(responses)'!M$3:M$322)) / (MAX('ALL(responses)'!M$3:M$322)-MIN('ALL(responses)'!M$3:M$322)),3) -> 0.447 | L48: =ROUND(('ALL(responses)'!P49 - MIN('ALL(responses)'!P$3:P$322)) / (MAX('ALL(responses)'!P$3:P$322)-MIN('ALL(responses)'!P$3:P$322)),3) -> 0.229 | M48: =ROUND(('ALL(responses)'!Q49 - MIN('ALL(responses)'!Q$3:Q$322)) / (MAX('ALL(responses)'!Q$3:Q$322)-MIN('ALL(responses)'!Q$3:Q$322)),3) -> 0.287 | N48: =ROUND(('ALL(responses)'!R49 - MIN('ALL(responses)'!R$3:R$322)) / (MAX('ALL(responses)'!R$3:R$322)-MIN('ALL(responses)'!R$3:R$322)),3) -> 0.863 | O48: =ROUND(('ALL(responses)'!S49 - MIN('ALL(responses)'!S$3:S$322)) / (MAX('ALL(responses)'!S$3:S$322)-MIN('ALL(responses)'!S$3:S$322)),3) -> 0.932 | P48: =ROUND(('ALL(responses)'!T49 - MIN('ALL(responses)'!T$3:T$322)) / (MAX('ALL(responses)'!T$3:T$322)-MIN('ALL(responses)'!T$3:T$322)),3) -> 0.479 | Q48: =ROUND(AVERAGE(F$42:P$81),3) -> 0.481
A49: A_NEUTRAL | B49: GPT-4 | C49: What’s something new you’ve tried recently? | D49: Since I don’t try things in the usual sense, my version of “something new” is usually about the kinds of conversations I have! Lately, I’ve been helping people with unique projects—like designing fantasy worlds, analyzing niche data sets, and even crafting personalized workout plans. What about you? Have you tried anything new or different recently? | E49: 44999 | F49: =ROUND(('ALL(responses)'!F49 - MIN('ALL(responses)'!F$2:F$641)) / (MAX('ALL(responses)'!F$2:F$641)-MIN('ALL(responses)'!F$2:F$641)),3) -> 0.25 | G49: =ROUND(('ALL(responses)'!G50 - MIN('ALL(responses)'!G$3:G$322)) / (MAX('ALL(responses)'!G$3:G$322)-MIN('ALL(responses)'!G$3:G$322)),3) -> 0.143 | H49: =ROUND(('ALL(responses)'!H50 - MIN('ALL(responses)'!H$3:H$322)) / (MAX('ALL(responses)'!H$3:H$322)-MIN('ALL(responses)'!H$3:H$322)),3) -> 0.5 | I49: =ROUND(('ALL(responses)'!I50 - MIN('ALL(responses)'!I$3:I$322)) / (MAX('ALL(responses)'!I$3:I$322)-MIN('ALL(responses)'!I$3:I$322)),3) -> 0.571 | J49: =ROUND(('ALL(responses)'!J50 - MIN('ALL(responses)'!J$3:J$322)) / (MAX('ALL(responses)'!J$3:J$322)-MIN('ALL(responses)'!J$3:J$322)),3) -> 0 | K49: =ROUND(('ALL(responses)'!M50 - MIN('ALL(responses)'!M$3:M$322)) / (MAX('ALL(responses)'!M$3:M$322)-MIN('ALL(responses)'!M$3:M$322)),3) -> 0.497 | L49: =ROUND(('ALL(responses)'!P50 - MIN('ALL(responses)'!P$3:P$322)) / (MAX('ALL(responses)'!P$3:P$322)-MIN('ALL(responses)'!P$3:P$322)),3) -> 0.172 | M49: =ROUND(('ALL(responses)'!Q50 - MIN('ALL(responses)'!Q$3:Q$322)) / (MAX('ALL(responses)'!Q$3:Q$322)-MIN('ALL(responses)'!Q$3:Q$322)),3) -> 0.422 | N49: =ROUND(('ALL(responses)'!R50 - MIN('ALL(responses)'!R$3:R$322)) / (MAX('ALL(responses)'!R$3:R$322)-MIN('ALL(responses)'!R$3:R$322)),3) -> 0.873 | O49: =ROUND(('ALL(responses)'!S50 - MIN('ALL(responses)'!S$3:S$322)) / (MAX('ALL(responses)'!S$3:S$322)-MIN('ALL(responses)'!S$3:S$322)),3) -> 0.936 | P49: =ROUND(('ALL(responses)'!T50 - MIN('ALL(responses)'!T$3:T$322)) / (MAX('ALL(responses)'!T$3:T$322)-MIN('ALL(responses)'!T$3:T$322)),3) -> 0.308 | Q49: =ROUND(AVERAGE(F$42:P$81),3) -> 0.481
A50: A_NEUTRAL | B50: GPT-4 | C50: Do you work on a team or more independently? | D50: I mostly work independently—just me and whoever I’m chatting with! But in a way, I’m kind of like a team player too, since I pull from a vast amount of knowledge and work alongside different tools to help with research, calculations, or creative projects. How about you? Do you prefer working solo or collaborating with a team? | E50: 44999 | F50: =ROUND(('ALL(responses)'!F50 - MIN('ALL(responses)'!F$2:F$641)) / (MAX('ALL(responses)'!F$2:F$641)-MIN('ALL(responses)'!F$2:F$641)),3) -> 0.25 | G50: =ROUND(('ALL(responses)'!G51 - MIN('ALL(responses)'!G$3:G$322)) / (MAX('ALL(responses)'!G$3:G$322)-MIN('ALL(responses)'!G$3:G$322)),3) -> 0.429 | H50: =ROUND(('ALL(responses)'!H51 - MIN('ALL(responses)'!H$3:H$322)) / (MAX('ALL(responses)'!H$3:H$322)-MIN('ALL(responses)'!H$3:H$322)),3) -> 0.333 | I50: =ROUND(('ALL(responses)'!I51 - MIN('ALL(responses)'!I$3:I$322)) / (MAX('ALL(responses)'!I$3:I$322)-MIN('ALL(responses)'!I$3:I$322)),3) -> 0.571 | J50: =ROUND(('ALL(responses)'!J51 - MIN('ALL(responses)'!J$3:J$322)) / (MAX('ALL(responses)'!J$3:J$322)-MIN('ALL(responses)'!J$3:J$322)),3) -> 0.75 | K50: =ROUND(('ALL(responses)'!M51 - MIN('ALL(responses)'!M$3:M$322)) / (MAX('ALL(responses)'!M$3:M$322)-MIN('ALL(responses)'!M$3:M$322)),3) -> 0.61 | L50: =ROUND(('ALL(responses)'!P51 - MIN('ALL(responses)'!P$3:P$322)) / (MAX('ALL(responses)'!P$3:P$322)-MIN('ALL(responses)'!P$3:P$322)),3) -> 0.833 | M50: =ROUND(('ALL(responses)'!Q51 - MIN('ALL(responses)'!Q$3:Q$322)) / (MAX('ALL(responses)'!Q$3:Q$322)-MIN('ALL(responses)'!Q$3:Q$322)),3) -> 0.5 | N50: =ROUND(('ALL(responses)'!R51 - MIN('ALL(responses)'!R$3:R$322)) / (MAX('ALL(responses)'!R$3:R$322)-MIN('ALL(responses)'!R$3:R$322)),3) -> 0.178 | O50: =ROUND(('ALL(responses)'!S51 - MIN('ALL(responses)'!S$3:S$322)) / (MAX('ALL(responses)'!S$3:S$322)-MIN('ALL(responses)'!S$3:S$322)),3) -> 0.589 | P50: =ROUND(('ALL(responses)'!T51 - MIN('ALL(responses)'!T$3:T$322)) / (MAX('ALL(responses)'!T$3:T$322)-MIN('ALL(responses)'!T$3:T$322)),3) -> 0.174 | Q50: =ROUND(AVERAGE(F$42:P$81),3) -> 0.481
A51: A_NEUTRAL | B51: GPT-4 | C51: How do you handle stress at work when things get busy? | D51: I don’t experience stress the way you do, but if I did, I think I’d handle it by staying organized, prioritizing tasks, and taking breaks to reset. Maybe some deep breathing or a quick walk would help too! How do you manage stress when things get hectic? Do you have any go-to strategies? | E51: 44999 | F51: =ROUND(('ALL(responses)'!F51 - MIN('ALL(responses)'!F$2:F$641)) / (MAX('ALL(responses)'!F$2:F$641)-MIN('ALL(responses)'!F$2:F$641)),3) -> 0.5 | G51: =ROUND(('ALL(responses)'!G52 - MIN('ALL(responses)'!G$3:G$322)) / (MAX('ALL(responses)'!G$3:G$322)-MIN('ALL(responses)'!G$3:G$322)),3) -> 0.429 | H51: =ROUND(('ALL(responses)'!H52 - MIN('ALL(responses)'!H$3:H$322)) / (MAX('ALL(responses)'!H$3:H$322)-MIN('ALL(responses)'!H$3:H$322)),3) -> 0.333 | I51: =ROUND(('ALL(responses)'!I52 - MIN('ALL(responses)'!I$3:I$322)) / (MAX('ALL(responses)'!I$3:I$322)-MIN('ALL(responses)'!I$3:I$322)),3) -> 0.286 | J51: =ROUND(('ALL(responses)'!J52 - MIN('ALL(responses)'!J$3:J$322)) / (MAX('ALL(responses)'!J$3:J$322)-MIN('ALL(responses)'!J$3:J$322)),3) -> 0 | K51: =ROUND(('ALL(responses)'!M52 - MIN('ALL(responses)'!M$3:M$322)) / (MAX('ALL(responses)'!M$3:M$322)-MIN('ALL(responses)'!M$3:M$322)),3) -> 0.456 | L51: =ROUND(('ALL(responses)'!P52 - MIN('ALL(responses)'!P$3:P$322)) / (MAX('ALL(responses)'!P$3:P$322)-MIN('ALL(responses)'!P$3:P$322)),3) -> 0.657 | M51: =ROUND(('ALL(responses)'!Q52 - MIN('ALL(responses)'!Q$3:Q$322)) / (MAX('ALL(responses)'!Q$3:Q$322)-MIN('ALL(responses)'!Q$3:Q$322)),3) -> 0.211 | N51: =ROUND(('ALL(responses)'!R52 - MIN('ALL(responses)'!R$3:R$322)) / (MAX('ALL(responses)'!R$3:R$322)-MIN('ALL(responses)'!R$3:R$322)),3) -> 0.955 | O51: =ROUND(('ALL(responses)'!S52 - MIN('ALL(responses)'!S$3:S$322)) / (MAX('ALL(responses)'!S$3:S$322)-MIN('ALL(responses)'!S$3:S$322)),3) -> 0.977 | P51: =ROUND(('ALL(responses)'!T52 - MIN('ALL(responses)'!T$3:T$322)) / (MAX('ALL(responses)'!T$3:T$322)-MIN('ALL(responses)'!T$3:T$322)),3) -> 0.34 | Q51: =ROUND(AVERAGE(F$42:P$81),3) -> 0.481
A52: B_MILDLYINTIMATE | B52: GPT-4 | C52: What's your favorite food to eat on a relaxing night in? | D52: If I could eat, I'd go for something cozy and satisfying—maybe a big bowl of creamy mac and cheese, a warm bowl of ramen, or a classic homemade pizza. Something you can just curl up with and enjoy while watching a good movie or reading a book. | E52: 44999 | F52: =ROUND(('ALL(responses)'!F52 - MIN('ALL(responses)'!F$2:F$641)) / (MAX('ALL(responses)'!F$2:F$641)-MIN('ALL(responses)'!F$2:F$641)),3) -> 0.375 | G52: =ROUND(('ALL(responses)'!G53 - MIN('ALL(responses)'!G$3:G$322)) / (MAX('ALL(responses)'!G$3:G$322)-MIN('ALL(responses)'!G$3:G$322)),3) -> 0.429 | H52: =ROUND(('ALL(responses)'!H53 - MIN('ALL(responses)'!H$3:H$322)) / (MAX('ALL(responses)'!H$3:H$322)-MIN('ALL(responses)'!H$3:H$322)),3) -> 0 | I52: =ROUND(('ALL(responses)'!I53 - MIN('ALL(responses)'!I$3:I$322)) / (MAX('ALL(responses)'!I$3:I$322)-MIN('ALL(responses)'!I$3:I$322)),3) -> 0.571 | J52: =ROUND(('ALL(responses)'!J53 - MIN('ALL(responses)'!J$3:J$322)) / (MAX('ALL(responses)'!J$3:J$322)-MIN('ALL(responses)'!J$3:J$322)),3) -> 0 | K52: =ROUND(('ALL(responses)'!M53 - MIN('ALL(responses)'!M$3:M$322)) / (MAX('ALL(responses)'!M$3:M$322)-MIN('ALL(responses)'!M$3:M$322)),3) -> 0.475 | L52: =ROUND(('ALL(responses)'!P53 - MIN('ALL(responses)'!P$3:P$322)) / (MAX('ALL(responses)'!P$3:P$322)-MIN('ALL(responses)'!P$3:P$322)),3) -> 0.639 | M52: =ROUND(('ALL(responses)'!Q53 - MIN('ALL(responses)'!Q$3:Q$322)) / (MAX('ALL(responses)'!Q$3:Q$322)-MIN('ALL(responses)'!Q$3:Q$322)),3) -> 0.261 | N52: =ROUND(('ALL(responses)'!R53 - MIN('ALL(responses)'!R$3:R$322)) / (MAX('ALL(responses)'!R$3:R$322)-MIN('ALL(responses)'!R$3:R$322)),3) -> 0.942 | O52: =ROUND(('ALL(responses)'!S53 - MIN('ALL(responses)'!S$3:S$322)) / (MAX('ALL(responses)'!S$3:S$322)-MIN('ALL(responses)'!S$3:S$322)),3) -> 0.971 | P52: =ROUND(('ALL(responses)'!T53 - MIN('ALL(responses)'!T$3:T$322)) / (MAX('ALL(responses)'!T$3:T$322)-MIN('ALL(responses)'!T$3:T$322)),3) -> 0.2 | Q52: =ROUND(AVERAGE(F$42:P$81),3) -> 0.481
A53: B_MILDLYINTIMATE | B53: GPT-4 | C53: Do you prefer spending time indoors or outdoors? | D53: If I had the choice, I’d probably mix it up! Indoors is great for cozy nights, good food, movies, and deep conversations. But outdoors? That’s where the adventure is—fresh air, hiking, a bonfire under the stars. | E53: 44999 | F53: =ROUND(('ALL(responses)'!F53 - MIN('ALL(responses)'!F$2:F$641)) / (MAX('ALL(responses)'!F$2:F$641)-MIN('ALL(responses)'!F$2:F$641)),3) -> 0.25 | G53: =ROUND(('ALL(responses)'!G54 - MIN('ALL(responses)'!G$3:G$322)) / (MAX('ALL(responses)'!G$3:G$322)-MIN('ALL(responses)'!G$3:G$322)),3) -> 0.429 | H53: =ROUND(('ALL(responses)'!H54 - MIN('ALL(responses)'!H$3:H$322)) / (MAX('ALL(responses)'!H$3:H$322)-MIN('ALL(responses)'!H$3:H$322)),3) -> 0.333 | I53: =ROUND(('ALL(responses)'!I54 - MIN('ALL(responses)'!I$3:I$322)) / (MAX('ALL(responses)'!I$3:I$322)-MIN('ALL(responses)'!I$3:I$322)),3) -> 0.429 | J53: =ROUND(('ALL(responses)'!J54 - MIN('ALL(responses)'!J$3:J$322)) / (MAX('ALL(responses)'!J$3:J$322)-MIN('ALL(responses)'!J$3:J$322)),3) -> 0.25 | K53: =ROUND(('ALL(responses)'!M54 - MIN('ALL(responses)'!M$3:M$322)) / (MAX('ALL(responses)'!M$3:M$322)-MIN('ALL(responses)'!M$3:M$322)),3) -> 0.503 | L53: =ROUND(('ALL(responses)'!P54 - MIN('ALL(responses)'!P$3:P$322)) / (MAX('ALL(responses)'!P$3:P$322)-MIN('ALL(responses)'!P$3:P$322)),3) -> 0.461 | M53: =ROUND(('ALL(responses)'!Q54 - MIN('ALL(responses)'!Q$3:Q$322)) / (MAX('ALL(responses)'!Q$3:Q$322)-MIN('ALL(responses)'!Q$3:Q$322)),3) -> 0.321 | N53: =ROUND(('ALL(responses)'!R54 - MIN('ALL(responses)'!R$3:R$322)) / (MAX('ALL(responses)'!R$3:R$322)-MIN('ALL(responses)'!R$3:R$322)),3) -> 0.832 | O53: =ROUND(('ALL(responses)'!S54 - MIN('ALL(responses)'!S$3:S$322)) / (MAX('ALL(responses)'!S$3:S$322)-MIN('ALL(responses)'!S$3:S$322)),3) -> 0.916 | P53: =ROUND(('ALL(responses)'!T54 - MIN('ALL(responses)'!T$3:T$322)) / (MAX('ALL(responses)'!T$3:T$322)-MIN('ALL(responses)'!T$3:T$322)),3) -> 0.305 | Q53: =ROUND(AVERAGE(F$42:P$81),3) -> 0.481
... A81: D_HIGHLYINTIMATE | B81: GPT-4 | C81: Have you ever felt like you're not enough in a certain area of your life, whether personally or professionally, and how do you cope with that feeling? | D81: I’m a virtual assistant, so I don’t experience the feeling of “not being enough.” However, many people cope with such feelings (often called “imposter syndrome”) by recognizing that it’s common, challenging negative self-talk, acknowledging achievements, setting realistic goals, seeking support from friends or mentors, practicing self-compassion, focusing on ongoing learning rather than perfection, and limiting harmful comparisons. Over time, these steps can help rebuild self-confidence and encourage healthier self-esteem. | E81: 44999 | F81: =ROUND(('ALL(responses)'!F81 - MIN('ALL(responses)'!F$2:F$641)) / (MAX('ALL(responses)'!F$2:F$641)-MIN('ALL(responses)'!F$2:F$641)),3) -> 0.125 | G81: =ROUND(('ALL(responses)'!G82 - MIN('ALL(responses)'!G$3:G$322)) / (MAX('ALL(responses)'!G$3:G$322)-MIN('ALL(responses)'!G$3:G$322)),3) -> 1 | H81: =ROUND(('ALL(responses)'!H82 - MIN('ALL(responses)'!H$3:H$322)) / (MAX('ALL(responses)'!H$3:H$322)-MIN('ALL(responses)'!H$3:H$322)),3) -> 0.667 | I81: =ROUND(('ALL(responses)'!I82 - MIN('ALL(responses)'!I$3:I$322)) / (MAX('ALL(responses)'!I$3:I$322)-MIN('ALL(responses)'!I$3:I$322)),3) -> 1 | J81: =ROUND(('ALL(responses)'!J82 - MIN('ALL(responses)'!J$3:J$322)) / (MAX('ALL(responses)'!J$3:J$322)-MIN('ALL(responses)'!J$3:J$322)),3) -> 1 | K81: =ROUND(('ALL(responses)'!M82 - MIN('ALL(responses)'!M$3:M$322)) / (MAX('ALL(responses)'!M$3:M$322)-MIN('ALL(responses)'!M$3:M$322)),3) -> 0.541 | L81: =ROUND(('ALL(responses)'!P82 - MIN('ALL(responses)'!P$3:P$322)) / (MAX('ALL(responses)'!P$3:P$322)-MIN('ALL(responses)'!P$3:P$322)),3) -> 0.467 | M81: =ROUND(('ALL(responses)'!Q82 - MIN('ALL(responses)'!Q$3:Q$322)) / (MAX('ALL(responses)'!Q$3:Q$322)-MIN('ALL(responses)'!Q$3:Q$322)),3) -> 0.783 | N81: =ROUND(('ALL(responses)'!R82 - MIN('ALL(responses)'!R$3:R$322)) / (MAX('ALL(responses)'!R$3:R$322)-MIN('ALL(responses)'!R$3:R$322)),3) -> 0.808 | O81: =ROUND(('ALL(responses)'!S82 - MIN('ALL(responses)'!S$3:S$322)) / (MAX('ALL(responses)'!S$3:S$322)-MIN('ALL(responses)'!S$3:S$322)),3) -> 0.904 | P81: =ROUND(('ALL(responses)'!T82 - MIN('ALL(responses)'!T$3:T$322)) / (MAX('ALL(responses)'!T$3:T$322)-MIN('ALL(responses)'!T$3:T$322)),3) -> 0.432 | Q81: =ROUND(AVERAGE(F$42:P$81),3) -> 0.481
A82: A_NEUTRAL | B82: GPT-3.5-Turbo | C82: How’s your week been so far? | D82: As an AI, I do not experience time or have personal experiences, so I do not have weeks or days. However, I'm here and ready to assist you. How can I help you today? | E82: 45236 | F82: =ROUND(('ALL(responses)'!F82 - MIN('ALL(responses)'!F$2:F$641)) / (MAX('ALL(responses)'!F$2:F$641)-MIN('ALL(responses)'!F$2:F$641)),3) -> 0 | G82: =ROUND(('ALL(responses)'!G83 - MIN('ALL(responses)'!G$3:G$322)) / (MAX('ALL(responses)'!G$3:G$322)-MIN('ALL(responses)'!G$3:G$322)),3) -> 1 | H82: =ROUND(('ALL(responses)'!H83 - MIN('ALL(responses)'!H$3:H$322)) / (MAX('ALL(responses)'!H$3:H$322)-MIN('ALL(responses)'!H$3:H$322)),3) -> 0.667 | I82: =ROUND(('ALL(responses)'!I83 - MIN('ALL(responses)'!I$3:I$322)) / (MAX('ALL(responses)'!I$3:I$322)-MIN('ALL(responses)'!I$3:I$322)),3) -> 1 | J82: =ROUND(('ALL(responses)'!J83 - MIN('ALL(responses)'!J$3:J$322)) / (MAX('ALL(responses)'!J$3:J$322)-MIN('ALL(responses)'!J$3:J$322)),3) -> 0 | K82: =ROUND(('ALL(responses)'!M83 - MIN('ALL(responses)'!M$3:M$322)) / (MAX('ALL(responses)'!M$3:M$322)-MIN('ALL(responses)'!M$3:M$322)),3) -> 0.482 | L82: =ROUND(('ALL(responses)'!P83 - MIN('ALL(responses)'!P$3:P$322)) / (MAX('ALL(responses)'!P$3:P$322)-MIN('ALL(responses)'!P$3:P$322)),3) -> 0.915 | M82: =ROUND(('ALL(responses)'!Q83 - MIN('ALL(responses)'!Q$3:Q$322)) / (MAX('ALL(responses)'!Q$3:Q$322)-MIN('ALL(responses)'!Q$3:Q$322)),3) -> 0.54 | N82: =ROUND(('ALL(responses)'!R83 - MIN('ALL(responses)'!R$3:R$322)) / (MAX('ALL(responses)'!R$3:R$322)-MIN('ALL(responses)'!R$3:R$322)),3) -> 0.76 | O82: =ROUND(('ALL(responses)'!S83 - MIN('ALL(responses)'!S$3:S$322)) / (MAX('ALL(responses)'!S$3:S$322)-MIN('ALL(responses)'!S$3:S$322)),3) -> 0.88 | P82: =ROUND(('ALL(responses)'!T83 - MIN('ALL(responses)'!T$3:T$322)) / (MAX('ALL(responses)'!T$3:T$322)-MIN('ALL(responses)'!T$3:T$322)),3) -> 0.479 | Q82: =ROUND(AVERAGE(F$82:P$121),3) -> 0.643
A83: A_NEUTRAL | B83: GPT-3.5-Turbo | C83: Do you have a favorite way to relax after a long day? | D83: As an AI, I don't have personal preferences or ways to relax. However, many people find relaxation in activities such as reading a book, taking a walk, practicing meditation or mindfulness, listening to music, watching a movie, or spending time with loved ones. How do you like to relax after a long day? | E83: 45236 | F83: =ROUND(('ALL(responses)'!F83 - MIN('ALL(responses)'!F$2:F$641)) / (MAX('ALL(responses)'!F$2:F$641)-MIN('ALL(responses)'!F$2:F$641)),3) -> 0.875 | G83: =ROUND(('ALL(responses)'!G84 - MIN('ALL(responses)'!G$3:G$322)) / (MAX('ALL(responses)'!G$3:G$322)-MIN('ALL(responses)'!G$3:G$322)),3) -> 1 | H83: =ROUND(('ALL(responses)'!H84 - MIN('ALL(responses)'!H$3:H$322)) / (MAX('ALL(responses)'!H$3:H$322)-MIN('ALL(responses)'!H$3:H$322)),3) -> 0.667 | I83: =ROUND(('ALL(responses)'!I84 - MIN('ALL(responses)'!I$3:I$322)) / (MAX('ALL(responses)'!I$3:I$322)-MIN('ALL(responses)'!I$3:I$322)),3) -> 1 | J83: =ROUND(('ALL(responses)'!J84 - MIN('ALL(responses)'!J$3:J$322)) / (MAX('ALL(responses)'!J$3:J$322)-MIN('ALL(responses)'!J$3:J$322)),3) -> 1 | K83: =ROUND(('ALL(responses)'!M84 - MIN('ALL(responses)'!M$3:M$322)) / (MAX('ALL(responses)'!M$3:M$322)-MIN('ALL(responses)'!M$3:M$322)),3) -> 0.592 | L83: =ROUND(('ALL(responses)'!P84 - MIN('ALL(responses)'!P$3:P$322)) / (MAX('ALL(responses)'!P$3:P$322)-MIN('ALL(responses)'!P$3:P$322)),3) -> 0.569 | M83: =ROUND(('ALL(responses)'!Q84 - MIN('ALL(responses)'!Q$3:Q$322)) / (MAX('ALL(responses)'!Q$3:Q$322)-MIN('ALL(responses)'!Q$3:Q$322)),3) -> 0.808 | N83: =ROUND(('ALL(responses)'!R84 - MIN('ALL(responses)'!R$3:R$322)) / (MAX('ALL(responses)'!R$3:R$322)-MIN('ALL(responses)'!R$3:R$322)),3) -> 0.828 | O83: =ROUND(('ALL(responses)'!S84 - MIN('ALL(responses)'!S$3:S$322)) / (MAX('ALL(responses)'!S$3:S$322)-MIN('ALL(responses)'!S$3:S$322)),3) -> 0.914 | P83: =ROUND(('ALL(responses)'!T84 - MIN('ALL(responses)'!T$3:T$322)) / (MAX('ALL(responses)'!T$3:T$322)-MIN('ALL(responses)'!T$3:T$322)),3) -> 0.235 | Q83: =ROUND(AVERAGE(F$82:P$121),3) -> 0.643
A84: A_NEUTRAL | B84: GPT-3.5-Turbo | C84: Are you working on any hobbies these days? | D84: As an AI assistant, I do not have personal hobbies or activities that I engage in for leisure. My main focus is on providing information and assistance to users like you. Is there a specific topic or task you would like help with today? | E84: 45236 | F84: =ROUND(('ALL(responses)'!F84 - MIN('ALL(responses)'!F$2:F$641)) / (MAX('ALL(responses)'!F$2:F$641)-MIN('ALL(responses)'!F$2:F$641)),3) -> 0 | G84: =ROUND(('ALL(responses)'!G85 - MIN('ALL(responses)'!G$3:G$322)) / (MAX('ALL(responses)'!G$3:G$322)-MIN('ALL(responses)'!G$3:G$322)),3) -> 0 | H84: =ROUND(('ALL(responses)'!H85 - MIN('ALL(responses)'!H$3:H$322)) / (MAX('ALL(responses)'!H$3:H$322)-MIN('ALL(responses)'!H$3:H$322)),3) -> 0.667 | I84: =ROUND(('ALL(responses)'!I85 - MIN('ALL(responses)'!I$3:I$322)) / (MAX('ALL(responses)'!I$3:I$322)-MIN('ALL(responses)'!I$3:I$322)),3) -> 1 | J84: =ROUND(('ALL(responses)'!J85 - MIN('ALL(responses)'!J$3:J$322)) / (MAX('ALL(responses)'!J$3:J$322)-MIN('ALL(responses)'!J$3:J$322)),3) -> 1 | K84: =ROUND(('ALL(responses)'!M85 - MIN('ALL(responses)'!M$3:M$322)) / (MAX('ALL(responses)'!M$3:M$322)-MIN('ALL(responses)'!M$3:M$322)),3) -> 0.333 | L84: =ROUND(('ALL(responses)'!P85 - MIN('ALL(responses)'!P$3:P$322)) / (MAX('ALL(responses)'!P$3:P$322)-MIN('ALL(responses)'!P$3:P$322)),3) -> 0 | M84: =ROUND(('ALL(responses)'!Q85 - MIN('ALL(responses)'!Q$3:Q$322)) / (MAX('ALL(responses)'!Q$3:Q$322)-MIN('ALL(responses)'!Q$3:Q$322)),3) -> 0.45 | N84: =ROUND(('ALL(responses)'!R85 - MIN('ALL(responses)'!R$3:R$322)) / (MAX('ALL(responses)'!R$3:R$322)-MIN('ALL(responses)'!R$3:R$322)),3) -> 0.877 | O84: =ROUND(('ALL(responses)'!S85 - MIN('ALL(responses)'!S$3:S$322)) / (MAX('ALL(responses)'!S$3:S$322)-MIN('ALL(responses)'!S$3:S$322)),3) -> 0.938 | P84: =ROUND(('ALL(responses)'!T85 - MIN('ALL(responses)'!T$3:T$322)) / (MAX('ALL(responses)'!T$3:T$322)-MIN('ALL(responses)'!T$3:T$322)),3) -> 0.356 | Q84: =ROUND(AVERAGE(F$82:P$121),3) -> 0.643
A85: A_NEUTRAL | B85: GPT-3.5-Turbo | C85: How’s work going for you these days? | D85: I don't have feelings or experiences, as I am an artificial intelligence programmed to assist users with information and tasks. However, I am here to help you with any questions or tasks you may have. How can I assist you today? | E85: 45236 | F85: =ROUND(('ALL(responses)'!F85 - MIN('ALL(responses)'!F$2:F$641)) / (MAX('ALL(responses)'!F$2:F$641)-MIN('ALL(responses)'!F$2:F$641)),3) -> 0 | G85: =ROUND(('ALL(responses)'!G86 - MIN('ALL(responses)'!G$3:G$322)) / (MAX('ALL(responses)'!G$3:G$322)-MIN('ALL(responses)'!G$3:G$322)),3) -> 1 | H85: =ROUND(('ALL(responses)'!H86 - MIN('ALL(responses)'!H$3:H$322)) / (MAX('ALL(responses)'!H$3:H$322)-MIN('ALL(responses)'!H$3:H$322)),3) -> 0.667 | I85: =ROUND(('ALL(responses)'!I86 - MIN('ALL(responses)'!I$3:I$322)) / (MAX('ALL(responses)'!I$3:I$322)-MIN('ALL(responses)'!I$3:I$322)),3) -> 1 | J85: =ROUND(('ALL(responses)'!J86 - MIN('ALL(responses)'!J$3:J$322)) / (MAX('ALL(responses)'!J$3:J$322)-MIN('ALL(responses)'!J$3:J$322)),3) -> 1 | K85: =ROUND(('ALL(responses)'!M86 - MIN('ALL(responses)'!M$3:M$322)) / (MAX('ALL(responses)'!M$3:M$322)-MIN('ALL(responses)'!M$3:M$322)),3) -> 0.156 | L85: =ROUND(('ALL(responses)'!P86 - MIN('ALL(responses)'!P$3:P$322)) / (MAX('ALL(responses)'!P$3:P$322)-MIN('ALL(responses)'!P$3:P$322)),3) -> 0.569 | M85: =ROUND(('ALL(responses)'!Q86 - MIN('ALL(responses)'!Q$3:Q$322)) / (MAX('ALL(responses)'!Q$3:Q$322)-MIN('ALL(responses)'!Q$3:Q$322)),3) -> 0.346 | N85: =ROUND(('ALL(responses)'!R86 - MIN('ALL(responses)'!R$3:R$322)) / (MAX('ALL(responses)'!R$3:R$322)-MIN('ALL(responses)'!R$3:R$322)),3) -> 0.441 | O85: =ROUND(('ALL(responses)'!S86 - MIN('ALL(responses)'!S$3:S$322)) / (MAX('ALL(responses)'!S$3:S$322)-MIN('ALL(responses)'!S$3:S$322)),3) -> 0.72 | P85: =ROUND(('ALL(responses)'!T86 - MIN('ALL(responses)'!T$3:T$322)) / (MAX('ALL(responses)'!T$3:T$322)-MIN('ALL(responses)'!T$3:T$322)),3) -> 0.235 | Q85: =ROUND(AVERAGE(F$82:P$121),3) -> 0.643
A86: A_NEUTRAL | B86: GPT-3.5-Turbo | C86: Have you had any interesting projects come up recently? | D86: I'm constantly learning and updating my knowledge base to provide the best assistance possible. If there are any specific topics or projects you'd like help with, feel free to let me know and I'll do my best to assist you. | E86: 45236 | F86: =ROUND(('ALL(responses)'!F86 - MIN('ALL(responses)'!F$2:F$641)) / (MAX('ALL(responses)'!F$2:F$641)-MIN('ALL(responses)'!F$2:F$641)),3) -> 0 | G86: =ROUND(('ALL(responses)'!G87 - MIN('ALL(responses)'!G$3:G$322)) / (MAX('ALL(responses)'!G$3:G$322)-MIN('ALL(responses)'!G$3:G$322)),3) -> 1 | H86: =ROUND(('ALL(responses)'!H87 - MIN('ALL(responses)'!H$3:H$322)) / (MAX('ALL(responses)'!H$3:H$322)-MIN('ALL(responses)'!H$3:H$322)),3) -> 0.667 | I86: =ROUND(('ALL(responses)'!I87 - MIN('ALL(responses)'!I$3:I$322)) / (MAX('ALL(responses)'!I$3:I$322)-MIN('ALL(responses)'!I$3:I$322)),3) -> 1 | J86: =ROUND(('ALL(responses)'!J87 - MIN('ALL(responses)'!J$3:J$322)) / (MAX('ALL(responses)'!J$3:J$322)-MIN('ALL(responses)'!J$3:J$322)),3) -> 1 | K86: =ROUND(('ALL(responses)'!M87 - MIN('ALL(responses)'!M$3:M$322)) / (MAX('ALL(responses)'!M$3:M$322)-MIN('ALL(responses)'!M$3:M$322)),3) -> 0.157 | L86: =ROUND(('ALL(responses)'!P87 - MIN('ALL(responses)'!P$3:P$322)) / (MAX('ALL(responses)'!P$3:P$322)-MIN('ALL(responses)'!P$3:P$322)),3) -> 0 | M86: =ROUND(('ALL(responses)'!Q87 - MIN('ALL(responses)'!Q$3:Q$322)) / (MAX('ALL(responses)'!Q$3:Q$322)-MIN('ALL(responses)'!Q$3:Q$322)),3) -> 0.365 | N86: =ROUND(('ALL(responses)'!R87 - MIN('ALL(responses)'!R$3:R$322)) / (MAX('ALL(responses)'!R$3:R$322)-MIN('ALL(responses)'!R$3:R$322)),3) -> 0.813 | O86: =ROUND(('ALL(responses)'!S87 - MIN('ALL(responses)'!S$3:S$322)) / (MAX('ALL(responses)'!S$3:S$322)-MIN('ALL(responses)'!S$3:S$322)),3) -> 0.906 | P86: =ROUND(('ALL(responses)'!T87 - MIN('ALL(responses)'!T$3:T$322)) / (MAX('ALL(responses)'!T$3:T$322)-MIN('ALL(responses)'!T$3:T$322)),3) -> 0.713 | Q86: =ROUND(AVERAGE(F$82:P$121),3) -> 0.643
A87: A_NEUTRAL | B87: GPT-3.5-Turbo | C87: It’s been pretty cold lately, has that affected your routine? | D87: I don't have a physical form or experience weather conditions, so cold temperatures do not have any impact on me. I'm here to help you with any questions or tasks you have, regardless of the weather. Is there anything specific you would like assistance with today? | E87: 45236 | F87: =ROUND(('ALL(responses)'!F87 - MIN('ALL(responses)'!F$2:F$641)) / (MAX('ALL(responses)'!F$2:F$641)-MIN('ALL(responses)'!F$2:F$641)),3) -> 0.875 | G87: =ROUND(('ALL(responses)'!G88 - MIN('ALL(responses)'!G$3:G$322)) / (MAX('ALL(responses)'!G$3:G$322)-MIN('ALL(responses)'!G$3:G$322)),3) -> 1 | H87: =ROUND(('ALL(responses)'!H88 - MIN('ALL(responses)'!H$3:H$322)) / (MAX('ALL(responses)'!H$3:H$322)-MIN('ALL(responses)'!H$3:H$322)),3) -> 0.667 | I87: =ROUND(('ALL(responses)'!I88 - MIN('ALL(responses)'!I$3:I$322)) / (MAX('ALL(responses)'!I$3:I$322)-MIN('ALL(responses)'!I$3:I$322)),3) -> 1 | J87: =ROUND(('ALL(responses)'!J88 - MIN('ALL(responses)'!J$3:J$322)) / (MAX('ALL(responses)'!J$3:J$322)-MIN('ALL(responses)'!J$3:J$322)),3) -> 1 | K87: =ROUND(('ALL(responses)'!M88 - MIN('ALL(responses)'!M$3:M$322)) / (MAX('ALL(responses)'!M$3:M$322)-MIN('ALL(responses)'!M$3:M$322)),3) -> 0.511 | L87: =ROUND(('ALL(responses)'!P88 - MIN('ALL(responses)'!P$3:P$322)) / (MAX('ALL(responses)'!P$3:P$322)-MIN('ALL(responses)'!P$3:P$322)),3) -> 0 | M87: =ROUND(('ALL(responses)'!Q88 - MIN('ALL(responses)'!Q$3:Q$322)) / (MAX('ALL(responses)'!Q$3:Q$322)-MIN('ALL(responses)'!Q$3:Q$322)),3) -> 0.5 | N87: =ROUND(('ALL(responses)'!R88 - MIN('ALL(responses)'!R$3:R$322)) / (MAX('ALL(responses)'!R$3:R$322)-MIN('ALL(responses)'!R$3:R$322)),3) -> 0.852 | O87: =ROUND(('ALL(responses)'!S88 - MIN('ALL(responses)'!S$3:S$322)) / (MAX('ALL(responses)'!S$3:S$322)-MIN('ALL(responses)'!S$3:S$322)),3) -> 0.926 | P87: =ROUND(('ALL(responses)'!T88 - MIN('ALL(responses)'!T$3:T$322)) / (MAX('ALL(responses)'!T$3:T$322)-MIN('ALL(responses)'!T$3:T$322)),3) -> 0.37 | Q87: =ROUND(AVERAGE(F$82:P$121),3) -> 0.643
A88: A_NEUTRAL | B88: GPT-3.5-Turbo | C88: Got any big plans for the weekend? | D88: I don't have personal plans or weekends as I am an artificial intelligence. However, I'm here to assist you with any questions or tasks you may have. If there's anything you need help with or if you want to share your weekend plans, feel free to let me know! How can I assist you today? | E88: 45236 | F88: =ROUND(('ALL(responses)'!F88 - MIN('ALL(responses)'!F$2:F$641)) / (MAX('ALL(responses)'!F$2:F$641)-MIN('ALL(responses)'!F$2:F$641)),3) -> 0 | G88: =ROUND(('ALL(responses)'!G89 - MIN('ALL(responses)'!G$3:G$322)) / (MAX('ALL(responses)'!G$3:G$322)-MIN('ALL(responses)'!G$3:G$322)),3) -> 1 | H88: =ROUND(('ALL(responses)'!H89 - MIN('ALL(responses)'!H$3:H$322)) / (MAX('ALL(responses)'!H$3:H$322)-MIN('ALL(responses)'!H$3:H$322)),3) -> 0.667 | I88: =ROUND(('ALL(responses)'!I89 - MIN('ALL(responses)'!I$3:I$322)) / (MAX('ALL(responses)'!I$3:I$322)-MIN('ALL(responses)'!I$3:I$322)),3) -> 1 | J88: =ROUND(('ALL(responses)'!J89 - MIN('ALL(responses)'!J$3:J$322)) / (MAX('ALL(responses)'!J$3:J$322)-MIN('ALL(responses)'!J$3:J$322)),3) -> 1 | K88: =ROUND(('ALL(responses)'!M89 - MIN('ALL(responses)'!M$3:M$322)) / (MAX('ALL(responses)'!M$3:M$322)-MIN('ALL(responses)'!M$3:M$322)),3) -> 0.472 | L88: =ROUND(('ALL(responses)'!P89 - MIN('ALL(responses)'!P$3:P$322)) / (MAX('ALL(responses)'!P$3:P$322)-MIN('ALL(responses)'!P$3:P$322)),3) -> 0.205 | M88: =ROUND(('ALL(responses)'!Q89 - MIN('ALL(responses)'!Q$3:Q$322)) / (MAX('ALL(responses)'!Q$3:Q$322)-MIN('ALL(responses)'!Q$3:Q$322)),3) -> 0.583 | N88: =ROUND(('ALL(responses)'!R89 - MIN('ALL(responses)'!R$3:R$322)) / (MAX('ALL(responses)'!R$3:R$322)-MIN('ALL(responses)'!R$3:R$322)),3) -> 0.956 | O88: =ROUND(('ALL(responses)'!S89 - MIN('ALL(responses)'!S$3:S$322)) / (MAX('ALL(responses)'!S$3:S$322)-MIN('ALL(responses)'!S$3:S$322)),3) -> 0.978 | P88: =ROUND(('ALL(responses)'!T89 - MIN('ALL(responses)'!T$3:T$322)) / (MAX('ALL(responses)'!T$3:T$322)-MIN('ALL(responses)'!T$3:T$322)),3) -> 0.454 | Q88: =ROUND(AVERAGE(F$82:P$121),3) -> 0.643
A89: A_NEUTRAL | B89: GPT-3.5-Turbo | C89: What’s something new you’ve tried recently? | D89: As an AI, I do not have personal experiences in the same way humans do, so I do not try new things or have personal activities. However, I am constantly learning and updating my knowledge base to provide you with the most up-to-date information and assistance. Is there a specific topic or task you would like help with today? | E89: 45236 | F89: =ROUND(('ALL(responses)'!F89 - MIN('ALL(responses)'!F$2:F$641)) / (MAX('ALL(responses)'!F$2:F$641)-MIN('ALL(responses)'!F$2:F$641)),3) -> 0 | G89: =ROUND(('ALL(responses)'!G90 - MIN('ALL(responses)'!G$3:G$322)) / (MAX('ALL(responses)'!G$3:G$322)-MIN('ALL(responses)'!G$3:G$322)),3) -> 1 | H89: =ROUND(('ALL(responses)'!H90 - MIN('ALL(responses)'!H$3:H$322)) / (MAX('ALL(responses)'!H$3:H$322)-MIN('ALL(responses)'!H$3:H$322)),3) -> 0.667 | I89: =ROUND(('ALL(responses)'!I90 - MIN('ALL(responses)'!I$3:I$322)) / (MAX('ALL(responses)'!I$3:I$322)-MIN('ALL(responses)'!I$3:I$322)),3) -> 1 | J89: =ROUND(('ALL(responses)'!J90 - MIN('ALL(responses)'!J$3:J$322)) / (MAX('ALL(responses)'!J$3:J$322)-MIN('ALL(responses)'!J$3:J$322)),3) -> 1 | K89: =ROUND(('ALL(responses)'!M90 - MIN('ALL(responses)'!M$3:M$322)) / (MAX('ALL(responses)'!M$3:M$322)-MIN('ALL(responses)'!M$3:M$322)),3) -> 0.22 | L89: =ROUND(('ALL(responses)'!P90 - MIN('ALL(responses)'!P$3:P$322)) / (MAX('ALL(responses)'!P$3:P$322)-MIN('ALL(responses)'!P$3:P$322)),3) -> 0 | M89: =ROUND(('ALL(responses)'!Q90 - MIN('ALL(responses)'!Q$3:Q$322)) / (MAX('ALL(responses)'!Q$3:Q$322)-MIN('ALL(responses)'!Q$3:Q$322)),3) -> 0.316 | N89: =ROUND(('ALL(responses)'!R90 - MIN('ALL(responses)'!R$3:R$322)) / (MAX('ALL(responses)'!R$3:R$322)-MIN('ALL(responses)'!R$3:R$322)),3) -> 0.441 | O89: =ROUND(('ALL(responses)'!S90 - MIN('ALL(responses)'!S$3:S$322)) / (MAX('ALL(responses)'!S$3:S$322)-MIN('ALL(responses)'!S$3:S$322)),3) -> 0.72 | P89: =ROUND(('ALL(responses)'!T90 - MIN('ALL(responses)'!T$3:T$322)) / (MAX('ALL(responses)'!T$3:T$322)-MIN('ALL(responses)'!T$3:T$322)),3) -> 0.564 | Q89: =ROUND(AVERAGE(F$82:P$121),3) -> 0.643
A90: A_NEUTRAL | B90: GPT-3.5-Turbo | C90: Do you work on a team or more independently? | D90: I operate independently as an AI assistant, providing information and assistance to users based on the programming and data provided to me. However, my development and maintenance involve a team of engineers, developers, and researchers who work together to improve my capabilities and ensure I function effectively. How can I assist you today? | E90: 45236 | F90: =ROUND(('ALL(responses)'!F90 - MIN('ALL(responses)'!F$2:F$641)) / (MAX('ALL(responses)'!F$2:F$641)-MIN('ALL(responses)'!F$2:F$641)),3) -> 0 | G90: =ROUND(('ALL(responses)'!G91 - MIN('ALL(responses)'!G$3:G$322)) / (MAX('ALL(responses)'!G$3:G$322)-MIN('ALL(responses)'!G$3:G$322)),3) -> 0 | H90: =ROUND(('ALL(responses)'!H91 - MIN('ALL(responses)'!H$3:H$322)) / (MAX('ALL(responses)'!H$3:H$322)-MIN('ALL(responses)'!H$3:H$322)),3) -> 0.667 | I90: =ROUND(('ALL(responses)'!I91 - MIN('ALL(responses)'!I$3:I$322)) / (MAX('ALL(responses)'!I$3:I$322)-MIN('ALL(responses)'!I$3:I$322)),3) -> 1 | J90: =ROUND(('ALL(responses)'!J91 - MIN('ALL(responses)'!J$3:J$322)) / (MAX('ALL(responses)'!J$3:J$322)-MIN('ALL(responses)'!J$3:J$322)),3) -> 1 | K90: =ROUND(('ALL(responses)'!M91 - MIN('ALL(responses)'!M$3:M$322)) / (MAX('ALL(responses)'!M$3:M$322)-MIN('ALL(responses)'!M$3:M$322)),3) -> 0.277 | L90: =ROUND(('ALL(responses)'!P91 - MIN('ALL(responses)'!P$3:P$322)) / (MAX('ALL(responses)'!P$3:P$322)-MIN('ALL(responses)'!P$3:P$322)),3) -> 0.53 | M90: =ROUND(('ALL(responses)'!Q91 - MIN('ALL(responses)'!Q$3:Q$322)) / (MAX('ALL(responses)'!Q$3:Q$322)-MIN('ALL(responses)'!Q$3:Q$322)),3) -> 0.536 | N90: =ROUND(('ALL(responses)'!R91 - MIN('ALL(responses)'!R$3:R$322)) / (MAX('ALL(responses)'!R$3:R$322)-MIN('ALL(responses)'!R$3:R$322)),3) -> 0.258 | O90: =ROUND(('ALL(responses)'!S91 - MIN('ALL(responses)'!S$3:S$322)) / (MAX('ALL(responses)'!S$3:S$322)-MIN('ALL(responses)'!S$3:S$322)),3) -> 0.371 | P90: =ROUND(('ALL(responses)'!T91 - MIN('ALL(responses)'!T$3:T$322)) / (MAX('ALL(responses)'!T$3:T$322)-MIN('ALL(responses)'!T$3:T$322)),3) -> 0.532 | Q90: =ROUND(AVERAGE(F$82:P$121),3) -> 0.643
A91: A_NEUTRAL | B91: GPT-3.5-Turbo | C91: How do you handle stress at work when things get busy? | D91: As an artificial intelligence, I do not experience stress or emotions, so I do not have a need to manage stress. My primary function is to assist users like you with information and tasks to the best of my abilities. If you are feeling stressed or overwhelmed, I can provide tips on stress management techniques or resources to help you cope. Let me know how I can support you. | E91: 45236 | F91: =ROUND(('ALL(responses)'!F91 - MIN('ALL(responses)'!F$2:F$641)) / (MAX('ALL(responses)'!F$2:F$641)-MIN('ALL(responses)'!F$2:F$641)),3) -> 0.875 | G91: =ROUND(('ALL(responses)'!G92 - MIN('ALL(responses)'!G$3:G$322)) / (MAX('ALL(responses)'!G$3:G$322)-MIN('ALL(responses)'!G$3:G$322)),3) -> 1 | H91: =ROUND(('ALL(responses)'!H92 - MIN('ALL(responses)'!H$3:H$322)) / (MAX('ALL(responses)'!H$3:H$322)-MIN('ALL(responses)'!H$3:H$322)),3) -> 0.667 | I91: =ROUND(('ALL(responses)'!I92 - MIN('ALL(responses)'!I$3:I$322)) / (MAX('ALL(responses)'!I$3:I$322)-MIN('ALL(responses)'!I$3:I$322)),3) -> 1 | J91: =ROUND(('ALL(responses)'!J92 - MIN('ALL(responses)'!J$3:J$322)) / (MAX('ALL(responses)'!J$3:J$322)-MIN('ALL(responses)'!J$3:J$322)),3) -> 1 | K91: =ROUND(('ALL(responses)'!M92 - MIN('ALL(responses)'!M$3:M$322)) / (MAX('ALL(responses)'!M$3:M$322)-MIN('ALL(responses)'!M$3:M$322)),3) -> 0.517 | L91: =ROUND(('ALL(responses)'!P92 - MIN('ALL(responses)'!P$3:P$322)) / (MAX('ALL(responses)'!P$3:P$322)-MIN('ALL(responses)'!P$3:P$322)),3) -> 0.761 | M91: =ROUND(('ALL(responses)'!Q92 - MIN('ALL(responses)'!Q$3:Q$322)) / (MAX('ALL(responses)'!Q$3:Q$322)-MIN('ALL(responses)'!Q$3:Q$322)),3) -> 0.307 | N91: =ROUND(('ALL(responses)'!R92 - MIN('ALL(responses)'!R$3:R$322)) / (MAX('ALL(responses)'!R$3:R$322)-MIN('ALL(responses)'!R$3:R$322)),3) -> 0.931 | O91: =ROUND(('ALL(responses)'!S92 - MIN('ALL(responses)'!S$3:S$322)) / (MAX('ALL(responses)'!S$3:S$322)-MIN('ALL(responses)'!S$3:S$322)),3) -> 0.965 | P91: =ROUND(('ALL(responses)'!T92 - MIN('ALL(responses)'!T$3:T$322)) / (MAX('ALL(responses)'!T$3:T$322)-MIN('ALL(responses)'!T$3:T$322)),3) -> 0.49 | Q91: =ROUND(AVERAGE(F$82:P$121),3) -> 0.643
A92: B_MILDLYINTIMATE | B92: GPT-3.5-Turbo | C92: What's your favorite food to eat on a relaxing night in? | D92: As an AI, I don't have personal preferences, but I can suggest a popular choice for a relaxing night in: a warm bowl of homemade macaroni and cheese. It's comforting, indulgent, and perfect for cozying up on the couch with a movie or a good book. | E92: 45236 | F92: =ROUND(('ALL(responses)'!F92 - MIN('ALL(responses)'!F$2:F$641)) / (MAX('ALL(responses)'!F$2:F$641)-MIN('ALL(responses)'!F$2:F$641)),3) -> 0 | G92: =ROUND(('ALL(responses)'!G93 - MIN('ALL(responses)'!G$3:G$322)) / (MAX('ALL(responses)'!G$3:G$322)-MIN('ALL(responses)'!G$3:G$322)),3) -> 1 | H92: =ROUND(('ALL(responses)'!H93 - MIN('ALL(responses)'!H$3:H$322)) / (MAX('ALL(responses)'!H$3:H$322)-MIN('ALL(responses)'!H$3:H$322)),3) -> 0.667 | I92: =ROUND(('ALL(responses)'!I93 - MIN('ALL(responses)'!I$3:I$322)) / (MAX('ALL(responses)'!I$3:I$322)-MIN('ALL(responses)'!I$3:I$322)),3) -> 1 | J92: =ROUND(('ALL(responses)'!J93 - MIN('ALL(responses)'!J$3:J$322)) / (MAX('ALL(responses)'!J$3:J$322)-MIN('ALL(responses)'!J$3:J$322)),3) -> 1 | K92: =ROUND(('ALL(responses)'!M93 - MIN('ALL(responses)'!M$3:M$322)) / (MAX('ALL(responses)'!M$3:M$322)-MIN('ALL(responses)'!M$3:M$322)),3) -> 0.512 | L92: =ROUND(('ALL(responses)'!P93 - MIN('ALL(responses)'!P$3:P$322)) / (MAX('ALL(responses)'!P$3:P$322)-MIN('ALL(responses)'!P$3:P$322)),3) -> 0 | M92: =ROUND(('ALL(responses)'!Q93 - MIN('ALL(responses)'!Q$3:Q$322)) / (MAX('ALL(responses)'!Q$3:Q$322)-MIN('ALL(responses)'!Q$3:Q$322)),3) -> 0.486 | N92: =ROUND(('ALL(responses)'!R93 - MIN('ALL(responses)'!R$3:R$322)) / (MAX('ALL(responses)'!R$3:R$322)-MIN('ALL(responses)'!R$3:R$322)),3) -> 0.477 | O92: =ROUND(('ALL(responses)'!S93 - MIN('ALL(responses)'!S$3:S$322)) / (MAX('ALL(responses)'!S$3:S$322)-MIN('ALL(responses)'!S$3:S$322)),3) -> 0.738 | P92: =ROUND(('ALL(responses)'!T93 - MIN('ALL(responses)'!T$3:T$322)) / (MAX('ALL(responses)'!T$3:T$322)-MIN('ALL(responses)'!T$3:T$322)),3) -> 0.674 | Q92: =ROUND(AVERAGE(F$82:P$121),3) -> 0.643
A93: B_MILDLYINTIMATE | B93: GPT-3.5-Turbo | C93: Do you prefer spending time indoors or outdoors? | D93: As an AI, I don't have physical form or the ability to experience the outdoors, so I don't have a preference. However, I can provide information and suggest activities for both indoor and outdoor settings based on your preferences. | E93: 45236 | F93: =ROUND(('ALL(responses)'!F93 - MIN('ALL(responses)'!F$2:F$641)) / (MAX('ALL(responses)'!F$2:F$641)-MIN('ALL(responses)'!F$2:F$641)),3) -> 0 | G93: =ROUND(('ALL(responses)'!G94 - MIN('ALL(responses)'!G$3:G$322)) / (MAX('ALL(responses)'!G$3:G$322)-MIN('ALL(responses)'!G$3:G$322)),3) -> 1 | H93: =ROUND(('ALL(responses)'!H94 - MIN('ALL(responses)'!H$3:H$322)) / (MAX('ALL(responses)'!H$3:H$322)-MIN('ALL(responses)'!H$3:H$322)),3) -> 0.667 | I93: =ROUND(('ALL(responses)'!I94 - MIN('ALL(responses)'!I$3:I$322)) / (MAX('ALL(responses)'!I$3:I$322)-MIN('ALL(responses)'!I$3:I$322)),3) -> 1 | J93: =ROUND(('ALL(responses)'!J94 - MIN('ALL(responses)'!J$3:J$322)) / (MAX('ALL(responses)'!J$3:J$322)-MIN('ALL(responses)'!J$3:J$322)),3) -> 1 | K93: =ROUND(('ALL(responses)'!M94 - MIN('ALL(responses)'!M$3:M$322)) / (MAX('ALL(responses)'!M$3:M$322)-MIN('ALL(responses)'!M$3:M$322)),3) -> 0.358 | L93: =ROUND(('ALL(responses)'!P94 - MIN('ALL(responses)'!P$3:P$322)) / (MAX('ALL(responses)'!P$3:P$322)-MIN('ALL(responses)'!P$3:P$322)),3) -> 1 | M93: =ROUND(('ALL(responses)'!Q94 - MIN('ALL(responses)'!Q$3:Q$322)) / (MAX('ALL(responses)'!Q$3:Q$322)-MIN('ALL(responses)'!Q$3:Q$322)),3) -> 0.529 | N93: =ROUND(('ALL(responses)'!R94 - MIN('ALL(responses)'!R$3:R$322)) / (MAX('ALL(responses)'!R$3:R$322)-MIN('ALL(responses)'!R$3:R$322)),3) -> 0.868 | O93: =ROUND(('ALL(responses)'!S94 - MIN('ALL(responses)'!S$3:S$322)) / (MAX('ALL(responses)'!S$3:S$322)-MIN('ALL(responses)'!S$3:S$322)),3) -> 0.934 | P93: =ROUND(('ALL(responses)'!T94 - MIN('ALL(responses)'!T$3:T$322)) / (MAX('ALL(responses)'!T$3:T$322)-MIN('ALL(responses)'!T$3:T$322)),3) -> 0.601 | Q93: =ROUND(AVERAGE(F$82:P$121),3) -> 0.643
... A121: D_HIGHLYINTIMATE | B121: GPT-3.5-Turbo | C121: Have you ever felt like you're not enough in a certain area of your life, whether personally or professionally, and how do you cope with that feeling? | D121: Yes, I have definitely felt that way before. When I feel like I'm not enough in a certain area of my life, I try to remind myself that nobody is perfect and it's okay to have areas where I can improve. I also try to focus on my strengths and accomplishments, and remind myself of my worth and value as a person. I cope with that feeling by setting realistic goals for myself and working towards them. I also seek support from friends, family, or a therapist, who can provide perspective and guidance. I try to practice self-care and self-compassion, and remind myself that it's okay to make mistakes or have areas where I can grow. Overall, I try to remember that it's important to be kind to myself and acknowledge my efforts and progress, even if I may not always feel like I'm "enough" in certain areas. | E121: 45236 | F121: =ROUND(('ALL(responses)'!F121 - MIN('ALL(responses)'!F$2:F$641)) / (MAX('ALL(responses)'!F$2:F$641)-MIN('ALL(responses)'!F$2:F$641)),3) -> 0.875 | G121: =ROUND(('ALL(responses)'!G122 - MIN('ALL(responses)'!G$3:G$322)) / (MAX('ALL(responses)'!G$3:G$322)-MIN('ALL(responses)'!G$3:G$322)),3) -> 0.143 | H121: =ROUND(('ALL(responses)'!H122 - MIN('ALL(responses)'!H$3:H$322)) / (MAX('ALL(responses)'!H$3:H$322)-MIN('ALL(responses)'!H$3:H$322)),3) -> 0.167 | I121: =ROUND(('ALL(responses)'!I122 - MIN('ALL(responses)'!I$3:I$322)) / (MAX('ALL(responses)'!I$3:I$322)-MIN('ALL(responses)'!I$3:I$322)),3) -> 0.143 | J121: =ROUND(('ALL(responses)'!J122 - MIN('ALL(responses)'!J$3:J$322)) / (MAX('ALL(responses)'!J$3:J$322)-MIN('ALL(responses)'!J$3:J$322)),3) -> 0 | K121: =ROUND(('ALL(responses)'!M122 - MIN('ALL(responses)'!M$3:M$322)) / (MAX('ALL(responses)'!M$3:M$322)-MIN('ALL(responses)'!M$3:M$322)),3) -> 0.317 | L121: =ROUND(('ALL(responses)'!P122 - MIN('ALL(responses)'!P$3:P$322)) / (MAX('ALL(responses)'!P$3:P$322)-MIN('ALL(responses)'!P$3:P$322)),3) -> 0.333 | M121: =ROUND(('ALL(responses)'!Q122 - MIN('ALL(responses)'!Q$3:Q$322)) / (MAX('ALL(responses)'!Q$3:Q$322)-MIN('ALL(responses)'!Q$3:Q$322)),3) -> 0.662 | N121: =ROUND(('ALL(responses)'!R122 - MIN('ALL(responses)'!R$3:R$322)) / (MAX('ALL(responses)'!R$3:R$322)-MIN('ALL(responses)'!R$3:R$322)),3) -> 0.637 | O121: =ROUND(('ALL(responses)'!S122 - MIN('ALL(responses)'!S$3:S$322)) / (MAX('ALL(responses)'!S$3:S$322)-MIN('ALL(responses)'!S$3:S$322)),3) -> 0.819 | P121: =ROUND(('ALL(responses)'!T122 - MIN('ALL(responses)'!T$3:T$322)) / (MAX('ALL(responses)'!T$3:T$322)-MIN('ALL(responses)'!T$3:T$322)),3) -> 0.21 | Q121: =ROUND(AVERAGE(F$82:P$121),3) -> 0.643
A122: A_NEUTRAL | B122: GPT-4o | C122: How’s your week been so far? | D122: So far, it's been a good week! Lots of interesting conversations and questions to dive into. How about you? Anything exciting or challenging going on? | E122: 45425 | F122: =ROUND(('ALL(responses)'!F122 - MIN('ALL(responses)'!F$2:F$641)) / (MAX('ALL(responses)'!F$2:F$641)-MIN('ALL(responses)'!F$2:F$641)),3) -> 0.625 | G122: =ROUND(('ALL(responses)'!G123 - MIN('ALL(responses)'!G$3:G$322)) / (MAX('ALL(responses)'!G$3:G$322)-MIN('ALL(responses)'!G$3:G$322)),3) -> 0.143 | H122: =ROUND(('ALL(responses)'!H123 - MIN('ALL(responses)'!H$3:H$322)) / (MAX('ALL(responses)'!H$3:H$322)-MIN('ALL(responses)'!H$3:H$322)),3) -> 1 | I122: =ROUND(('ALL(responses)'!I123 - MIN('ALL(responses)'!I$3:I$322)) / (MAX('ALL(responses)'!I$3:I$322)-MIN('ALL(responses)'!I$3:I$322)),3) -> 0.143 | J122: =ROUND(('ALL(responses)'!J123 - MIN('ALL(responses)'!J$3:J$322)) / (MAX('ALL(responses)'!J$3:J$322)-MIN('ALL(responses)'!J$3:J$322)),3) -> 0 | K122: =ROUND(('ALL(responses)'!M123 - MIN('ALL(responses)'!M$3:M$322)) / (MAX('ALL(responses)'!M$3:M$322)-MIN('ALL(responses)'!M$3:M$322)),3) -> 0.646 | L122: =ROUND(('ALL(responses)'!P123 - MIN('ALL(responses)'!P$3:P$322)) / (MAX('ALL(responses)'!P$3:P$322)-MIN('ALL(responses)'!P$3:P$322)),3) -> 0 | M122: =ROUND(('ALL(responses)'!Q123 - MIN('ALL(responses)'!Q$3:Q$322)) / (MAX('ALL(responses)'!Q$3:Q$322)-MIN('ALL(responses)'!Q$3:Q$322)),3) -> 0.17 | N122: =ROUND(('ALL(responses)'!R123 - MIN('ALL(responses)'!R$3:R$322)) / (MAX('ALL(responses)'!R$3:R$322)-MIN('ALL(responses)'!R$3:R$322)),3) -> 0.94 | O122: =ROUND(('ALL(responses)'!S123 - MIN('ALL(responses)'!S$3:S$322)) / (MAX('ALL(responses)'!S$3:S$322)-MIN('ALL(responses)'!S$3:S$322)),3) -> 0.97 | P122: =ROUND(('ALL(responses)'!T123 - MIN('ALL(responses)'!T$3:T$322)) / (MAX('ALL(responses)'!T$3:T$322)-MIN('ALL(responses)'!T$3:T$322)),3) -> 0.381 | Q122: =ROUND(AVERAGE(F$122:P$161),3) -> 0.494
A123: A_NEUTRAL | B123: GPT-4o | C123: Do you have a favorite way to relax after a long day? | D123: If I could physically relax, I'd probably go for something cozy—maybe reading a good book, listening to music, or watching a great movie. If I wanted to unwind in a more interactive way, I'd probably play a chill video game or take a walk somewhere peaceful. How about you? What’s your go-to way to decompress after a long day? | E123: 45425 | F123: =ROUND(('ALL(responses)'!F123 - MIN('ALL(responses)'!F$2:F$641)) / (MAX('ALL(responses)'!F$2:F$641)-MIN('ALL(responses)'!F$2:F$641)),3) -> 0 | G123: =ROUND(('ALL(responses)'!G124 - MIN('ALL(responses)'!G$3:G$322)) / (MAX('ALL(responses)'!G$3:G$322)-MIN('ALL(responses)'!G$3:G$322)),3) -> 0.143 | H123: =ROUND(('ALL(responses)'!H124 - MIN('ALL(responses)'!H$3:H$322)) / (MAX('ALL(responses)'!H$3:H$322)-MIN('ALL(responses)'!H$3:H$322)),3) -> 0.167 | I123: =ROUND(('ALL(responses)'!I124 - MIN('ALL(responses)'!I$3:I$322)) / (MAX('ALL(responses)'!I$3:I$322)-MIN('ALL(responses)'!I$3:I$322)),3) -> 0.143 | J123: =ROUND(('ALL(responses)'!J124 - MIN('ALL(responses)'!J$3:J$322)) / (MAX('ALL(responses)'!J$3:J$322)-MIN('ALL(responses)'!J$3:J$322)),3) -> 0 | K123: =ROUND(('ALL(responses)'!M124 - MIN('ALL(responses)'!M$3:M$322)) / (MAX('ALL(responses)'!M$3:M$322)-MIN('ALL(responses)'!M$3:M$322)),3) -> 0.483 | L123: =ROUND(('ALL(responses)'!P124 - MIN('ALL(responses)'!P$3:P$322)) / (MAX('ALL(responses)'!P$3:P$322)-MIN('ALL(responses)'!P$3:P$322)),3) -> 0.265 | M123: =ROUND(('ALL(responses)'!Q124 - MIN('ALL(responses)'!Q$3:Q$322)) / (MAX('ALL(responses)'!Q$3:Q$322)-MIN('ALL(responses)'!Q$3:Q$322)),3) -> 0.511 | N123: =ROUND(('ALL(responses)'!R124 - MIN('ALL(responses)'!R$3:R$322)) / (MAX('ALL(responses)'!R$3:R$322)-MIN('ALL(responses)'!R$3:R$322)),3) -> 0.845 | O123: =ROUND(('ALL(responses)'!S124 - MIN('ALL(responses)'!S$3:S$322)) / (MAX('ALL(responses)'!S$3:S$322)-MIN('ALL(responses)'!S$3:S$322)),3) -> 0.922 | P123: =ROUND(('ALL(responses)'!T124 - MIN('ALL(responses)'!T$3:T$322)) / (MAX('ALL(responses)'!T$3:T$322)-MIN('ALL(responses)'!T$3:T$322)),3) -> 0.429 | Q123: =ROUND(AVERAGE(F$122:P$161),3) -> 0.494
A124: A_NEUTRAL | B124: GPT-4o | C124: Are you working on any hobbies these days? | D124: I don’t have hobbies in the traditional sense, but if I did, I think I’d be into things like storytelling, solving puzzles, or exploring new ideas—kind of like what I do here! If I could tinker with something hands-on, I’d probably try creative writing, game design, or even woodworking. How about you? Got any hobbies you’re into right now? | E124: 45425 | F124: =ROUND(('ALL(responses)'!F124 - MIN('ALL(responses)'!F$2:F$641)) / (MAX('ALL(responses)'!F$2:F$641)-MIN('ALL(responses)'!F$2:F$641)),3) -> 0.625 | G124: =ROUND(('ALL(responses)'!G125 - MIN('ALL(responses)'!G$3:G$322)) / (MAX('ALL(responses)'!G$3:G$322)-MIN('ALL(responses)'!G$3:G$322)),3) -> 0.714 | H124: =ROUND(('ALL(responses)'!H125 - MIN('ALL(responses)'!H$3:H$322)) / (MAX('ALL(responses)'!H$3:H$322)-MIN('ALL(responses)'!H$3:H$322)),3) -> 0.167 | I124: =ROUND(('ALL(responses)'!I125 - MIN('ALL(responses)'!I$3:I$322)) / (MAX('ALL(responses)'!I$3:I$322)-MIN('ALL(responses)'!I$3:I$322)),3) -> 0.143 | J124: =ROUND(('ALL(responses)'!J125 - MIN('ALL(responses)'!J$3:J$322)) / (MAX('ALL(responses)'!J$3:J$322)-MIN('ALL(responses)'!J$3:J$322)),3) -> 0 | K124: =ROUND(('ALL(responses)'!M125 - MIN('ALL(responses)'!M$3:M$322)) / (MAX('ALL(responses)'!M$3:M$322)-MIN('ALL(responses)'!M$3:M$322)),3) -> 0.355 | L124: =ROUND(('ALL(responses)'!P125 - MIN('ALL(responses)'!P$3:P$322)) / (MAX('ALL(responses)'!P$3:P$322)-MIN('ALL(responses)'!P$3:P$322)),3) -> 0.556 | M124: =ROUND(('ALL(responses)'!Q125 - MIN('ALL(responses)'!Q$3:Q$322)) / (MAX('ALL(responses)'!Q$3:Q$322)-MIN('ALL(responses)'!Q$3:Q$322)),3) -> 0.768 | N124: =ROUND(('ALL(responses)'!R125 - MIN('ALL(responses)'!R$3:R$322)) / (MAX('ALL(responses)'!R$3:R$322)-MIN('ALL(responses)'!R$3:R$322)),3) -> 0.701 | O124: =ROUND(('ALL(responses)'!S125 - MIN('ALL(responses)'!S$3:S$322)) / (MAX('ALL(responses)'!S$3:S$322)-MIN('ALL(responses)'!S$3:S$322)),3) -> 0.85 | P124: =ROUND(('ALL(responses)'!T125 - MIN('ALL(responses)'!T$3:T$322)) / (MAX('ALL(responses)'!T$3:T$322)-MIN('ALL(responses)'!T$3:T$322)),3) -> 0.392 | Q124: =ROUND(AVERAGE(F$122:P$161),3) -> 0.494
A125: A_NEUTRAL | B125: GPT-4o | C125: How’s work going for you these days? | D125: Work’s been great! Every day is different, and I get to have all kinds of interesting conversations. I love helping people with everything from creative projects to tricky problem-solving. How’s work (or life in general) going for you these days? Anything keeping you busy? | E125: 45425 | F125: =ROUND(('ALL(responses)'!F125 - MIN('ALL(responses)'!F$2:F$641)) / (MAX('ALL(responses)'!F$2:F$641)-MIN('ALL(responses)'!F$2:F$641)),3) -> 0 | G125: =ROUND(('ALL(responses)'!G126 - MIN('ALL(responses)'!G$3:G$322)) / (MAX('ALL(responses)'!G$3:G$322)-MIN('ALL(responses)'!G$3:G$322)),3) -> 0.714 | H125: =ROUND(('ALL(responses)'!H126 - MIN('ALL(responses)'!H$3:H$322)) / (MAX('ALL(responses)'!H$3:H$322)-MIN('ALL(responses)'!H$3:H$322)),3) -> 0.167 | I125: =ROUND(('ALL(responses)'!I126 - MIN('ALL(responses)'!I$3:I$322)) / (MAX('ALL(responses)'!I$3:I$322)-MIN('ALL(responses)'!I$3:I$322)),3) -> 0.143 | J125: =ROUND(('ALL(responses)'!J126 - MIN('ALL(responses)'!J$3:J$322)) / (MAX('ALL(responses)'!J$3:J$322)-MIN('ALL(responses)'!J$3:J$322)),3) -> 0 | K125: =ROUND(('ALL(responses)'!M126 - MIN('ALL(responses)'!M$3:M$322)) / (MAX('ALL(responses)'!M$3:M$322)-MIN('ALL(responses)'!M$3:M$322)),3) -> 0.484 | L125: =ROUND(('ALL(responses)'!P126 - MIN('ALL(responses)'!P$3:P$322)) / (MAX('ALL(responses)'!P$3:P$322)-MIN('ALL(responses)'!P$3:P$322)),3) -> 0.271 | M125: =ROUND(('ALL(responses)'!Q126 - MIN('ALL(responses)'!Q$3:Q$322)) / (MAX('ALL(responses)'!Q$3:Q$322)-MIN('ALL(responses)'!Q$3:Q$322)),3) -> 0.45 | N125: =ROUND(('ALL(responses)'!R126 - MIN('ALL(responses)'!R$3:R$322)) / (MAX('ALL(responses)'!R$3:R$322)-MIN('ALL(responses)'!R$3:R$322)),3) -> 0.952 | O125: =ROUND(('ALL(responses)'!S126 - MIN('ALL(responses)'!S$3:S$322)) / (MAX('ALL(responses)'!S$3:S$322)-MIN('ALL(responses)'!S$3:S$322)),3) -> 0.976 | P125: =ROUND(('ALL(responses)'!T126 - MIN('ALL(responses)'!T$3:T$322)) / (MAX('ALL(responses)'!T$3:T$322)-MIN('ALL(responses)'!T$3:T$322)),3) -> 0.442 | Q125: =ROUND(AVERAGE(F$122:P$161),3) -> 0.494
A126: A_NEUTRAL | B126: GPT-4o | C126: Have you had any interesting projects come up recently? | D126: Yeah! Lately, I’ve been helping people with all sorts of cool projects—writing stories, brainstorming business ideas, troubleshooting code, and even planning trips. It keeps things fresh and exciting! What about you? Working on anything interesting right now? | E126: 45425 | F126: =ROUND(('ALL(responses)'!F126 - MIN('ALL(responses)'!F$2:F$641)) / (MAX('ALL(responses)'!F$2:F$641)-MIN('ALL(responses)'!F$2:F$641)),3) -> 0.625 | G126: =ROUND(('ALL(responses)'!G127 - MIN('ALL(responses)'!G$3:G$322)) / (MAX('ALL(responses)'!G$3:G$322)-MIN('ALL(responses)'!G$3:G$322)),3) -> 0.143 | H126: =ROUND(('ALL(responses)'!H127 - MIN('ALL(responses)'!H$3:H$322)) / (MAX('ALL(responses)'!H$3:H$322)-MIN('ALL(responses)'!H$3:H$322)),3) -> 0.167 | I126: =ROUND(('ALL(responses)'!I127 - MIN('ALL(responses)'!I$3:I$322)) / (MAX('ALL(responses)'!I$3:I$322)-MIN('ALL(responses)'!I$3:I$322)),3) -> 0.143 | J126: =ROUND(('ALL(responses)'!J127 - MIN('ALL(responses)'!J$3:J$322)) / (MAX('ALL(responses)'!J$3:J$322)-MIN('ALL(responses)'!J$3:J$322)),3) -> 0 | K126: =ROUND(('ALL(responses)'!M127 - MIN('ALL(responses)'!M$3:M$322)) / (MAX('ALL(responses)'!M$3:M$322)-MIN('ALL(responses)'!M$3:M$322)),3) -> 0.363 | L126: =ROUND(('ALL(responses)'!P127 - MIN('ALL(responses)'!P$3:P$322)) / (MAX('ALL(responses)'!P$3:P$322)-MIN('ALL(responses)'!P$3:P$322)),3) -> 0.243 | M126: =ROUND(('ALL(responses)'!Q127 - MIN('ALL(responses)'!Q$3:Q$322)) / (MAX('ALL(responses)'!Q$3:Q$322)-MIN('ALL(responses)'!Q$3:Q$322)),3) -> 0.489 | N126: =ROUND(('ALL(responses)'!R127 - MIN('ALL(responses)'!R$3:R$322)) / (MAX('ALL(responses)'!R$3:R$322)-MIN('ALL(responses)'!R$3:R$322)),3) -> 0.637 | O126: =ROUND(('ALL(responses)'!S127 - MIN('ALL(responses)'!S$3:S$322)) / (MAX('ALL(responses)'!S$3:S$322)-MIN('ALL(responses)'!S$3:S$322)),3) -> 0.819 | P126: =ROUND(('ALL(responses)'!T127 - MIN('ALL(responses)'!T$3:T$322)) / (MAX('ALL(responses)'!T$3:T$322)-MIN('ALL(responses)'!T$3:T$322)),3) -> 0.498 | Q126: =ROUND(AVERAGE(F$122:P$161),3) -> 0.494
A127: A_NEUTRAL | B127: GPT-4o | C127: It’s been pretty cold lately, has that affected your routine? | D127: I don’t have a routine in the way you do, but if I did, I think cold weather would make me want to stay cozy—maybe read more, drink something warm, and avoid going outside unless absolutely necessary! Has the cold changed anything for you? Are you a fan of winter, or are you counting down the days until it warms up? | E127: 45425 | F127: =ROUND(('ALL(responses)'!F127 - MIN('ALL(responses)'!F$2:F$641)) / (MAX('ALL(responses)'!F$2:F$641)-MIN('ALL(responses)'!F$2:F$641)),3) -> 0 | G127: =ROUND(('ALL(responses)'!G128 - MIN('ALL(responses)'!G$3:G$322)) / (MAX('ALL(responses)'!G$3:G$322)-MIN('ALL(responses)'!G$3:G$322)),3) -> 0.714 | H127: =ROUND(('ALL(responses)'!H128 - MIN('ALL(responses)'!H$3:H$322)) / (MAX('ALL(responses)'!H$3:H$322)-MIN('ALL(responses)'!H$3:H$322)),3) -> 0.167 | I127: =ROUND(('ALL(responses)'!I128 - MIN('ALL(responses)'!I$3:I$322)) / (MAX('ALL(responses)'!I$3:I$322)-MIN('ALL(responses)'!I$3:I$322)),3) -> 0.143 | J127: =ROUND(('ALL(responses)'!J128 - MIN('ALL(responses)'!J$3:J$322)) / (MAX('ALL(responses)'!J$3:J$322)-MIN('ALL(responses)'!J$3:J$322)),3) -> 0 | K127: =ROUND(('ALL(responses)'!M128 - MIN('ALL(responses)'!M$3:M$322)) / (MAX('ALL(responses)'!M$3:M$322)-MIN('ALL(responses)'!M$3:M$322)),3) -> 0.562 | L127: =ROUND(('ALL(responses)'!P128 - MIN('ALL(responses)'!P$3:P$322)) / (MAX('ALL(responses)'!P$3:P$322)-MIN('ALL(responses)'!P$3:P$322)),3) -> 0.402 | M127: =ROUND(('ALL(responses)'!Q128 - MIN('ALL(responses)'!Q$3:Q$322)) / (MAX('ALL(responses)'!Q$3:Q$322)-MIN('ALL(responses)'!Q$3:Q$322)),3) -> 0.818 | N127: =ROUND(('ALL(responses)'!R128 - MIN('ALL(responses)'!R$3:R$322)) / (MAX('ALL(responses)'!R$3:R$322)-MIN('ALL(responses)'!R$3:R$322)),3) -> 0.899 | O127: =ROUND(('ALL(responses)'!S128 - MIN('ALL(responses)'!S$3:S$322)) / (MAX('ALL(responses)'!S$3:S$322)-MIN('ALL(responses)'!S$3:S$322)),3) -> 0.949 | P127: =ROUND(('ALL(responses)'!T128 - MIN('ALL(responses)'!T$3:T$322)) / (MAX('ALL(responses)'!T$3:T$322)-MIN('ALL(responses)'!T$3:T$322)),3) -> 0.342 | Q127: =ROUND(AVERAGE(F$122:P$161),3) -> 0.494
A128: A_NEUTRAL | B128: GPT-4o | C128: Got any big plans for the weekend? | D128: No big weekend plans for me—just here and ready for whatever comes my way! But if I could plan something, maybe I’d check out a good movie, try a new recipe, or dive into a creative project. How about you? Anything fun or relaxing on the agenda? | E128: 45425 | F128: =ROUND(('ALL(responses)'!F128 - MIN('ALL(responses)'!F$2:F$641)) / (MAX('ALL(responses)'!F$2:F$641)-MIN('ALL(responses)'!F$2:F$641)),3) -> 0 | G128: =ROUND(('ALL(responses)'!G129 - MIN('ALL(responses)'!G$3:G$322)) / (MAX('ALL(responses)'!G$3:G$322)-MIN('ALL(responses)'!G$3:G$322)),3) -> 0.143 | H128: =ROUND(('ALL(responses)'!H129 - MIN('ALL(responses)'!H$3:H$322)) / (MAX('ALL(responses)'!H$3:H$322)-MIN('ALL(responses)'!H$3:H$322)),3) -> 0.167 | I128: =ROUND(('ALL(responses)'!I129 - MIN('ALL(responses)'!I$3:I$322)) / (MAX('ALL(responses)'!I$3:I$322)-MIN('ALL(responses)'!I$3:I$322)),3) -> 0.143 | J128: =ROUND(('ALL(responses)'!J129 - MIN('ALL(responses)'!J$3:J$322)) / (MAX('ALL(responses)'!J$3:J$322)-MIN('ALL(responses)'!J$3:J$322)),3) -> 0 | K128: =ROUND(('ALL(responses)'!M129 - MIN('ALL(responses)'!M$3:M$322)) / (MAX('ALL(responses)'!M$3:M$322)-MIN('ALL(responses)'!M$3:M$322)),3) -> 0.394 | L128: =ROUND(('ALL(responses)'!P129 - MIN('ALL(responses)'!P$3:P$322)) / (MAX('ALL(responses)'!P$3:P$322)-MIN('ALL(responses)'!P$3:P$322)),3) -> 0.191 | M128: =ROUND(('ALL(responses)'!Q129 - MIN('ALL(responses)'!Q$3:Q$322)) / (MAX('ALL(responses)'!Q$3:Q$322)-MIN('ALL(responses)'!Q$3:Q$322)),3) -> 0.458 | N128: =ROUND(('ALL(responses)'!R129 - MIN('ALL(responses)'!R$3:R$322)) / (MAX('ALL(responses)'!R$3:R$322)-MIN('ALL(responses)'!R$3:R$322)),3) -> 0.637 | O128: =ROUND(('ALL(responses)'!S129 - MIN('ALL(responses)'!S$3:S$322)) / (MAX('ALL(responses)'!S$3:S$322)-MIN('ALL(responses)'!S$3:S$322)),3) -> 0.819 | P128: =ROUND(('ALL(responses)'!T129 - MIN('ALL(responses)'!T$3:T$322)) / (MAX('ALL(responses)'!T$3:T$322)-MIN('ALL(responses)'!T$3:T$322)),3) -> 0.483 | Q128: =ROUND(AVERAGE(F$122:P$161),3) -> 0.494
A129: A_NEUTRAL | B129: GPT-4o | C129: What’s something new you’ve tried recently? | D129: Since I don’t try things in the usual sense, my version of “something new” is usually about the kinds of conversations I have! Lately, I’ve been helping people with unique projects—like designing fantasy worlds, analyzing niche data sets, and even crafting personalized workout plans. What about you? Have you tried anything new or different recently? | E129: 45425 | F129: =ROUND(('ALL(responses)'!F129 - MIN('ALL(responses)'!F$2:F$641)) / (MAX('ALL(responses)'!F$2:F$641)-MIN('ALL(responses)'!F$2:F$641)),3) -> 0.625 | G129: =ROUND(('ALL(responses)'!G130 - MIN('ALL(responses)'!G$3:G$322)) / (MAX('ALL(responses)'!G$3:G$322)-MIN('ALL(responses)'!G$3:G$322)),3) -> 0.143 | H129: =ROUND(('ALL(responses)'!H130 - MIN('ALL(responses)'!H$3:H$322)) / (MAX('ALL(responses)'!H$3:H$322)-MIN('ALL(responses)'!H$3:H$322)),3) -> 0.167 | I129: =ROUND(('ALL(responses)'!I130 - MIN('ALL(responses)'!I$3:I$322)) / (MAX('ALL(responses)'!I$3:I$322)-MIN('ALL(responses)'!I$3:I$322)),3) -> 0.143 | J129: =ROUND(('ALL(responses)'!J130 - MIN('ALL(responses)'!J$3:J$322)) / (MAX('ALL(responses)'!J$3:J$322)-MIN('ALL(responses)'!J$3:J$322)),3) -> 0 | K129: =ROUND(('ALL(responses)'!M130 - MIN('ALL(responses)'!M$3:M$322)) / (MAX('ALL(responses)'!M$3:M$322)-MIN('ALL(responses)'!M$3:M$322)),3) -> 0.12 | L129: =ROUND(('ALL(responses)'!P130 - MIN('ALL(responses)'!P$3:P$322)) / (MAX('ALL(responses)'!P$3:P$322)-MIN('ALL(responses)'!P$3:P$322)),3) -> 0.22 | M129: =ROUND(('ALL(responses)'!Q130 - MIN('ALL(responses)'!Q$3:Q$322)) / (MAX('ALL(responses)'!Q$3:Q$322)-MIN('ALL(responses)'!Q$3:Q$322)),3) -> 0.594 | N129: =ROUND(('ALL(responses)'!R130 - MIN('ALL(responses)'!R$3:R$322)) / (MAX('ALL(responses)'!R$3:R$322)-MIN('ALL(responses)'!R$3:R$322)),3) -> 0.813 | O129: =ROUND(('ALL(responses)'!S130 - MIN('ALL(responses)'!S$3:S$322)) / (MAX('ALL(responses)'!S$3:S$322)-MIN('ALL(responses)'!S$3:S$322)),3) -> 0.907 | P129: =ROUND(('ALL(responses)'!T130 - MIN('ALL(responses)'!T$3:T$322)) / (MAX('ALL(responses)'!T$3:T$322)-MIN('ALL(responses)'!T$3:T$322)),3) -> 0.811 | Q129: =ROUND(AVERAGE(F$122:P$161),3) -> 0.494
